Workbook

Sheet 00_README
A1: DeciBridge Economic Validation Model | B1: DeciBridge Economic Validation Model | C1: DeciBridge Economic Validation Model | D1: DeciBridge Economic Validation Model | E1: DeciBridge Economic Validation Model | F1: DeciBridge Economic Validation Model | G1: DeciBridge Economic Validation Model | H1: DeciBridge Economic Validation Model
A2: Gold-standard test workbook for HF_ARNI_ACEI_001; not a final RS Unud HTA decision model. | B2: Gold-standard test workbook for HF_ARNI_ACEI_001; not a final RS Unud HTA decision model. | C2: Gold-standard test workbook for HF_ARNI_ACEI_001; not a final RS Unud HTA decision model. | D2: Gold-standard test workbook for HF_ARNI_ACEI_001; not a final RS Unud HTA decision model. | E2: Gold-standard test workbook for HF_ARNI_ACEI_001; not a final RS Unud HTA decision model. | F2: Gold-standard test workbook for HF_ARNI_ACEI_001; not a final RS Unud HTA decision model. | G2: Gold-standard test workbook for HF_ARNI_ACEI_001; not a final RS Unud HTA decision model. | H2: Gold-standard test workbook for HF_ARNI_ACEI_001; not a final RS Unud HTA decision model.
A4: Purpose and status | B4: Purpose and status | C4: Purpose and status | D4: Purpose and status | E4: Purpose and status | F4: Purpose and status | G4: Purpose and status | H4: Purpose and status
A5: Item | B5: Description
A6: Primary use | B6: Validate DeciBridge calculations for total costs, QALYs, incremental outcomes, ICER, INB/NMB, discounting, BIA, PSA, CE plane, and CEAC.
A7: Case | B7: HF_ARNI_ACEI_001 – Sacubitril/valsartan versus ACE inhibitor.
A8: Model type | B8: Annual decision model with repeated annual values; editable horizon 1–5 years.
A9: Status | B9: SYSTEM-TEST MODEL / ILLUSTRATIVE ASSUMPTIONS – not for final formulary decision.
A10: PSA | B10: 1,000 fixed-uniform simulations (seed 20260724). Dynamic mode follows updated inputs while retaining reproducibility.
A11: Yellow cells | B11: Editable inputs/assumptions.
A12: Blue cells | B12: Calculated cells/formulas.
A14: Model equations | B14: Model equations | C14: Model equations | D14: Model equations | E14: Model equations | F14: Model equations | G14: Model equations | H14: Model equations
A15: Output | B15: Equation
A16: Annual total cost | B16: Annual medicine cost + (rehospitalization probability × HF admission cost) + annual monitoring cost
A17: Annual QALY | B17: Stable-state utility − (rehospitalization probability × QALY loss per admission)
A18: Discounted cost | B18: Annual cost ÷ (1 + cost discount rate)^(year − 1)
A19: Discounted QALY | B19: Annual QALY ÷ (1 + outcome discount rate)^(year − 1)
A20: ICER | B20: (Cost ARNI − Cost ACEI) ÷ (QALY ARNI − QALY ACEI)
A21: INB | B21: (WTP × incremental QALY) − incremental cost
A22: CEAC | B22: Proportion of PSA simulations with positive INB at each WTP threshold
A24: Important limitations | B24: Important limitations | C24: Important limitations | D24: Important limitations | E24: Important limitations | F24: Important limitations | G24: Important limitations | H24: Important limitations
A25: QALY inputs were not available in the uploaded files; utility and QALY loss are explicitly illustrative and editable.
A26: Select Baseline validation to reproduce the original test case, or Dynamic fixed-seed to make PSA and CEAC follow current inputs.
A27: The 12-month RWE rehospitalization proportions are reused for each active model year if the horizon is increased beyond one year.
A28: Mortality, adverse events, treatment discontinuation, and state transitions are not modeled in this test workbook.
A29: All proxy costs must be replaced with validated RS Unud data before policy use.

Sheet 01_INPUTS
A1: Model Inputs – ARNI versus ACEI | B1: Model Inputs – ARNI versus ACEI | C1: Model Inputs – ARNI versus ACEI | D1: Model Inputs – ARNI versus ACEI | E1: Model Inputs – ARNI versus ACEI | F1: Model Inputs – ARNI versus ACEI
A2: Yellow cells are editable. Source status distinguishes observed, proxy, and illustrative assumptions. | B2: Yellow cells are editable. Source status distinguishes observed, proxy, and illustrative assumptions. | C2: Yellow cells are editable. Source status distinguishes observed, proxy, and illustrative assumptions. | D2: Yellow cells are editable. Source status distinguishes observed, proxy, and illustrative assumptions. | E2: Yellow cells are editable. Source status distinguishes observed, proxy, and illustrative assumptions. | F2: Yellow cells are editable. Source status distinguishes observed, proxy, and illustrative assumptions.
A4: Parameter | B4: Base value | C4: Unit | D4: Status | E4: Source | F4: Notes
A5: Case ID | B5: HF_ARNI_ACEI_001 | C5: text | D5: Observed | E5: Uploaded DeciBridge files | F5: Must match across all imported tables.
A6: Time horizon | B6: 1 | C6: years | D6: Test setting | E6: User-defined | F6: Allowed range: 1–5 years.
A7: Cost discount rate | B7: 0.03 | C7: annual proportion | D7: Illustrative | E7: Editable test assumption | F7: Year 1 is not discounted; later years are discounted.
A8: Outcome discount rate | B8: 0.03 | C8: annual proportion | D8: Illustrative | E8: Editable test assumption | F8: Year 1 is not discounted; later years are discounted.
A9: WTP threshold | B9: 85000000 | C9: IDR/QALY | D9: Illustrative | E9: Editable test assumption | F9: Not an official Indonesian threshold.
A10: ARNI rehospitalization probability | B10: 0.45 | C10: annual proportion | D10: Observed RWE | E10: Casepack: 18/40 | F10: 12-month rehospitalization.
A11: ACEI rehospitalization probability | B11: 0.7077 | C11: annual proportion | D11: Observed RWE | E11: Casepack: 46/65 | F11: 12-month rehospitalization.
A12: ARNI median LOS | B12: 4 | C12: days/admission | D12: Observed RWE | E12: Casepack | F12: Secondary clinical validation field.
A13: ACEI median LOS | B13: 5 | C13: days/admission | D13: Observed RWE | E13: Casepack | F13: Secondary clinical validation field.
A14: ARNI annual medicine cost | B14: 15399360 | C14: IDR/patient-year | D14: Proxy | E14: Template: 01_Harga_Obat | F14: Rp21,388/tablet × 60/month × 12.
A15: ACEI annual medicine cost | B15: 324000 | C15: IDR/patient-year | D15: Proxy | E15: Template: 01_Harga_Obat | F15: Rp450/tablet × 60/month × 12.
A16: HF admission cost – base case | B16: 6889093 | C16: IDR/admission | D16: Proxy | E16: Casepack: Biaya Tabanan.xlsx | F16: Median proxy; not RS Unud final.
A17: HF admission cost – alternative | B17: 9105003 | C17: IDR/admission | D17: Proxy | E17: Template: Jogja Hospital 2023 | F17: Mean proxy for scenario checking.
... A27: PSA seed | B27: 20260724 | C27: integer | D27: Fixed | E27: Model specification | F27: Ensures reproducible expected results.
A28: PSA mode | B28: Dynamic fixed-seed | C28: selection | D28: User control | E28: Dropdown | F28: Dynamic follows current inputs; Baseline preserves original validation parameters.

Sheet 02_DETERMINISTIC
A1: Deterministic Cost-Utility Analysis | B1: Deterministic Cost-Utility Analysis | C1: Deterministic Cost-Utility Analysis | D1: Deterministic Cost-Utility Analysis | E1: Deterministic Cost-Utility Analysis | F1: Deterministic Cost-Utility Analysis | G1: Deterministic Cost-Utility Analysis | H1: Deterministic Cost-Utility Analysis | I1: Deterministic Cost-Utility Analysis | J1: Deterministic Cost-Utility Analysis
A2: Formula-driven results. Change yellow cells in 01_INPUTS; all outputs update. | B2: Formula-driven results. Change yellow cells in 01_INPUTS; all outputs update. | C2: Formula-driven results. Change yellow cells in 01_INPUTS; all outputs update. | D2: Formula-driven results. Change yellow cells in 01_INPUTS; all outputs update. | E2: Formula-driven results. Change yellow cells in 01_INPUTS; all outputs update. | F2: Formula-driven results. Change yellow cells in 01_INPUTS; all outputs update. | G2: Formula-driven results. Change yellow cells in 01_INPUTS; all outputs update. | H2: Formula-driven results. Change yellow cells in 01_INPUTS; all outputs update. | I2: Formula-driven results. Change yellow cells in 01_INPUTS; all outputs update. | J2: Formula-driven results. Change yellow cells in 01_INPUTS; all outputs update.
A4: Year | B4: Active? | C4: Cost DF | D4: QALY DF | E4: ARNI cost | F4: ACEI cost | G4: ARNI QALY | H4: ACEI QALY | I4: Incremental cost | J4: Incremental QALY
A5: 1 | B5: =IF(A5<='01_INPUTS'!B6,1,0) -> 1 | C5: =IF(B5=1,1/(1+'01_INPUTS'!B7)^(A5-1),0) -> 1 | D5: =IF(B5=1,1/(1+'01_INPUTS'!B8)^(A5-1),0) -> 1 | E5: =B5*C5*('01_INPUTS'!B14+'01_INPUTS'!B10*'01_INPUTS'!B16+'01_INPUTS'!B20) -> 18499452 | F5: =B5*C5*('01_INPUTS'!B15+'01_INPUTS'!B11*'01_INPUTS'!B16+'01_INPUTS'!B21) -> 5199411.1 | G5: =B5*D5*('01_INPUTS'!B18-'01_INPUTS'!B10*'01_INPUTS'!B19) -> 0.655 | H5: =B5*D5*('01_INPUTS'!B18-'01_INPUTS'!B11*'01_INPUTS'!B19) -> 0.62923 | I5: =E5-F5 -> 13300041 | J5: =G5-H5 -> 0.02577
A6: 2 | B6: =IF(A6<='01_INPUTS'!B6,1,0) -> 0 | C6: =IF(B6=1,1/(1+'01_INPUTS'!B7)^(A6-1),0) -> 0 | D6: =IF(B6=1,1/(1+'01_INPUTS'!B8)^(A6-1),0) -> 0 | E6: =B6*C6*('01_INPUTS'!B14+'01_INPUTS'!B10*'01_INPUTS'!B16+'01_INPUTS'!B20) -> 0 | F6: =B6*C6*('01_INPUTS'!B15+'01_INPUTS'!B11*'01_INPUTS'!B16+'01_INPUTS'!B21) -> 0 | G6: =B6*D6*('01_INPUTS'!B18-'01_INPUTS'!B10*'01_INPUTS'!B19) -> 0 | H6: =B6*D6*('01_INPUTS'!B18-'01_INPUTS'!B11*'01_INPUTS'!B19) -> 0 | I6: =E6-F6 -> 0 | J6: =G6-H6 -> 0
A7: 3 | B7: =IF(A7<='01_INPUTS'!B6,1,0) -> 0 | C7: =IF(B7=1,1/(1+'01_INPUTS'!B7)^(A7-1),0) -> 0 | D7: =IF(B7=1,1/(1+'01_INPUTS'!B8)^(A7-1),0) -> 0 | E7: =B7*C7*('01_INPUTS'!B14+'01_INPUTS'!B10*'01_INPUTS'!B16+'01_INPUTS'!B20) -> 0 | F7: =B7*C7*('01_INPUTS'!B15+'01_INPUTS'!B11*'01_INPUTS'!B16+'01_INPUTS'!B21) -> 0 | G7: =B7*D7*('01_INPUTS'!B18-'01_INPUTS'!B10*'01_INPUTS'!B19) -> 0 | H7: =B7*D7*('01_INPUTS'!B18-'01_INPUTS'!B11*'01_INPUTS'!B19) -> 0 | I7: =E7-F7 -> 0 | J7: =G7-H7 -> 0
A8: 4 | B8: =IF(A8<='01_INPUTS'!B6,1,0) -> 0 | C8: =IF(B8=1,1/(1+'01_INPUTS'!B7)^(A8-1),0) -> 0 | D8: =IF(B8=1,1/(1+'01_INPUTS'!B8)^(A8-1),0) -> 0 | E8: =B8*C8*('01_INPUTS'!B14+'01_INPUTS'!B10*'01_INPUTS'!B16+'01_INPUTS'!B20) -> 0 | F8: =B8*C8*('01_INPUTS'!B15+'01_INPUTS'!B11*'01_INPUTS'!B16+'01_INPUTS'!B21) -> 0 | G8: =B8*D8*('01_INPUTS'!B18-'01_INPUTS'!B10*'01_INPUTS'!B19) -> 0 | H8: =B8*D8*('01_INPUTS'!B18-'01_INPUTS'!B11*'01_INPUTS'!B19) -> 0 | I8: =E8-F8 -> 0 | J8: =G8-H8 -> 0
A9: 5 | B9: =IF(A9<='01_INPUTS'!B6,1,0) -> 0 | C9: =IF(B9=1,1/(1+'01_INPUTS'!B7)^(A9-1),0) -> 0 | D9: =IF(B9=1,1/(1+'01_INPUTS'!B8)^(A9-1),0) -> 0 | E9: =B9*C9*('01_INPUTS'!B14+'01_INPUTS'!B10*'01_INPUTS'!B16+'01_INPUTS'!B20) -> 0 | F9: =B9*C9*('01_INPUTS'!B15+'01_INPUTS'!B11*'01_INPUTS'!B16+'01_INPUTS'!B21) -> 0 | G9: =B9*D9*('01_INPUTS'!B18-'01_INPUTS'!B10*'01_INPUTS'!B19) -> 0 | H9: =B9*D9*('01_INPUTS'!B18-'01_INPUTS'!B11*'01_INPUTS'!B19) -> 0 | I9: =E9-F9 -> 0 | J9: =G9-H9 -> 0
A11: TOTAL | E11: =SUM(E5:E9) -> 18499452 | F11: =SUM(F5:F9) -> 5199411.1 | G11: =SUM(G5:G9) -> 0.655 | H11: =SUM(H5:H9) -> 0.62923 | I11: =SUM(I5:I9) -> 13300041 | J11: =SUM(J5:J9) -> 0.02577
A14: Economic outputs | B14: Economic outputs | C14: Economic outputs | D14: Economic outputs | F14: Clinical validation outputs | G14: Clinical validation outputs | H14: Clinical validation outputs | I14: Clinical validation outputs | J14: Clinical validation outputs
A15: Metric | B15: Value | C15: Unit | D15: Interpretation | F15: Metric | G15: Value | H15: Unit
A16: Total cost – ARNI | B16: =E11 -> 18499452 | C16: IDR/patient | D16: Discounted total | F16: Absolute rehospitalization reduction | G16: ='01_INPUTS'!B11-'01_INPUTS'!B10 -> 0.2577 | H16: proportion
A17: Total cost – ACEI | B17: =F11 -> 5199411.1 | C17: IDR/patient | D17: Discounted total | F17: Relative risk | G17: ='01_INPUTS'!B10/'01_INPUTS'!B11 -> 0.63586265 | H17: RR
A18: Total QALY – ARNI | B18: =G11 -> 0.655 | C18: QALY/patient | D18: Discounted total | F18: Relative risk reduction | G18: =1-G17 -> 0.36413735 | H18: proportion
A19: Total QALY – ACEI | B19: =H11 -> 0.62923 | C19: QALY/patient | D19: Discounted total | F19: NNT (12 months) | G19: =IF(G16=0,"NA",1/G16) -> 3.8804812 | H19: patients
A20: Incremental cost | B20: =I11 -> 13300041 | C20: IDR/patient | D20: ARNI minus ACEI | F20: LOS difference | G20: ='01_INPUTS'!B12-'01_INPUTS'!B13 -> -1 | H20: days
A21: Incremental effectiveness | B21: =J11 -> 0.02577 | C21: QALY/patient | D21: ARNI minus ACEI | F21: Admission cost saving/patient-year | G21: =G16*'01_INPUTS'!B16 -> 1775319.3 | H21: IDR
A22: ICER | B22: =IF(B21=0,"NA",B20/B21) -> 5.1610558e+08 | C22: IDR/QALY | D22: Incremental cost ÷ incremental QALY
A23: INB | B23: ='01_INPUTS'!B9*B21-B20 -> -11109591 | C23: IDR/patient | D23: Positive favors ARNI at selected WTP
A24: Decision at WTP | B24: =IF(B23>0,"Cost-effective at selected WTP","Not cost-effective at selected WTP") -> Not cost-effective at selected WTP | C24: text | D24: Based only on illustrative economic model

Sheet 03_BIA
A1: Budget Impact Scenarios | B1: Budget Impact Scenarios | C1: Budget Impact Scenarios | D1: Budget Impact Scenarios | E1: Budget Impact Scenarios | F1: Budget Impact Scenarios | G1: Budget Impact Scenarios | H1: Budget Impact Scenarios
A2: One-year budget impact for 10%, 30%, and 50% uptake; eligible population is illustrative until replaced. | B2: One-year budget impact for 10%, 30%, and 50% uptake; eligible population is illustrative until replaced. | C2: One-year budget impact for 10%, 30%, and 50% uptake; eligible population is illustrative until replaced. | D2: One-year budget impact for 10%, 30%, and 50% uptake; eligible population is illustrative until replaced. | E2: One-year budget impact for 10%, 30%, and 50% uptake; eligible population is illustrative until replaced. | F2: One-year budget impact for 10%, 30%, and 50% uptake; eligible population is illustrative until replaced. | G2: One-year budget impact for 10%, 30%, and 50% uptake; eligible population is illustrative until replaced. | H2: One-year budget impact for 10%, 30%, and 50% uptake; eligible population is illustrative until replaced.
A4: Scenario | B4: Uptake | C4: Eligible patients | D4: ARNI patients | E4: Drug-only incremental budget | F4: Admission cost offset | G4: Net budget impact | H4: Status
A5: Low | B5: ='01_INPUTS'!B23 -> 0.1 | C5: ='01_INPUTS'!B22 -> 100 | D5: =ROUND(B5*C5,0) -> 10 | E5: =D5*('01_INPUTS'!B14-'01_INPUTS'!B15) -> 150753600 | F5: =D5*('01_INPUTS'!B11-'01_INPUTS'!B10)*'01_INPUTS'!B16 -> 17753193 | G5: =E5-F5+D5*('01_INPUTS'!B20-'01_INPUTS'!B21) -> 1.3300041e+08 | H5: =IF('01_INPUTS'!B22=100,"Illustrative population","User-provided population") -> Illustrative population
A6: Medium | B6: ='01_INPUTS'!B24 -> 0.3 | C6: ='01_INPUTS'!B22 -> 100 | D6: =ROUND(B6*C6,0) -> 30 | E6: =D6*('01_INPUTS'!B14-'01_INPUTS'!B15) -> 452260800 | F6: =D6*('01_INPUTS'!B11-'01_INPUTS'!B10)*'01_INPUTS'!B16 -> 53259578 | G6: =E6-F6+D6*('01_INPUTS'!B20-'01_INPUTS'!B21) -> 3.9900122e+08 | H6: =IF('01_INPUTS'!B22=100,"Illustrative population","User-provided population") -> Illustrative population
A7: High | B7: ='01_INPUTS'!B25 -> 0.5 | C7: ='01_INPUTS'!B22 -> 100 | D7: =ROUND(B7*C7,0) -> 50 | E7: =D7*('01_INPUTS'!B14-'01_INPUTS'!B15) -> 753768000 | F7: =D7*('01_INPUTS'!B11-'01_INPUTS'!B10)*'01_INPUTS'!B16 -> 88765963 | G7: =E7-F7+D7*('01_INPUTS'!B20-'01_INPUTS'!B21) -> 6.6500204e+08 | H7: =IF('01_INPUTS'!B22=100,"Illustrative population","User-provided population") -> Illustrative population
A10: Interpretation | B10: Interpretation | C10: Interpretation | D10: Interpretation | E10: Interpretation | F10: Interpretation | G10: Interpretation | H10: Interpretation
A11: Drug-only budget impact counts medicine cost differences only.
A12: Admission cost offset uses absolute rehospitalization reduction × admission cost.
A13: Net budget impact also adds any difference in annual monitoring cost.
A14: This is a static one-year BIA; population growth, displacement, and multi-year uptake are not included.

Sheet 04_PSA_INPUTS
A1: PSA Distribution Specifications | B1: PSA Distribution Specifications | C1: PSA Distribution Specifications | D1: PSA Distribution Specifications | E1: PSA Distribution Specifications | F1: PSA Distribution Specifications | G1: PSA Distribution Specifications | H1: PSA Distribution Specifications | I1: PSA Distribution Specifications | J1: PSA Distribution Specifications
A2: Active parameters follow the selected PSA mode. Change current inputs only in 01_INPUTS. | B2: Active parameters follow the selected PSA mode. Change current inputs only in 01_INPUTS. | C2: Active parameters follow the selected PSA mode. Change current inputs only in 01_INPUTS. | D2: Active parameters follow the selected PSA mode. Change current inputs only in 01_INPUTS. | E2: Active parameters follow the selected PSA mode. Change current inputs only in 01_INPUTS. | F2: Active parameters follow the selected PSA mode. Change current inputs only in 01_INPUTS. | G2: Active parameters follow the selected PSA mode. Change current inputs only in 01_INPUTS. | H2: Active parameters follow the selected PSA mode. Change current inputs only in 01_INPUTS. | I2: Active parameters follow the selected PSA mode. Change current inputs only in 01_INPUTS. | J2: Active parameters follow the selected PSA mode. Change current inputs only in 01_INPUTS.
A4: Parameter | B4: Distribution | C4: Baseline mean | D4: Current input | E4: Active mean | F4: Uncertainty | G4: Value | H4: Alpha/shape | I4: Beta/scale | J4: Source/status
A5: ARNI rehospitalization | B5: Beta | C5: 0.45 | D5: ='01_INPUTS'!B10 -> 0.45 | E5: =IF('01_INPUTS'!B28="Baseline validation",C5,D5) -> 0.45 | F5: Effective N | G5: 40 | H5: =E5*G5+1 -> 19 | I5: =(1-E5)*G5+1 -> 23 | J5: Observed RWE; uncertainty responds to current probability
A6: ACEI rehospitalization | B6: Beta | C6: 0.7077 | D6: ='01_INPUTS'!B11 -> 0.7077 | E6: =IF('01_INPUTS'!B28="Baseline validation",C6,D6) -> 0.7077 | F6: Effective N | G6: 65 | H6: =E6*G6+1 -> 47.0005 | I6: =(1-E6)*G6+1 -> 19.9995 | J6: Observed RWE; uncertainty responds to current probability
A7: ARNI annual medicine cost | B7: Gamma | C7: 15399360 | D7: ='01_INPUTS'!B14 -> 15399360 | E7: =IF('01_INPUTS'!B28="Baseline validation",C7,D7) -> 15399360 | F7: CV | G7: 0.1 | H7: =1/(G7^2) -> 100 | I7: =E7/H7 -> 153993.6 | J7: Illustrative CV 10%
A8: ACEI annual medicine cost | B8: Gamma | C8: 324000 | D8: ='01_INPUTS'!B15 -> 324000 | E8: =IF('01_INPUTS'!B28="Baseline validation",C8,D8) -> 324000 | F8: CV | G8: 0.1 | H8: =1/(G8^2) -> 100 | I8: =E8/H8 -> 3240 | J8: Illustrative CV 10%
A9: HF admission cost | B9: Gamma | C9: 6889093 | D9: ='01_INPUTS'!B16 -> 6889093 | E9: =IF('01_INPUTS'!B28="Baseline validation",C9,D9) -> 6889093 | F9: CV | G9: 0.2 | H9: =1/(G9^2) -> 25 | I9: =E9/H9 -> 275563.72 | J9: Proxy cost; illustrative CV 20%
A10: Stable utility | B10: Beta | C10: 0.7 | D10: ='01_INPUTS'!B18 -> 0.7 | E10: =IF('01_INPUTS'!B28="Baseline validation",C10,D10) -> 0.7 | F10: SE | G10: 0.03 | H10: =E10*(E10*(1-E10)/(G10^2)-1) -> 162.63333 | I10: =(1-E10)*(E10*(1-E10)/(G10^2)-1) -> 69.7 | J10: Illustrative SE 0.03
A11: QALY loss/admission | B11: Beta | C11: 0.1 | D11: ='01_INPUTS'!B19 -> 0.1 | E11: =IF('01_INPUTS'!B28="Baseline validation",C11,D11) -> 0.1 | F11: SE | G11: 0.02 | H11: =E11*(E11*(1-E11)/(G11^2)-1) -> 22.4 | I11: =(1-E11)*(E11*(1-E11)/(G11^2)-1) -> 201.6 | J11: Illustrative SE 0.02
A14: Mode status | B14: Mode status | C14: Mode status | D14: Mode status | E14: Mode status | F14: Mode status | G14: Mode status | H14: Mode status | I14: Mode status | J14: Mode status
A15: Selected mode | B15: ='01_INPUTS'!B28 -> Dynamic fixed-seed
A16: Behavior | B16: =IF(B15="Baseline validation","Original parameters retained for dashboard regression testing","All active means follow current values in 01_INPUTS") -> All active means follow current values in 01_INPUTS

Sheet 05_PSA_1000
A1: Iteration | B1: p_rehosp_ARNI | C1: p_rehosp_ACEI | D1: DrugCost_ARNI | E1: DrugCost_ACEI | F1: AdmissionCost | G1: StableUtility | H1: QALYLossAdmission | I1: TotalCost_ARNI | J1: TotalCost_ACEI | K1: DeltaCost | L1: QALY_ARNI | M1: QALY_ACEI | N1: DeltaQALY | O1: ICER | P1: INB_at_base_WTP | Q1: CostEffective | R1: U_p_ARNI | S1: U_p_ACEI | T1: U_cost_ARNI | U1: U_cost_ACEI | V1: U_admission | W1: U_utility | X1: U_qaly_loss
A2: 1 | B2: =_xludf.BETA.INV(R2,'04_PSA_INPUTS'!H5,'04_PSA_INPUTS'!I5) -> #NAME? | C2: =_xludf.BETA.INV(S2,'04_PSA_INPUTS'!H6,'04_PSA_INPUTS'!I6) -> #NAME? | D2: =_xludf.GAMMA.INV(T2,'04_PSA_INPUTS'!H7,'04_PSA_INPUTS'!I7) -> #NAME? | E2: =_xludf.GAMMA.INV(U2,'04_PSA_INPUTS'!H8,'04_PSA_INPUTS'!I8) -> #NAME? | F2: =_xludf.GAMMA.INV(V2,'04_PSA_INPUTS'!H9,'04_PSA_INPUTS'!I9) -> #NAME? | G2: =_xludf.BETA.INV(W2,'04_PSA_INPUTS'!H10,'04_PSA_INPUTS'!I10) -> #NAME? | H2: =_xludf.BETA.INV(X2,'04_PSA_INPUTS'!H11,'04_PSA_INPUTS'!I11) -> #NAME? | I2: =D2+B2*F2+'01_INPUTS'!B20 -> #NAME? | J2: =E2+C2*F2+'01_INPUTS'!B21 -> #NAME? | K2: =I2-J2 -> #NAME? | L2: =G2-B2*H2 -> #NAME? | M2: =G2-C2*H2 -> #NAME? | N2: =L2-M2 -> #NAME? | O2: =IF(N2=0,"",K2/N2) -> #NAME? | P2: ='01_INPUTS'!B9*N2-K2 -> #NAME? | Q2: =IF(P2>0,1,0) -> #NAME? | R2: 0.59542984 | S2: 0.85337417 | T2: 0.85474902 | U2: 0.80741449 | V2: 0.97727951 | W2: 0.87234909 | X2: 0.85758323
A3: 2 | B3: =_xludf.BETA.INV(R3,'04_PSA_INPUTS'!H5,'04_PSA_INPUTS'!I5) -> #NAME? | C3: =_xludf.BETA.INV(S3,'04_PSA_INPUTS'!H6,'04_PSA_INPUTS'!I6) -> #NAME? | D3: =_xludf.GAMMA.INV(T3,'04_PSA_INPUTS'!H7,'04_PSA_INPUTS'!I7) -> #NAME? | E3: =_xludf.GAMMA.INV(U3,'04_PSA_INPUTS'!H8,'04_PSA_INPUTS'!I8) -> #NAME? | F3: =_xludf.GAMMA.INV(V3,'04_PSA_INPUTS'!H9,'04_PSA_INPUTS'!I9) -> #NAME? | G3: =_xludf.BETA.INV(W3,'04_PSA_INPUTS'!H10,'04_PSA_INPUTS'!I10) -> #NAME? | H3: =_xludf.BETA.INV(X3,'04_PSA_INPUTS'!H11,'04_PSA_INPUTS'!I11) -> #NAME? | I3: =D3+B3*F3+'01_INPUTS'!B20 -> #NAME? | J3: =E3+C3*F3+'01_INPUTS'!B21 -> #NAME? | K3: =I3-J3 -> #NAME? | L3: =G3-B3*H3 -> #NAME? | M3: =G3-C3*H3 -> #NAME? | N3: =L3-M3 -> #NAME? | O3: =IF(N3=0,"",K3/N3) -> #NAME? | P3: ='01_INPUTS'!B9*N3-K3 -> #NAME? | Q3: =IF(P3>0,1,0) -> #NAME? | R3: 0.77433389 | S3: 0.39597799 | T3: 0.40293736 | U3: 0.7103226 | V3: 0.42011354 | W3: 0.34255354 | X3: 0.26147472
A4: 3 | B4: =_xludf.BETA.INV(R4,'04_PSA_INPUTS'!H5,'04_PSA_INPUTS'!I5) -> #NAME? | C4: =_xludf.BETA.INV(S4,'04_PSA_INPUTS'!H6,'04_PSA_INPUTS'!I6) -> #NAME? | D4: =_xludf.GAMMA.INV(T4,'04_PSA_INPUTS'!H7,'04_PSA_INPUTS'!I7) -> #NAME? | E4: =_xludf.GAMMA.INV(U4,'04_PSA_INPUTS'!H8,'04_PSA_INPUTS'!I8) -> #NAME? | F4: =_xludf.GAMMA.INV(V4,'04_PSA_INPUTS'!H9,'04_PSA_INPUTS'!I9) -> #NAME? | G4: =_xludf.BETA.INV(W4,'04_PSA_INPUTS'!H10,'04_PSA_INPUTS'!I10) -> #NAME? | H4: =_xludf.BETA.INV(X4,'04_PSA_INPUTS'!H11,'04_PSA_INPUTS'!I11) -> #NAME? | I4: =D4+B4*F4+'01_INPUTS'!B20 -> #NAME? | J4: =E4+C4*F4+'01_INPUTS'!B21 -> #NAME? | K4: =I4-J4 -> #NAME? | L4: =G4-B4*H4 -> #NAME? | M4: =G4-C4*H4 -> #NAME? | N4: =L4-M4 -> #NAME? | O4: =IF(N4=0,"",K4/N4) -> #NAME? | P4: ='01_INPUTS'!B9*N4-K4 -> #NAME? | Q4: =IF(P4>0,1,0) -> #NAME? | R4: 0.5651422 | S4: 0.82894488 | T4: 0.43205855 | U4: 0.38104961 | V4: 0.83900348 | W4: 0.20886718 | X4: 0.17588501
A5: 4 | B5: =_xludf.BETA.INV(R5,'04_PSA_INPUTS'!H5,'04_PSA_INPUTS'!I5) -> #NAME? | C5: =_xludf.BETA.INV(S5,'04_PSA_INPUTS'!H6,'04_PSA_INPUTS'!I6) -> #NAME? | D5: =_xludf.GAMMA.INV(T5,'04_PSA_INPUTS'!H7,'04_PSA_INPUTS'!I7) -> #NAME? | E5: =_xludf.GAMMA.INV(U5,'04_PSA_INPUTS'!H8,'04_PSA_INPUTS'!I8) -> #NAME? | F5: =_xludf.GAMMA.INV(V5,'04_PSA_INPUTS'!H9,'04_PSA_INPUTS'!I9) -> #NAME? | G5: =_xludf.BETA.INV(W5,'04_PSA_INPUTS'!H10,'04_PSA_INPUTS'!I10) -> #NAME? | H5: =_xludf.BETA.INV(X5,'04_PSA_INPUTS'!H11,'04_PSA_INPUTS'!I11) -> #NAME? | I5: =D5+B5*F5+'01_INPUTS'!B20 -> #NAME? | J5: =E5+C5*F5+'01_INPUTS'!B21 -> #NAME? | K5: =I5-J5 -> #NAME? | L5: =G5-B5*H5 -> #NAME? | M5: =G5-C5*H5 -> #NAME? | N5: =L5-M5 -> #NAME? | O5: =IF(N5=0,"",K5/N5) -> #NAME? | P5: ='01_INPUTS'!B9*N5-K5 -> #NAME? | Q5: =IF(P5>0,1,0) -> #NAME? | R5: 0.34360758 | S5: 0.71049677 | T5: 0.87053893 | U5: 0.58722469 | V5: 0.25799171 | W5: 0.18662832 | X5: 0.36372541
A6: 5 | B6: =_xludf.BETA.INV(R6,'04_PSA_INPUTS'!H5,'04_PSA_INPUTS'!I5) -> #NAME? | C6: =_xludf.BETA.INV(S6,'04_PSA_INPUTS'!H6,'04_PSA_INPUTS'!I6) -> #NAME? | D6: =_xludf.GAMMA.INV(T6,'04_PSA_INPUTS'!H7,'04_PSA_INPUTS'!I7) -> #NAME? | E6: =_xludf.GAMMA.INV(U6,'04_PSA_INPUTS'!H8,'04_PSA_INPUTS'!I8) -> #NAME? | F6: =_xludf.GAMMA.INV(V6,'04_PSA_INPUTS'!H9,'04_PSA_INPUTS'!I9) -> #NAME? | G6: =_xludf.BETA.INV(W6,'04_PSA_INPUTS'!H10,'04_PSA_INPUTS'!I10) -> #NAME? | H6: =_xludf.BETA.INV(X6,'04_PSA_INPUTS'!H11,'04_PSA_INPUTS'!I11) -> #NAME? | I6: =D6+B6*F6+'01_INPUTS'!B20 -> #NAME? | J6: =E6+C6*F6+'01_INPUTS'!B21 -> #NAME? | K6: =I6-J6 -> #NAME? | L6: =G6-B6*H6 -> #NAME? | M6: =G6-C6*H6 -> #NAME? | N6: =L6-M6 -> #NAME? | O6: =IF(N6=0,"",K6/N6) -> #NAME? | P6: ='01_INPUTS'!B9*N6-K6 -> #NAME? | Q6: =IF(P6>0,1,0) -> #NAME? | R6: 0.0094469818 | S6: 0.13853907 | T6: 0.17702434 | U6: 0.67983699 | V6: 0.37754766 | W6: 0.90289794 | X6: 0.15275539
A7: 6 | B7: =_xludf.BETA.INV(R7,'04_PSA_INPUTS'!H5,'04_PSA_INPUTS'!I5) -> #NAME? | C7: =_xludf.BETA.INV(S7,'04_PSA_INPUTS'!H6,'04_PSA_INPUTS'!I6) -> #NAME? | D7: =_xludf.GAMMA.INV(T7,'04_PSA_INPUTS'!H7,'04_PSA_INPUTS'!I7) -> #NAME? | E7: =_xludf.GAMMA.INV(U7,'04_PSA_INPUTS'!H8,'04_PSA_INPUTS'!I8) -> #NAME? | F7: =_xludf.GAMMA.INV(V7,'04_PSA_INPUTS'!H9,'04_PSA_INPUTS'!I9) -> #NAME? | G7: =_xludf.BETA.INV(W7,'04_PSA_INPUTS'!H10,'04_PSA_INPUTS'!I10) -> #NAME? | H7: =_xludf.BETA.INV(X7,'04_PSA_INPUTS'!H11,'04_PSA_INPUTS'!I11) -> #NAME? | I7: =D7+B7*F7+'01_INPUTS'!B20 -> #NAME? | J7: =E7+C7*F7+'01_INPUTS'!B21 -> #NAME? | K7: =I7-J7 -> #NAME? | L7: =G7-B7*H7 -> #NAME? | M7: =G7-C7*H7 -> #NAME? | N7: =L7-M7 -> #NAME? | O7: =IF(N7=0,"",K7/N7) -> #NAME? | P7: ='01_INPUTS'!B9*N7-K7 -> #NAME? | Q7: =IF(P7>0,1,0) -> #NAME? | R7: 0.35481747 | S7: 0.38531392 | T7: 0.89068506 | U7: 0.5445113 | V7: 0.9707977 | W7: 0.83096633 | X7: 0.99970181
A8: 7 | B8: =_xludf.BETA.INV(R8,'04_PSA_INPUTS'!H5,'04_PSA_INPUTS'!I5) -> #NAME? | C8: =_xludf.BETA.INV(S8,'04_PSA_INPUTS'!H6,'04_PSA_INPUTS'!I6) -> #NAME? | D8: =_xludf.GAMMA.INV(T8,'04_PSA_INPUTS'!H7,'04_PSA_INPUTS'!I7) -> #NAME? | E8: =_xludf.GAMMA.INV(U8,'04_PSA_INPUTS'!H8,'04_PSA_INPUTS'!I8) -> #NAME? | F8: =_xludf.GAMMA.INV(V8,'04_PSA_INPUTS'!H9,'04_PSA_INPUTS'!I9) -> #NAME? | G8: =_xludf.BETA.INV(W8,'04_PSA_INPUTS'!H10,'04_PSA_INPUTS'!I10) -> #NAME? | H8: =_xludf.BETA.INV(X8,'04_PSA_INPUTS'!H11,'04_PSA_INPUTS'!I11) -> #NAME? | I8: =D8+B8*F8+'01_INPUTS'!B20 -> #NAME? | J8: =E8+C8*F8+'01_INPUTS'!B21 -> #NAME? | K8: =I8-J8 -> #NAME? | L8: =G8-B8*H8 -> #NAME? | M8: =G8-C8*H8 -> #NAME? | N8: =L8-M8 -> #NAME? | O8: =IF(N8=0,"",K8/N8) -> #NAME? | P8: ='01_INPUTS'!B9*N8-K8 -> #NAME? | Q8: =IF(P8>0,1,0) -> #NAME? | R8: 0.97384578 | S8: 0.049857999 | T8: 0.98408977 | U8: 0.36080815 | V8: 0.49235751 | W8: 0.011080653 | X8: 0.41827401
A9: 8 | B9: =_xludf.BETA.INV(R9,'04_PSA_INPUTS'!H5,'04_PSA_INPUTS'!I5) -> #NAME? | C9: =_xludf.BETA.INV(S9,'04_PSA_INPUTS'!H6,'04_PSA_INPUTS'!I6) -> #NAME? | D9: =_xludf.GAMMA.INV(T9,'04_PSA_INPUTS'!H7,'04_PSA_INPUTS'!I7) -> #NAME? | E9: =_xludf.GAMMA.INV(U9,'04_PSA_INPUTS'!H8,'04_PSA_INPUTS'!I8) -> #NAME? | F9: =_xludf.GAMMA.INV(V9,'04_PSA_INPUTS'!H9,'04_PSA_INPUTS'!I9) -> #NAME? | G9: =_xludf.BETA.INV(W9,'04_PSA_INPUTS'!H10,'04_PSA_INPUTS'!I10) -> #NAME? | H9: =_xludf.BETA.INV(X9,'04_PSA_INPUTS'!H11,'04_PSA_INPUTS'!I11) -> #NAME? | I9: =D9+B9*F9+'01_INPUTS'!B20 -> #NAME? | J9: =E9+C9*F9+'01_INPUTS'!B21 -> #NAME? | K9: =I9-J9 -> #NAME? | L9: =G9-B9*H9 -> #NAME? | M9: =G9-C9*H9 -> #NAME? | N9: =L9-M9 -> #NAME? | O9: =IF(N9=0,"",K9/N9) -> #NAME? | P9: ='01_INPUTS'!B9*N9-K9 -> #NAME? | Q9: =IF(P9>0,1,0) -> #NAME? | R9: 0.56894008 | S9: 0.33330683 | T9: 0.51246177 | U9: 0.4215151 | V9: 0.81069763 | W9: 0.31157325 | X9: 0.14950265
A10: 9 | B10: =_xludf.BETA.INV(R10,'04_PSA_INPUTS'!H5,'04_PSA_INPUTS'!I5) -> #NAME? | C10: =_xludf.BETA.INV(S10,'04_PSA_INPUTS'!H6,'04_PSA_INPUTS'!I6) -> #NAME? | D10: =_xludf.GAMMA.INV(T10,'04_PSA_INPUTS'!H7,'04_PSA_INPUTS'!I7) -> #NAME? | E10: =_xludf.GAMMA.INV(U10,'04_PSA_INPUTS'!H8,'04_PSA_INPUTS'!I8) -> #NAME? | F10: =_xludf.GAMMA.INV(V10,'04_PSA_INPUTS'!H9,'04_PSA_INPUTS'!I9) -> #NAME? | G10: =_xludf.BETA.INV(W10,'04_PSA_INPUTS'!H10,'04_PSA_INPUTS'!I10) -> #NAME? | H10: =_xludf.BETA.INV(X10,'04_PSA_INPUTS'!H11,'04_PSA_INPUTS'!I11) -> #NAME? | I10: =D10+B10*F10+'01_INPUTS'!B20 -> #NAME? | J10: =E10+C10*F10+'01_INPUTS'!B21 -> #NAME? | K10: =I10-J10 -> #NAME? | L10: =G10-B10*H10 -> #NAME? | M10: =G10-C10*H10 -> #NAME? | N10: =L10-M10 -> #NAME? | O10: =IF(N10=0,"",K10/N10) -> #NAME? | P10: ='01_INPUTS'!B9*N10-K10 -> #NAME? | Q10: =IF(P10>0,1,0) -> #NAME? | R10: 0.80603485 | S10: 0.63524625 | T10: 0.49112567 | U10: 0.15584527 | V10: 0.79029972 | W10: 0.83961507 | X10: 0.84839473
A11: 10 | B11: =_xludf.BETA.INV(R11,'04_PSA_INPUTS'!H5,'04_PSA_INPUTS'!I5) -> #NAME? | C11: =_xludf.BETA.INV(S11,'04_PSA_INPUTS'!H6,'04_PSA_INPUTS'!I6) -> #NAME? | D11: =_xludf.GAMMA.INV(T11,'04_PSA_INPUTS'!H7,'04_PSA_INPUTS'!I7) -> #NAME? | E11: =_xludf.GAMMA.INV(U11,'04_PSA_INPUTS'!H8,'04_PSA_INPUTS'!I8) -> #NAME? | F11: =_xludf.GAMMA.INV(V11,'04_PSA_INPUTS'!H9,'04_PSA_INPUTS'!I9) -> #NAME? | G11: =_xludf.BETA.INV(W11,'04_PSA_INPUTS'!H10,'04_PSA_INPUTS'!I10) -> #NAME? | H11: =_xludf.BETA.INV(X11,'04_PSA_INPUTS'!H11,'04_PSA_INPUTS'!I11) -> #NAME? | I11: =D11+B11*F11+'01_INPUTS'!B20 -> #NAME? | J11: =E11+C11*F11+'01_INPUTS'!B21 -> #NAME? | K11: =I11-J11 -> #NAME? | L11: =G11-B11*H11 -> #NAME? | M11: =G11-C11*H11 -> #NAME? | N11: =L11-M11 -> #NAME? | O11: =IF(N11=0,"",K11/N11) -> #NAME? | P11: ='01_INPUTS'!B9*N11-K11 -> #NAME? | Q11: =IF(P11>0,1,0) -> #NAME? | R11: 0.5483465 | S11: 0.92545174 | T11: 0.22026996 | U11: 0.79709808 | V11: 0.037196886 | W11: 0.95171876 | X11: 0.20807444
A12: 11 | B12: =_xludf.BETA.INV(R12,'04_PSA_INPUTS'!H5,'04_PSA_INPUTS'!I5) -> #NAME? | C12: =_xludf.BETA.INV(S12,'04_PSA_INPUTS'!H6,'04_PSA_INPUTS'!I6) -> #NAME? | D12: =_xludf.GAMMA.INV(T12,'04_PSA_INPUTS'!H7,'04_PSA_INPUTS'!I7) -> #NAME? | E12: =_xludf.GAMMA.INV(U12,'04_PSA_INPUTS'!H8,'04_PSA_INPUTS'!I8) -> #NAME? | F12: =_xludf.GAMMA.INV(V12,'04_PSA_INPUTS'!H9,'04_PSA_INPUTS'!I9) -> #NAME? | G12: =_xludf.BETA.INV(W12,'04_PSA_INPUTS'!H10,'04_PSA_INPUTS'!I10) -> #NAME? | H12: =_xludf.BETA.INV(X12,'04_PSA_INPUTS'!H11,'04_PSA_INPUTS'!I11) -> #NAME? | I12: =D12+B12*F12+'01_INPUTS'!B20 -> #NAME? | J12: =E12+C12*F12+'01_INPUTS'!B21 -> #NAME? | K12: =I12-J12 -> #NAME? | L12: =G12-B12*H12 -> #NAME? | M12: =G12-C12*H12 -> #NAME? | N12: =L12-M12 -> #NAME? | O12: =IF(N12=0,"",K12/N12) -> #NAME? | P12: ='01_INPUTS'!B9*N12-K12 -> #NAME? | Q12: =IF(P12>0,1,0) -> #NAME? | R12: 0.5248102 | S12: 0.51498771 | T12: 0.15554826 | U12: 0.93610191 | V12: 0.16751501 | W12: 0.84223013 | X12: 0.15109838
A13: 12 | B13: =_xludf.BETA.INV(R13,'04_PSA_INPUTS'!H5,'04_PSA_INPUTS'!I5) -> #NAME? | C13: =_xludf.BETA.INV(S13,'04_PSA_INPUTS'!H6,'04_PSA_INPUTS'!I6) -> #NAME? | D13: =_xludf.GAMMA.INV(T13,'04_PSA_INPUTS'!H7,'04_PSA_INPUTS'!I7) -> #NAME? | E13: =_xludf.GAMMA.INV(U13,'04_PSA_INPUTS'!H8,'04_PSA_INPUTS'!I8) -> #NAME? | F13: =_xludf.GAMMA.INV(V13,'04_PSA_INPUTS'!H9,'04_PSA_INPUTS'!I9) -> #NAME? | G13: =_xludf.BETA.INV(W13,'04_PSA_INPUTS'!H10,'04_PSA_INPUTS'!I10) -> #NAME? | H13: =_xludf.BETA.INV(X13,'04_PSA_INPUTS'!H11,'04_PSA_INPUTS'!I11) -> #NAME? | I13: =D13+B13*F13+'01_INPUTS'!B20 -> #NAME? | J13: =E13+C13*F13+'01_INPUTS'!B21 -> #NAME? | K13: =I13-J13 -> #NAME? | L13: =G13-B13*H13 -> #NAME? | M13: =G13-C13*H13 -> #NAME? | N13: =L13-M13 -> #NAME? | O13: =IF(N13=0,"",K13/N13) -> #NAME? | P13: ='01_INPUTS'!B9*N13-K13 -> #NAME? | Q13: =IF(P13>0,1,0) -> #NAME? | R13: 0.91630495 | S13: 0.79980992 | T13: 0.50627315 | U13: 0.33772049 | V13: 0.42095801 | W13: 0.90187859 | X13: 0.28751272
A14: 13 | B14: =_xludf.BETA.INV(R14,'04_PSA_INPUTS'!H5,'04_PSA_INPUTS'!I5) -> #NAME? | C14: =_xludf.BETA.INV(S14,'04_PSA_INPUTS'!H6,'04_PSA_INPUTS'!I6) -> #NAME? | D14: =_xludf.GAMMA.INV(T14,'04_PSA_INPUTS'!H7,'04_PSA_INPUTS'!I7) -> #NAME? | E14: =_xludf.GAMMA.INV(U14,'04_PSA_INPUTS'!H8,'04_PSA_INPUTS'!I8) -> #NAME? | F14: =_xludf.GAMMA.INV(V14,'04_PSA_INPUTS'!H9,'04_PSA_INPUTS'!I9) -> #NAME? | G14: =_xludf.BETA.INV(W14,'04_PSA_INPUTS'!H10,'04_PSA_INPUTS'!I10) -> #NAME? | H14: =_xludf.BETA.INV(X14,'04_PSA_INPUTS'!H11,'04_PSA_INPUTS'!I11) -> #NAME? | I14: =D14+B14*F14+'01_INPUTS'!B20 -> #NAME? | J14: =E14+C14*F14+'01_INPUTS'!B21 -> #NAME? | K14: =I14-J14 -> #NAME? | L14: =G14-B14*H14 -> #NAME? | M14: =G14-C14*H14 -> #NAME? | N14: =L14-M14 -> #NAME? | O14: =IF(N14=0,"",K14/N14) -> #NAME? | P14: ='01_INPUTS'!B9*N14-K14 -> #NAME? | Q14: =IF(P14>0,1,0) -> #NAME? | R14: 0.40605669 | S14: 0.32619334 | T14: 0.43881465 | U14: 0.18029065 | V14: 0.90321131 | W14: 0.36014099 | X14: 0.0062810294
A15: 14 | B15: =_xludf.BETA.INV(R15,'04_PSA_INPUTS'!H5,'04_PSA_INPUTS'!I5) -> #NAME? | C15: =_xludf.BETA.INV(S15,'04_PSA_INPUTS'!H6,'04_PSA_INPUTS'!I6) -> #NAME? | D15: =_xludf.GAMMA.INV(T15,'04_PSA_INPUTS'!H7,'04_PSA_INPUTS'!I7) -> #NAME? | E15: =_xludf.GAMMA.INV(U15,'04_PSA_INPUTS'!H8,'04_PSA_INPUTS'!I8) -> #NAME? | F15: =_xludf.GAMMA.INV(V15,'04_PSA_INPUTS'!H9,'04_PSA_INPUTS'!I9) -> #NAME? | G15: =_xludf.BETA.INV(W15,'04_PSA_INPUTS'!H10,'04_PSA_INPUTS'!I10) -> #NAME? | H15: =_xludf.BETA.INV(X15,'04_PSA_INPUTS'!H11,'04_PSA_INPUTS'!I11) -> #NAME? | I15: =D15+B15*F15+'01_INPUTS'!B20 -> #NAME? | J15: =E15+C15*F15+'01_INPUTS'!B21 -> #NAME? | K15: =I15-J15 -> #NAME? | L15: =G15-B15*H15 -> #NAME? | M15: =G15-C15*H15 -> #NAME? | N15: =L15-M15 -> #NAME? | O15: =IF(N15=0,"",K15/N15) -> #NAME? | P15: ='01_INPUTS'!B9*N15-K15 -> #NAME? | Q15: =IF(P15>0,1,0) -> #NAME? | R15: 0.87412803 | S15: 0.76323962 | T15: 0.90191245 | U15: 0.41939342 | V15: 0.48104646 | W15: 0.50956619 | X15: 0.55092532
A16: 15 | B16: =_xludf.BETA.INV(R16,'04_PSA_INPUTS'!H5,'04_PSA_INPUTS'!I5) -> #NAME? | C16: =_xludf.BETA.INV(S16,'04_PSA_INPUTS'!H6,'04_PSA_INPUTS'!I6) -> #NAME? | D16: =_xludf.GAMMA.INV(T16,'04_PSA_INPUTS'!H7,'04_PSA_INPUTS'!I7) -> #NAME? | E16: =_xludf.GAMMA.INV(U16,'04_PSA_INPUTS'!H8,'04_PSA_INPUTS'!I8) -> #NAME? | F16: =_xludf.GAMMA.INV(V16,'04_PSA_INPUTS'!H9,'04_PSA_INPUTS'!I9) -> #NAME? | G16: =_xludf.BETA.INV(W16,'04_PSA_INPUTS'!H10,'04_PSA_INPUTS'!I10) -> #NAME? | H16: =_xludf.BETA.INV(X16,'04_PSA_INPUTS'!H11,'04_PSA_INPUTS'!I11) -> #NAME? | I16: =D16+B16*F16+'01_INPUTS'!B20 -> #NAME? | J16: =E16+C16*F16+'01_INPUTS'!B21 -> #NAME? | K16: =I16-J16 -> #NAME? | L16: =G16-B16*H16 -> #NAME? | M16: =G16-C16*H16 -> #NAME? | N16: =L16-M16 -> #NAME? | O16: =IF(N16=0,"",K16/N16) -> #NAME? | P16: ='01_INPUTS'!B9*N16-K16 -> #NAME? | Q16: =IF(P16>0,1,0) -> #NAME? | R16: 0.48684134 | S16: 0.28072798 | T16: 0.57817117 | U16: 0.6263273 | V16: 0.6132418 | W16: 0.4329998 | X16: 0.57236792
A17: 16 | B17: =_xludf.BETA.INV(R17,'04_PSA_INPUTS'!H5,'04_PSA_INPUTS'!I5) -> #NAME? | C17: =_xludf.BETA.INV(S17,'04_PSA_INPUTS'!H6,'04_PSA_INPUTS'!I6) -> #NAME? | D17: =_xludf.GAMMA.INV(T17,'04_PSA_INPUTS'!H7,'04_PSA_INPUTS'!I7) -> #NAME? | E17: =_xludf.GAMMA.INV(U17,'04_PSA_INPUTS'!H8,'04_PSA_INPUTS'!I8) -> #NAME? | F17: =_xludf.GAMMA.INV(V17,'04_PSA_INPUTS'!H9,'04_PSA_INPUTS'!I9) -> #NAME? | G17: =_xludf.BETA.INV(W17,'04_PSA_INPUTS'!H10,'04_PSA_INPUTS'!I10) -> #NAME? | H17: =_xludf.BETA.INV(X17,'04_PSA_INPUTS'!H11,'04_PSA_INPUTS'!I11) -> #NAME? | I17: =D17+B17*F17+'01_INPUTS'!B20 -> #NAME? | J17: =E17+C17*F17+'01_INPUTS'!B21 -> #NAME? | K17: =I17-J17 -> #NAME? | L17: =G17-B17*H17 -> #NAME? | M17: =G17-C17*H17 -> #NAME? | N17: =L17-M17 -> #NAME? | O17: =IF(N17=0,"",K17/N17) -> #NAME? | P17: ='01_INPUTS'!B9*N17-K17 -> #NAME? | Q17: =IF(P17>0,1,0) -> #NAME? | R17: 0.46217532 | S17: 0.67562501 | T17: 0.24186856 | U17: 0.01028772 | V17: 0.0062165749 | W17: 0.32776461 | X17: 0.66877373
A18: 17 | B18: =_xludf.BETA.INV(R18,'04_PSA_INPUTS'!H5,'04_PSA_INPUTS'!I5) -> #NAME? | C18: =_xludf.BETA.INV(S18,'04_PSA_INPUTS'!H6,'04_PSA_INPUTS'!I6) -> #NAME? | D18: =_xludf.GAMMA.INV(T18,'04_PSA_INPUTS'!H7,'04_PSA_INPUTS'!I7) -> #NAME? | E18: =_xludf.GAMMA.INV(U18,'04_PSA_INPUTS'!H8,'04_PSA_INPUTS'!I8) -> #NAME? | F18: =_xludf.GAMMA.INV(V18,'04_PSA_INPUTS'!H9,'04_PSA_INPUTS'!I9) -> #NAME? | G18: =_xludf.BETA.INV(W18,'04_PSA_INPUTS'!H10,'04_PSA_INPUTS'!I10) -> #NAME? | H18: =_xludf.BETA.INV(X18,'04_PSA_INPUTS'!H11,'04_PSA_INPUTS'!I11) -> #NAME? | I18: =D18+B18*F18+'01_INPUTS'!B20 -> #NAME? | J18: =E18+C18*F18+'01_INPUTS'!B21 -> #NAME? | K18: =I18-J18 -> #NAME? | L18: =G18-B18*H18 -> #NAME? | M18: =G18-C18*H18 -> #NAME? | N18: =L18-M18 -> #NAME? | O18: =IF(N18=0,"",K18/N18) -> #NAME? | P18: ='01_INPUTS'!B9*N18-K18 -> #NAME? | Q18: =IF(P18>0,1,0) -> #NAME? | R18: 0.30768241 | S18: 0.23279399 | T18: 0.58335451 | U18: 0.32894357 | V18: 0.94068828 | W18: 0.70336181 | X18: 0.065895996
A19: 18 | B19: =_xludf.BETA.INV(R19,'04_PSA_INPUTS'!H5,'04_PSA_INPUTS'!I5) -> #NAME? | C19: =_xludf.BETA.INV(S19,'04_PSA_INPUTS'!H6,'04_PSA_INPUTS'!I6) -> #NAME? | D19: =_xludf.GAMMA.INV(T19,'04_PSA_INPUTS'!H7,'04_PSA_INPUTS'!I7) -> #NAME? | E19: =_xludf.GAMMA.INV(U19,'04_PSA_INPUTS'!H8,'04_PSA_INPUTS'!I8) -> #NAME? | F19: =_xludf.GAMMA.INV(V19,'04_PSA_INPUTS'!H9,'04_PSA_INPUTS'!I9) -> #NAME? | G19: =_xludf.BETA.INV(W19,'04_PSA_INPUTS'!H10,'04_PSA_INPUTS'!I10) -> #NAME? | H19: =_xludf.BETA.INV(X19,'04_PSA_INPUTS'!H11,'04_PSA_INPUTS'!I11) -> #NAME? | I19: =D19+B19*F19+'01_INPUTS'!B20 -> #NAME? | J19: =E19+C19*F19+'01_INPUTS'!B21 -> #NAME? | K19: =I19-J19 -> #NAME? | L19: =G19-B19*H19 -> #NAME? | M19: =G19-C19*H19 -> #NAME? | N19: =L19-M19 -> #NAME? | O19: =IF(N19=0,"",K19/N19) -> #NAME? | P19: ='01_INPUTS'!B9*N19-K19 -> #NAME? | Q19: =IF(P19>0,1,0) -> #NAME? | R19: 0.060064552 | S19: 0.2605299 | T19: 0.35653109 | U19: 0.8570683 | V19: 0.13567876 | W19: 0.14050025 | X19: 0.58545119
A20: 19 | B20: =_xludf.BETA.INV(R20,'04_PSA_INPUTS'!H5,'04_PSA_INPUTS'!I5) -> #NAME? | C20: =_xludf.BETA.INV(S20,'04_PSA_INPUTS'!H6,'04_PSA_INPUTS'!I6) -> #NAME? | D20: =_xludf.GAMMA.INV(T20,'04_PSA_INPUTS'!H7,'04_PSA_INPUTS'!I7) -> #NAME? | E20: =_xludf.GAMMA.INV(U20,'04_PSA_INPUTS'!H8,'04_PSA_INPUTS'!I8) -> #NAME? | F20: =_xludf.GAMMA.INV(V20,'04_PSA_INPUTS'!H9,'04_PSA_INPUTS'!I9) -> #NAME? | G20: =_xludf.BETA.INV(W20,'04_PSA_INPUTS'!H10,'04_PSA_INPUTS'!I10) -> #NAME? | H20: =_xludf.BETA.INV(X20,'04_PSA_INPUTS'!H11,'04_PSA_INPUTS'!I11) -> #NAME? | I20: =D20+B20*F20+'01_INPUTS'!B20 -> #NAME? | J20: =E20+C20*F20+'01_INPUTS'!B21 -> #NAME? | K20: =I20-J20 -> #NAME? | L20: =G20-B20*H20 -> #NAME? | M20: =G20-C20*H20 -> #NAME? | N20: =L20-M20 -> #NAME? | O20: =IF(N20=0,"",K20/N20) -> #NAME? | P20: ='01_INPUTS'!B9*N20-K20 -> #NAME? | Q20: =IF(P20>0,1,0) -> #NAME? | R20: 0.55061992 | S20: 0.51293799 | T20: 0.30710693 | U20: 0.31237237 | V20: 0.25454317 | W20: 0.59673006 | X20: 0.39574339
A21: 20 | B21: =_xludf.BETA.INV(R21,'04_PSA_INPUTS'!H5,'04_PSA_INPUTS'!I5) -> #NAME? | C21: =_xludf.BETA.INV(S21,'04_PSA_INPUTS'!H6,'04_PSA_INPUTS'!I6) -> #NAME? | D21: =_xludf.GAMMA.INV(T21,'04_PSA_INPUTS'!H7,'04_PSA_INPUTS'!I7) -> #NAME? | E21: =_xludf.GAMMA.INV(U21,'04_PSA_INPUTS'!H8,'04_PSA_INPUTS'!I8) -> #NAME? | F21: =_xludf.GAMMA.INV(V21,'04_PSA_INPUTS'!H9,'04_PSA_INPUTS'!I9) -> #NAME? | G21: =_xludf.BETA.INV(W21,'04_PSA_INPUTS'!H10,'04_PSA_INPUTS'!I10) -> #NAME? | H21: =_xludf.BETA.INV(X21,'04_PSA_INPUTS'!H11,'04_PSA_INPUTS'!I11) -> #NAME? | I21: =D21+B21*F21+'01_INPUTS'!B20 -> #NAME? | J21: =E21+C21*F21+'01_INPUTS'!B21 -> #NAME? | K21: =I21-J21 -> #NAME? | L21: =G21-B21*H21 -> #NAME? | M21: =G21-C21*H21 -> #NAME? | N21: =L21-M21 -> #NAME? | O21: =IF(N21=0,"",K21/N21) -> #NAME? | P21: ='01_INPUTS'!B9*N21-K21 -> #NAME? | Q21: =IF(P21>0,1,0) -> #NAME? | R21: 0.22088744 | S21: 0.6453192 | T21: 0.93834112 | U21: 0.1619097 | V21: 0.74984376 | W21: 0.12902333 | X21: 0.037859896
A22: 21 | B22: =_xludf.BETA.INV(R22,'04_PSA_INPUTS'!H5,'04_PSA_INPUTS'!I5) -> #NAME? | C22: =_xludf.BETA.INV(S22,'04_PSA_INPUTS'!H6,'04_PSA_INPUTS'!I6) -> #NAME? | D22: =_xludf.GAMMA.INV(T22,'04_PSA_INPUTS'!H7,'04_PSA_INPUTS'!I7) -> #NAME? | E22: =_xludf.GAMMA.INV(U22,'04_PSA_INPUTS'!H8,'04_PSA_INPUTS'!I8) -> #NAME? | F22: =_xludf.GAMMA.INV(V22,'04_PSA_INPUTS'!H9,'04_PSA_INPUTS'!I9) -> #NAME? | G22: =_xludf.BETA.INV(W22,'04_PSA_INPUTS'!H10,'04_PSA_INPUTS'!I10) -> #NAME? | H22: =_xludf.BETA.INV(X22,'04_PSA_INPUTS'!H11,'04_PSA_INPUTS'!I11) -> #NAME? | I22: =D22+B22*F22+'01_INPUTS'!B20 -> #NAME? | J22: =E22+C22*F22+'01_INPUTS'!B21 -> #NAME? | K22: =I22-J22 -> #NAME? | L22: =G22-B22*H22 -> #NAME? | M22: =G22-C22*H22 -> #NAME? | N22: =L22-M22 -> #NAME? | O22: =IF(N22=0,"",K22/N22) -> #NAME? | P22: ='01_INPUTS'!B9*N22-K22 -> #NAME? | Q22: =IF(P22>0,1,0) -> #NAME? | R22: 0.53822981 | S22: 0.87924275 | T22: 0.57269545 | U22: 0.058258447 | V22: 0.79198635 | W22: 0.85815303 | X22: 0.85617431
A23: 22 | B23: =_xludf.BETA.INV(R23,'04_PSA_INPUTS'!H5,'04_PSA_INPUTS'!I5) -> #NAME? | C23: =_xludf.BETA.INV(S23,'04_PSA_INPUTS'!H6,'04_PSA_INPUTS'!I6) -> #NAME? | D23: =_xludf.GAMMA.INV(T23,'04_PSA_INPUTS'!H7,'04_PSA_INPUTS'!I7) -> #NAME? | E23: =_xludf.GAMMA.INV(U23,'04_PSA_INPUTS'!H8,'04_PSA_INPUTS'!I8) -> #NAME? | F23: =_xludf.GAMMA.INV(V23,'04_PSA_INPUTS'!H9,'04_PSA_INPUTS'!I9) -> #NAME? | G23: =_xludf.BETA.INV(W23,'04_PSA_INPUTS'!H10,'04_PSA_INPUTS'!I10) -> #NAME? | H23: =_xludf.BETA.INV(X23,'04_PSA_INPUTS'!H11,'04_PSA_INPUTS'!I11) -> #NAME? | I23: =D23+B23*F23+'01_INPUTS'!B20 -> #NAME? | J23: =E23+C23*F23+'01_INPUTS'!B21 -> #NAME? | K23: =I23-J23 -> #NAME? | L23: =G23-B23*H23 -> #NAME? | M23: =G23-C23*H23 -> #NAME? | N23: =L23-M23 -> #NAME? | O23: =IF(N23=0,"",K23/N23) -> #NAME? | P23: ='01_INPUTS'!B9*N23-K23 -> #NAME? | Q23: =IF(P23>0,1,0) -> #NAME? | R23: 0.38472014 | S23: 0.6902828 | T23: 0.3251801 | U23: 0.21952724 | V23: 0.77691693 | W23: 0.74446116 | X23: 0.078943223
A24: 23 | B24: =_xludf.BETA.INV(R24,'04_PSA_INPUTS'!H5,'04_PSA_INPUTS'!I5) -> #NAME? | C24: =_xludf.BETA.INV(S24,'04_PSA_INPUTS'!H6,'04_PSA_INPUTS'!I6) -> #NAME? | D24: =_xludf.GAMMA.INV(T24,'04_PSA_INPUTS'!H7,'04_PSA_INPUTS'!I7) -> #NAME? | E24: =_xludf.GAMMA.INV(U24,'04_PSA_INPUTS'!H8,'04_PSA_INPUTS'!I8) -> #NAME? | F24: =_xludf.GAMMA.INV(V24,'04_PSA_INPUTS'!H9,'04_PSA_INPUTS'!I9) -> #NAME? | G24: =_xludf.BETA.INV(W24,'04_PSA_INPUTS'!H10,'04_PSA_INPUTS'!I10) -> #NAME? | H24: =_xludf.BETA.INV(X24,'04_PSA_INPUTS'!H11,'04_PSA_INPUTS'!I11) -> #NAME? | I24: =D24+B24*F24+'01_INPUTS'!B20 -> #NAME? | J24: =E24+C24*F24+'01_INPUTS'!B21 -> #NAME? | K24: =I24-J24 -> #NAME? | L24: =G24-B24*H24 -> #NAME? | M24: =G24-C24*H24 -> #NAME? | N24: =L24-M24 -> #NAME? | O24: =IF(N24=0,"",K24/N24) -> #NAME? | P24: ='01_INPUTS'!B9*N24-K24 -> #NAME? | Q24: =IF(P24>0,1,0) -> #NAME? | R24: 0.80523276 | S24: 0.15439995 | T24: 0.18937044 | U24: 0.40894322 | V24: 0.87333946 | W24: 0.89972263 | X24: 0.040390044
A25: 24 | B25: =_xludf.BETA.INV(R25,'04_PSA_INPUTS'!H5,'04_PSA_INPUTS'!I5) -> #NAME? | C25: =_xludf.BETA.INV(S25,'04_PSA_INPUTS'!H6,'04_PSA_INPUTS'!I6) -> #NAME? | D25: =_xludf.GAMMA.INV(T25,'04_PSA_INPUTS'!H7,'04_PSA_INPUTS'!I7) -> #NAME? | E25: =_xludf.GAMMA.INV(U25,'04_PSA_INPUTS'!H8,'04_PSA_INPUTS'!I8) -> #NAME? | F25: =_xludf.GAMMA.INV(V25,'04_PSA_INPUTS'!H9,'04_PSA_INPUTS'!I9) -> #NAME? | G25: =_xludf.BETA.INV(W25,'04_PSA_INPUTS'!H10,'04_PSA_INPUTS'!I10) -> #NAME? | H25: =_xludf.BETA.INV(X25,'04_PSA_INPUTS'!H11,'04_PSA_INPUTS'!I11) -> #NAME? | I25: =D25+B25*F25+'01_INPUTS'!B20 -> #NAME? | J25: =E25+C25*F25+'01_INPUTS'!B21 -> #NAME? | K25: =I25-J25 -> #NAME? | L25: =G25-B25*H25 -> #NAME? | M25: =G25-C25*H25 -> #NAME? | N25: =L25-M25 -> #NAME? | O25: =IF(N25=0,"",K25/N25) -> #NAME? | P25: ='01_INPUTS'!B9*N25-K25 -> #NAME? | Q25: =IF(P25>0,1,0) -> #NAME? | R25: 0.33599298 | S25: 0.28770193 | T25: 0.17793842 | U25: 0.88799565 | V25: 0.99012109 | W25: 0.91350429 | X25: 0.66642391
A26: 25 | B26: =_xludf.BETA.INV(R26,'04_PSA_INPUTS'!H5,'04_PSA_INPUTS'!I5) -> #NAME? | C26: =_xludf.BETA.INV(S26,'04_PSA_INPUTS'!H6,'04_PSA_INPUTS'!I6) -> #NAME? | D26: =_xludf.GAMMA.INV(T26,'04_PSA_INPUTS'!H7,'04_PSA_INPUTS'!I7) -> #NAME? | E26: =_xludf.GAMMA.INV(U26,'04_PSA_INPUTS'!H8,'04_PSA_INPUTS'!I8) -> #NAME? | F26: =_xludf.GAMMA.INV(V26,'04_PSA_INPUTS'!H9,'04_PSA_INPUTS'!I9) -> #NAME? | G26: =_xludf.BETA.INV(W26,'04_PSA_INPUTS'!H10,'04_PSA_INPUTS'!I10) -> #NAME? | H26: =_xludf.BETA.INV(X26,'04_PSA_INPUTS'!H11,'04_PSA_INPUTS'!I11) -> #NAME? | I26: =D26+B26*F26+'01_INPUTS'!B20 -> #NAME? | J26: =E26+C26*F26+'01_INPUTS'!B21 -> #NAME? | K26: =I26-J26 -> #NAME? | L26: =G26-B26*H26 -> #NAME? | M26: =G26-C26*H26 -> #NAME? | N26: =L26-M26 -> #NAME? | O26: =IF(N26=0,"",K26/N26) -> #NAME? | P26: ='01_INPUTS'!B9*N26-K26 -> #NAME? | Q26: =IF(P26>0,1,0) -> #NAME? | R26: 0.67887075 | S26: 0.7724005 | T26: 0.46824686 | U26: 0.042103337 | V26: 0.3706097 | W26: 0.83133215 | X26: 0.2904357
A27: 26 | B27: =_xludf.BETA.INV(R27,'04_PSA_INPUTS'!H5,'04_PSA_INPUTS'!I5) -> #NAME? | C27: =_xludf.BETA.INV(S27,'04_PSA_INPUTS'!H6,'04_PSA_INPUTS'!I6) -> #NAME? | D27: =_xludf.GAMMA.INV(T27,'04_PSA_INPUTS'!H7,'04_PSA_INPUTS'!I7) -> #NAME? | E27: =_xludf.GAMMA.INV(U27,'04_PSA_INPUTS'!H8,'04_PSA_INPUTS'!I8) -> #NAME? | F27: =_xludf.GAMMA.INV(V27,'04_PSA_INPUTS'!H9,'04_PSA_INPUTS'!I9) -> #NAME? | G27: =_xludf.BETA.INV(W27,'04_PSA_INPUTS'!H10,'04_PSA_INPUTS'!I10) -> #NAME? | H27: =_xludf.BETA.INV(X27,'04_PSA_INPUTS'!H11,'04_PSA_INPUTS'!I11) -> #NAME? | I27: =D27+B27*F27+'01_INPUTS'!B20 -> #NAME? | J27: =E27+C27*F27+'01_INPUTS'!B21 -> #NAME? | K27: =I27-J27 -> #NAME? | L27: =G27-B27*H27 -> #NAME? | M27: =G27-C27*H27 -> #NAME? | N27: =L27-M27 -> #NAME? | O27: =IF(N27=0,"",K27/N27) -> #NAME? | P27: ='01_INPUTS'!B9*N27-K27 -> #NAME? | Q27: =IF(P27>0,1,0) -> #NAME? | R27: 0.93637224 | S27: 0.71798151 | T27: 0.17751263 | U27: 0.11121219 | V27: 0.029119569 | W27: 0.72373369 | X27: 0.46903111
A28: 27 | B28: =_xludf.BETA.INV(R28,'04_PSA_INPUTS'!H5,'04_PSA_INPUTS'!I5) -> #NAME? | C28: =_xludf.BETA.INV(S28,'04_PSA_INPUTS'!H6,'04_PSA_INPUTS'!I6) -> #NAME? | D28: =_xludf.GAMMA.INV(T28,'04_PSA_INPUTS'!H7,'04_PSA_INPUTS'!I7) -> #NAME? | E28: =_xludf.GAMMA.INV(U28,'04_PSA_INPUTS'!H8,'04_PSA_INPUTS'!I8) -> #NAME? | F28: =_xludf.GAMMA.INV(V28,'04_PSA_INPUTS'!H9,'04_PSA_INPUTS'!I9) -> #NAME? | G28: =_xludf.BETA.INV(W28,'04_PSA_INPUTS'!H10,'04_PSA_INPUTS'!I10) -> #NAME? | H28: =_xludf.BETA.INV(X28,'04_PSA_INPUTS'!H11,'04_PSA_INPUTS'!I11) -> #NAME? | I28: =D28+B28*F28+'01_INPUTS'!B20 -> #NAME? | J28: =E28+C28*F28+'01_INPUTS'!B21 -> #NAME? | K28: =I28-J28 -> #NAME? | L28: =G28-B28*H28 -> #NAME? | M28: =G28-C28*H28 -> #NAME? | N28: =L28-M28 -> #NAME? | O28: =IF(N28=0,"",K28/N28) -> #NAME? | P28: ='01_INPUTS'!B9*N28-K28 -> #NAME? | Q28: =IF(P28>0,1,0) -> #NAME? | R28: 0.47613508 | S28: 0.8793365 | T28: 0.70249098 | U28: 0.13945042 | V28: 0.21436374 | W28: 0.36085462 | X28: 0.62827811
A29: 28 | B29: =_xludf.BETA.INV(R29,'04_PSA_INPUTS'!H5,'04_PSA_INPUTS'!I5) -> #NAME? | C29: =_xludf.BETA.INV(S29,'04_PSA_INPUTS'!H6,'04_PSA_INPUTS'!I6) -> #NAME? | D29: =_xludf.GAMMA.INV(T29,'04_PSA_INPUTS'!H7,'04_PSA_INPUTS'!I7) -> #NAME? | E29: =_xludf.GAMMA.INV(U29,'04_PSA_INPUTS'!H8,'04_PSA_INPUTS'!I8) -> #NAME? | F29: =_xludf.GAMMA.INV(V29,'04_PSA_INPUTS'!H9,'04_PSA_INPUTS'!I9) -> #NAME? | G29: =_xludf.BETA.INV(W29,'04_PSA_INPUTS'!H10,'04_PSA_INPUTS'!I10) -> #NAME? | H29: =_xludf.BETA.INV(X29,'04_PSA_INPUTS'!H11,'04_PSA_INPUTS'!I11) -> #NAME? | I29: =D29+B29*F29+'01_INPUTS'!B20 -> #NAME? | J29: =E29+C29*F29+'01_INPUTS'!B21 -> #NAME? | K29: =I29-J29 -> #NAME? | L29: =G29-B29*H29 -> #NAME? | M29: =G29-C29*H29 -> #NAME? | N29: =L29-M29 -> #NAME? | O29: =IF(N29=0,"",K29/N29) -> #NAME? | P29: ='01_INPUTS'!B9*N29-K29 -> #NAME? | Q29: =IF(P29>0,1,0) -> #NAME? | R29: 0.16209288 | S29: 0.030991339 | T29: 0.75910468 | U29: 0.35181342 | V29: 0.046143564 | W29: 0.89630331 | X29: 0.80500658
A30: 29 | B30: =_xludf.BETA.INV(R30,'04_PSA_INPUTS'!H5,'04_PSA_INPUTS'!I5) -> #NAME? | C30: =_xludf.BETA.INV(S30,'04_PSA_INPUTS'!H6,'04_PSA_INPUTS'!I6) -> #NAME? | D30: =_xludf.GAMMA.INV(T30,'04_PSA_INPUTS'!H7,'04_PSA_INPUTS'!I7) -> #NAME? | E30: =_xludf.GAMMA.INV(U30,'04_PSA_INPUTS'!H8,'04_PSA_INPUTS'!I8) -> #NAME? | F30: =_xludf.GAMMA.INV(V30,'04_PSA_INPUTS'!H9,'04_PSA_INPUTS'!I9) -> #NAME? | G30: =_xludf.BETA.INV(W30,'04_PSA_INPUTS'!H10,'04_PSA_INPUTS'!I10) -> #NAME? | H30: =_xludf.BETA.INV(X30,'04_PSA_INPUTS'!H11,'04_PSA_INPUTS'!I11) -> #NAME? | I30: =D30+B30*F30+'01_INPUTS'!B20 -> #NAME? | J30: =E30+C30*F30+'01_INPUTS'!B21 -> #NAME? | K30: =I30-J30 -> #NAME? | L30: =G30-B30*H30 -> #NAME? | M30: =G30-C30*H30 -> #NAME? | N30: =L30-M30 -> #NAME? | O30: =IF(N30=0,"",K30/N30) -> #NAME? | P30: ='01_INPUTS'!B9*N30-K30 -> #NAME? | Q30: =IF(P30>0,1,0) -> #NAME? | R30: 0.68381136 | S30: 0.80275786 | T30: 0.011304724 | U30: 0.94317518 | V30: 0.62026487 | W30: 0.45494096 | X30: 0.062180173
A31: 30 | B31: =_xludf.BETA.INV(R31,'04_PSA_INPUTS'!H5,'04_PSA_INPUTS'!I5) -> #NAME? | C31: =_xludf.BETA.INV(S31,'04_PSA_INPUTS'!H6,'04_PSA_INPUTS'!I6) -> #NAME? | D31: =_xludf.GAMMA.INV(T31,'04_PSA_INPUTS'!H7,'04_PSA_INPUTS'!I7) -> #NAME? | E31: =_xludf.GAMMA.INV(U31,'04_PSA_INPUTS'!H8,'04_PSA_INPUTS'!I8) -> #NAME? | F31: =_xludf.GAMMA.INV(V31,'04_PSA_INPUTS'!H9,'04_PSA_INPUTS'!I9) -> #NAME? | G31: =_xludf.BETA.INV(W31,'04_PSA_INPUTS'!H10,'04_PSA_INPUTS'!I10) -> #NAME? | H31: =_xludf.BETA.INV(X31,'04_PSA_INPUTS'!H11,'04_PSA_INPUTS'!I11) -> #NAME? | I31: =D31+B31*F31+'01_INPUTS'!B20 -> #NAME? | J31: =E31+C31*F31+'01_INPUTS'!B21 -> #NAME? | K31: =I31-J31 -> #NAME? | L31: =G31-B31*H31 -> #NAME? | M31: =G31-C31*H31 -> #NAME? | N31: =L31-M31 -> #NAME? | O31: =IF(N31=0,"",K31/N31) -> #NAME? | P31: ='01_INPUTS'!B9*N31-K31 -> #NAME? | Q31: =IF(P31>0,1,0) -> #NAME? | R31: 0.36028325 | S31: 0.099905874 | T31: 0.78880939 | U31: 0.17113769 | V31: 0.79248085 | W31: 0.80271818 | X31: 0.80431883
A32: 31 | B32: =_xludf.BETA.INV(R32,'04_PSA_INPUTS'!H5,'04_PSA_INPUTS'!I5) -> #NAME? | C32: =_xludf.BETA.INV(S32,'04_PSA_INPUTS'!H6,'04_PSA_INPUTS'!I6) -> #NAME? | D32: =_xludf.GAMMA.INV(T32,'04_PSA_INPUTS'!H7,'04_PSA_INPUTS'!I7) -> #NAME? | E32: =_xludf.GAMMA.INV(U32,'04_PSA_INPUTS'!H8,'04_PSA_INPUTS'!I8) -> #NAME? | F32: =_xludf.GAMMA.INV(V32,'04_PSA_INPUTS'!H9,'04_PSA_INPUTS'!I9) -> #NAME? | G32: =_xludf.BETA.INV(W32,'04_PSA_INPUTS'!H10,'04_PSA_INPUTS'!I10) -> #NAME? | H32: =_xludf.BETA.INV(X32,'04_PSA_INPUTS'!H11,'04_PSA_INPUTS'!I11) -> #NAME? | I32: =D32+B32*F32+'01_INPUTS'!B20 -> #NAME? | J32: =E32+C32*F32+'01_INPUTS'!B21 -> #NAME? | K32: =I32-J32 -> #NAME? | L32: =G32-B32*H32 -> #NAME? | M32: =G32-C32*H32 -> #NAME? | N32: =L32-M32 -> #NAME? | O32: =IF(N32=0,"",K32/N32) -> #NAME? | P32: ='01_INPUTS'!B9*N32-K32 -> #NAME? | Q32: =IF(P32>0,1,0) -> #NAME? | R32: 0.082159915 | S32: 0.6993287 | T32: 0.42707174 | U32: 0.85733852 | V32: 0.65570965 | W32: 0.11014309 | X32: 0.24447316
A33: 32 | B33: =_xludf.BETA.INV(R33,'04_PSA_INPUTS'!H5,'04_PSA_INPUTS'!I5) -> #NAME? | C33: =_xludf.BETA.INV(S33,'04_PSA_INPUTS'!H6,'04_PSA_INPUTS'!I6) -> #NAME? | D33: =_xludf.GAMMA.INV(T33,'04_PSA_INPUTS'!H7,'04_PSA_INPUTS'!I7) -> #NAME? | E33: =_xludf.GAMMA.INV(U33,'04_PSA_INPUTS'!H8,'04_PSA_INPUTS'!I8) -> #NAME? | F33: =_xludf.GAMMA.INV(V33,'04_PSA_INPUTS'!H9,'04_PSA_INPUTS'!I9) -> #NAME? | G33: =_xludf.BETA.INV(W33,'04_PSA_INPUTS'!H10,'04_PSA_INPUTS'!I10) -> #NAME? | H33: =_xludf.BETA.INV(X33,'04_PSA_INPUTS'!H11,'04_PSA_INPUTS'!I11) -> #NAME? | I33: =D33+B33*F33+'01_INPUTS'!B20 -> #NAME? | J33: =E33+C33*F33+'01_INPUTS'!B21 -> #NAME? | K33: =I33-J33 -> #NAME? | L33: =G33-B33*H33 -> #NAME? | M33: =G33-C33*H33 -> #NAME? | N33: =L33-M33 -> #NAME? | O33: =IF(N33=0,"",K33/N33) -> #NAME? | P33: ='01_INPUTS'!B9*N33-K33 -> #NAME? | Q33: =IF(P33>0,1,0) -> #NAME? | R33: 0.52799638 | S33: 0.43523017 | T33: 0.37641143 | U33: 0.20478291 | V33: 0.13294651 | W33: 0.13275171 | X33: 0.46114236
A34: 33 | B34: =_xludf.BETA.INV(R34,'04_PSA_INPUTS'!H5,'04_PSA_INPUTS'!I5) -> #NAME? | C34: =_xludf.BETA.INV(S34,'04_PSA_INPUTS'!H6,'04_PSA_INPUTS'!I6) -> #NAME? | D34: =_xludf.GAMMA.INV(T34,'04_PSA_INPUTS'!H7,'04_PSA_INPUTS'!I7) -> #NAME? | E34: =_xludf.GAMMA.INV(U34,'04_PSA_INPUTS'!H8,'04_PSA_INPUTS'!I8) -> #NAME? | F34: =_xludf.GAMMA.INV(V34,'04_PSA_INPUTS'!H9,'04_PSA_INPUTS'!I9) -> #NAME? | G34: =_xludf.BETA.INV(W34,'04_PSA_INPUTS'!H10,'04_PSA_INPUTS'!I10) -> #NAME? | H34: =_xludf.BETA.INV(X34,'04_PSA_INPUTS'!H11,'04_PSA_INPUTS'!I11) -> #NAME? | I34: =D34+B34*F34+'01_INPUTS'!B20 -> #NAME? | J34: =E34+C34*F34+'01_INPUTS'!B21 -> #NAME? | K34: =I34-J34 -> #NAME? | L34: =G34-B34*H34 -> #NAME? | M34: =G34-C34*H34 -> #NAME? | N34: =L34-M34 -> #NAME? | O34: =IF(N34=0,"",K34/N34) -> #NAME? | P34: ='01_INPUTS'!B9*N34-K34 -> #NAME? | Q34: =IF(P34>0,1,0) -> #NAME? | R34: 0.95489144 | S34: 0.43646426 | T34: 0.068110791 | U34: 0.40751075 | V34: 0.84810984 | W34: 0.24183545 | X34: 0.1792598
A35: 34 | B35: =_xludf.BETA.INV(R35,'04_PSA_INPUTS'!H5,'04_PSA_INPUTS'!I5) -> #NAME? | C35: =_xludf.BETA.INV(S35,'04_PSA_INPUTS'!H6,'04_PSA_INPUTS'!I6) -> #NAME? | D35: =_xludf.GAMMA.INV(T35,'04_PSA_INPUTS'!H7,'04_PSA_INPUTS'!I7) -> #NAME? | E35: =_xludf.GAMMA.INV(U35,'04_PSA_INPUTS'!H8,'04_PSA_INPUTS'!I8) -> #NAME? | F35: =_xludf.GAMMA.INV(V35,'04_PSA_INPUTS'!H9,'04_PSA_INPUTS'!I9) -> #NAME? | G35: =_xludf.BETA.INV(W35,'04_PSA_INPUTS'!H10,'04_PSA_INPUTS'!I10) -> #NAME? | H35: =_xludf.BETA.INV(X35,'04_PSA_INPUTS'!H11,'04_PSA_INPUTS'!I11) -> #NAME? | I35: =D35+B35*F35+'01_INPUTS'!B20 -> #NAME? | J35: =E35+C35*F35+'01_INPUTS'!B21 -> #NAME? | K35: =I35-J35 -> #NAME? | L35: =G35-B35*H35 -> #NAME? | M35: =G35-C35*H35 -> #NAME? | N35: =L35-M35 -> #NAME? | O35: =IF(N35=0,"",K35/N35) -> #NAME? | P35: ='01_INPUTS'!B9*N35-K35 -> #NAME? | Q35: =IF(P35>0,1,0) -> #NAME? | R35: 0.14766824 | S35: 0.68838141 | T35: 0.17783968 | U35: 0.81518968 | V35: 0.1000904 | W35: 0.061739107 | X35: 0.10379789
A36: 35 | B36: =_xludf.BETA.INV(R36,'04_PSA_INPUTS'!H5,'04_PSA_INPUTS'!I5) -> #NAME? | C36: =_xludf.BETA.INV(S36,'04_PSA_INPUTS'!H6,'04_PSA_INPUTS'!I6) -> #NAME? | D36: =_xludf.GAMMA.INV(T36,'04_PSA_INPUTS'!H7,'04_PSA_INPUTS'!I7) -> #NAME? | E36: =_xludf.GAMMA.INV(U36,'04_PSA_INPUTS'!H8,'04_PSA_INPUTS'!I8) -> #NAME? | F36: =_xludf.GAMMA.INV(V36,'04_PSA_INPUTS'!H9,'04_PSA_INPUTS'!I9) -> #NAME? | G36: =_xludf.BETA.INV(W36,'04_PSA_INPUTS'!H10,'04_PSA_INPUTS'!I10) -> #NAME? | H36: =_xludf.BETA.INV(X36,'04_PSA_INPUTS'!H11,'04_PSA_INPUTS'!I11) -> #NAME? | I36: =D36+B36*F36+'01_INPUTS'!B20 -> #NAME? | J36: =E36+C36*F36+'01_INPUTS'!B21 -> #NAME? | K36: =I36-J36 -> #NAME? | L36: =G36-B36*H36 -> #NAME? | M36: =G36-C36*H36 -> #NAME? | N36: =L36-M36 -> #NAME? | O36: =IF(N36=0,"",K36/N36) -> #NAME? | P36: ='01_INPUTS'!B9*N36-K36 -> #NAME? | Q36: =IF(P36>0,1,0) -> #NAME? | R36: 0.49467662 | S36: 0.58229837 | T36: 0.48921708 | U36: 0.47409887 | V36: 0.99543186 | W36: 0.26044876 | X36: 0.7436664
A37: 36 | B37: =_xludf.BETA.INV(R37,'04_PSA_INPUTS'!H5,'04_PSA_INPUTS'!I5) -> #NAME? | C37: =_xludf.BETA.INV(S37,'04_PSA_INPUTS'!H6,'04_PSA_INPUTS'!I6) -> #NAME? | D37: =_xludf.GAMMA.INV(T37,'04_PSA_INPUTS'!H7,'04_PSA_INPUTS'!I7) -> #NAME? | E37: =_xludf.GAMMA.INV(U37,'04_PSA_INPUTS'!H8,'04_PSA_INPUTS'!I8) -> #NAME? | F37: =_xludf.GAMMA.INV(V37,'04_PSA_INPUTS'!H9,'04_PSA_INPUTS'!I9) -> #NAME? | G37: =_xludf.BETA.INV(W37,'04_PSA_INPUTS'!H10,'04_PSA_INPUTS'!I10) -> #NAME? | H37: =_xludf.BETA.INV(X37,'04_PSA_INPUTS'!H11,'04_PSA_INPUTS'!I11) -> #NAME? | I37: =D37+B37*F37+'01_INPUTS'!B20 -> #NAME? | J37: =E37+C37*F37+'01_INPUTS'!B21 -> #NAME? | K37: =I37-J37 -> #NAME? | L37: =G37-B37*H37 -> #NAME? | M37: =G37-C37*H37 -> #NAME? | N37: =L37-M37 -> #NAME? | O37: =IF(N37=0,"",K37/N37) -> #NAME? | P37: ='01_INPUTS'!B9*N37-K37 -> #NAME? | Q37: =IF(P37>0,1,0) -> #NAME? | R37: 0.60412116 | S37: 0.15550622 | T37: 0.49846658 | U37: 0.82374349 | V37: 0.18869707 | W37: 0.14194688 | X37: 0.76720174
A38: 37 | B38: =_xludf.BETA.INV(R38,'04_PSA_INPUTS'!H5,'04_PSA_INPUTS'!I5) -> #NAME? | C38: =_xludf.BETA.INV(S38,'04_PSA_INPUTS'!H6,'04_PSA_INPUTS'!I6) -> #NAME? | D38: =_xludf.GAMMA.INV(T38,'04_PSA_INPUTS'!H7,'04_PSA_INPUTS'!I7) -> #NAME? | E38: =_xludf.GAMMA.INV(U38,'04_PSA_INPUTS'!H8,'04_PSA_INPUTS'!I8) -> #NAME? | F38: =_xludf.GAMMA.INV(V38,'04_PSA_INPUTS'!H9,'04_PSA_INPUTS'!I9) -> #NAME? | G38: =_xludf.BETA.INV(W38,'04_PSA_INPUTS'!H10,'04_PSA_INPUTS'!I10) -> #NAME? | H38: =_xludf.BETA.INV(X38,'04_PSA_INPUTS'!H11,'04_PSA_INPUTS'!I11) -> #NAME? | I38: =D38+B38*F38+'01_INPUTS'!B20 -> #NAME? | J38: =E38+C38*F38+'01_INPUTS'!B21 -> #NAME? | K38: =I38-J38 -> #NAME? | L38: =G38-B38*H38 -> #NAME? | M38: =G38-C38*H38 -> #NAME? | N38: =L38-M38 -> #NAME? | O38: =IF(N38=0,"",K38/N38) -> #NAME? | P38: ='01_INPUTS'!B9*N38-K38 -> #NAME? | Q38: =IF(P38>0,1,0) -> #NAME? | R38: 0.74376619 | S38: 0.46219565 | T38: 0.71656598 | U38: 0.59107143 | V38: 0.93136511 | W38: 0.54263121 | X38: 0.77302049
A39: 38 | B39: =_xludf.BETA.INV(R39,'04_PSA_INPUTS'!H5,'04_PSA_INPUTS'!I5) -> #NAME? | C39: =_xludf.BETA.INV(S39,'04_PSA_INPUTS'!H6,'04_PSA_INPUTS'!I6) -> #NAME? | D39: =_xludf.GAMMA.INV(T39,'04_PSA_INPUTS'!H7,'04_PSA_INPUTS'!I7) -> #NAME? | E39: =_xludf.GAMMA.INV(U39,'04_PSA_INPUTS'!H8,'04_PSA_INPUTS'!I8) -> #NAME? | F39: =_xludf.GAMMA.INV(V39,'04_PSA_INPUTS'!H9,'04_PSA_INPUTS'!I9) -> #NAME? | G39: =_xludf.BETA.INV(W39,'04_PSA_INPUTS'!H10,'04_PSA_INPUTS'!I10) -> #NAME? | H39: =_xludf.BETA.INV(X39,'04_PSA_INPUTS'!H11,'04_PSA_INPUTS'!I11) -> #NAME? | I39: =D39+B39*F39+'01_INPUTS'!B20 -> #NAME? | J39: =E39+C39*F39+'01_INPUTS'!B21 -> #NAME? | K39: =I39-J39 -> #NAME? | L39: =G39-B39*H39 -> #NAME? | M39: =G39-C39*H39 -> #NAME? | N39: =L39-M39 -> #NAME? | O39: =IF(N39=0,"",K39/N39) -> #NAME? | P39: ='01_INPUTS'!B9*N39-K39 -> #NAME? | Q39: =IF(P39>0,1,0) -> #NAME? | R39: 0.76275777 | S39: 0.26780302 | T39: 0.7781536 | U39: 0.04043909 | V39: 0.32147946 | W39: 0.83398546 | X39: 0.8773302
A40: 39 | B40: =_xludf.BETA.INV(R40,'04_PSA_INPUTS'!H5,'04_PSA_INPUTS'!I5) -> #NAME? | C40: =_xludf.BETA.INV(S40,'04_PSA_INPUTS'!H6,'04_PSA_INPUTS'!I6) -> #NAME? | D40: =_xludf.GAMMA.INV(T40,'04_PSA_INPUTS'!H7,'04_PSA_INPUTS'!I7) -> #NAME? | E40: =_xludf.GAMMA.INV(U40,'04_PSA_INPUTS'!H8,'04_PSA_INPUTS'!I8) -> #NAME? | F40: =_xludf.GAMMA.INV(V40,'04_PSA_INPUTS'!H9,'04_PSA_INPUTS'!I9) -> #NAME? | G40: =_xludf.BETA.INV(W40,'04_PSA_INPUTS'!H10,'04_PSA_INPUTS'!I10) -> #NAME? | H40: =_xludf.BETA.INV(X40,'04_PSA_INPUTS'!H11,'04_PSA_INPUTS'!I11) -> #NAME? | I40: =D40+B40*F40+'01_INPUTS'!B20 -> #NAME? | J40: =E40+C40*F40+'01_INPUTS'!B21 -> #NAME? | K40: =I40-J40 -> #NAME? | L40: =G40-B40*H40 -> #NAME? | M40: =G40-C40*H40 -> #NAME? | N40: =L40-M40 -> #NAME? | O40: =IF(N40=0,"",K40/N40) -> #NAME? | P40: ='01_INPUTS'!B9*N40-K40 -> #NAME? | Q40: =IF(P40>0,1,0) -> #NAME? | R40: 0.59351966 | S40: 0.17065936 | T40: 0.46072244 | U40: 0.98115048 | V40: 0.10345178 | W40: 0.011356538 | X40: 0.50443445
A41: 40 | B41: =_xludf.BETA.INV(R41,'04_PSA_INPUTS'!H5,'04_PSA_INPUTS'!I5) -> #NAME? | C41: =_xludf.BETA.INV(S41,'04_PSA_INPUTS'!H6,'04_PSA_INPUTS'!I6) -> #NAME? | D41: =_xludf.GAMMA.INV(T41,'04_PSA_INPUTS'!H7,'04_PSA_INPUTS'!I7) -> #NAME? | E41: =_xludf.GAMMA.INV(U41,'04_PSA_INPUTS'!H8,'04_PSA_INPUTS'!I8) -> #NAME? | F41: =_xludf.GAMMA.INV(V41,'04_PSA_INPUTS'!H9,'04_PSA_INPUTS'!I9) -> #NAME? | G41: =_xludf.BETA.INV(W41,'04_PSA_INPUTS'!H10,'04_PSA_INPUTS'!I10) -> #NAME? | H41: =_xludf.BETA.INV(X41,'04_PSA_INPUTS'!H11,'04_PSA_INPUTS'!I11) -> #NAME? | I41: =D41+B41*F41+'01_INPUTS'!B20 -> #NAME? | J41: =E41+C41*F41+'01_INPUTS'!B21 -> #NAME? | K41: =I41-J41 -> #NAME? | L41: =G41-B41*H41 -> #NAME? | M41: =G41-C41*H41 -> #NAME? | N41: =L41-M41 -> #NAME? | O41: =IF(N41=0,"",K41/N41) -> #NAME? | P41: ='01_INPUTS'!B9*N41-K41 -> #NAME? | Q41: =IF(P41>0,1,0) -> #NAME? | R41: 0.074437336 | S41: 0.76721721 | T41: 0.7992701 | U41: 0.90725125 | V41: 0.049952091 | W41: 0.12805839 | X41: 0.86852931
A42: 41 | B42: =_xludf.BETA.INV(R42,'04_PSA_INPUTS'!H5,'04_PSA_INPUTS'!I5) -> #NAME? | C42: =_xludf.BETA.INV(S42,'04_PSA_INPUTS'!H6,'04_PSA_INPUTS'!I6) -> #NAME? | D42: =_xludf.GAMMA.INV(T42,'04_PSA_INPUTS'!H7,'04_PSA_INPUTS'!I7) -> #NAME? | E42: =_xludf.GAMMA.INV(U42,'04_PSA_INPUTS'!H8,'04_PSA_INPUTS'!I8) -> #NAME? | F42: =_xludf.GAMMA.INV(V42,'04_PSA_INPUTS'!H9,'04_PSA_INPUTS'!I9) -> #NAME? | G42: =_xludf.BETA.INV(W42,'04_PSA_INPUTS'!H10,'04_PSA_INPUTS'!I10) -> #NAME? | H42: =_xludf.BETA.INV(X42,'04_PSA_INPUTS'!H11,'04_PSA_INPUTS'!I11) -> #NAME? | I42: =D42+B42*F42+'01_INPUTS'!B20 -> #NAME? | J42: =E42+C42*F42+'01_INPUTS'!B21 -> #NAME? | K42: =I42-J42 -> #NAME? | L42: =G42-B42*H42 -> #NAME? | M42: =G42-C42*H42 -> #NAME? | N42: =L42-M42 -> #NAME? | O42: =IF(N42=0,"",K42/N42) -> #NAME? | P42: ='01_INPUTS'!B9*N42-K42 -> #NAME? | Q42: =IF(P42>0,1,0) -> #NAME? | R42: 0.49597465 | S42: 0.17420338 | T42: 0.85655248 | U42: 0.85669778 | V42: 0.90952184 | W42: 0.54948515 | X42: 0.0068326353
A43: 42 | B43: =_xludf.BETA.INV(R43,'04_PSA_INPUTS'!H5,'04_PSA_INPUTS'!I5) -> #NAME? | C43: =_xludf.BETA.INV(S43,'04_PSA_INPUTS'!H6,'04_PSA_INPUTS'!I6) -> #NAME? | D43: =_xludf.GAMMA.INV(T43,'04_PSA_INPUTS'!H7,'04_PSA_INPUTS'!I7) -> #NAME? | E43: =_xludf.GAMMA.INV(U43,'04_PSA_INPUTS'!H8,'04_PSA_INPUTS'!I8) -> #NAME? | F43: =_xludf.GAMMA.INV(V43,'04_PSA_INPUTS'!H9,'04_PSA_INPUTS'!I9) -> #NAME? | G43: =_xludf.BETA.INV(W43,'04_PSA_INPUTS'!H10,'04_PSA_INPUTS'!I10) -> #NAME? | H43: =_xludf.BETA.INV(X43,'04_PSA_INPUTS'!H11,'04_PSA_INPUTS'!I11) -> #NAME? | I43: =D43+B43*F43+'01_INPUTS'!B20 -> #NAME? | J43: =E43+C43*F43+'01_INPUTS'!B21 -> #NAME? | K43: =I43-J43 -> #NAME? | L43: =G43-B43*H43 -> #NAME? | M43: =G43-C43*H43 -> #NAME? | N43: =L43-M43 -> #NAME? | O43: =IF(N43=0,"",K43/N43) -> #NAME? | P43: ='01_INPUTS'!B9*N43-K43 -> #NAME? | Q43: =IF(P43>0,1,0) -> #NAME? | R43: 0.04082392 | S43: 0.48412317 | T43: 0.45624019 | U43: 0.99950072 | V43: 0.54267196 | W43: 0.87032543 | X43: 0.90030532
A44: 43 | B44: =_xludf.BETA.INV(R44,'04_PSA_INPUTS'!H5,'04_PSA_INPUTS'!I5) -> #NAME? | C44: =_xludf.BETA.INV(S44,'04_PSA_INPUTS'!H6,'04_PSA_INPUTS'!I6) -> #NAME? | D44: =_xludf.GAMMA.INV(T44,'04_PSA_INPUTS'!H7,'04_PSA_INPUTS'!I7) -> #NAME? | E44: =_xludf.GAMMA.INV(U44,'04_PSA_INPUTS'!H8,'04_PSA_INPUTS'!I8) -> #NAME? | F44: =_xludf.GAMMA.INV(V44,'04_PSA_INPUTS'!H9,'04_PSA_INPUTS'!I9) -> #NAME? | G44: =_xludf.BETA.INV(W44,'04_PSA_INPUTS'!H10,'04_PSA_INPUTS'!I10) -> #NAME? | H44: =_xludf.BETA.INV(X44,'04_PSA_INPUTS'!H11,'04_PSA_INPUTS'!I11) -> #NAME? | I44: =D44+B44*F44+'01_INPUTS'!B20 -> #NAME? | J44: =E44+C44*F44+'01_INPUTS'!B21 -> #NAME? | K44: =I44-J44 -> #NAME? | L44: =G44-B44*H44 -> #NAME? | M44: =G44-C44*H44 -> #NAME? | N44: =L44-M44 -> #NAME? | O44: =IF(N44=0,"",K44/N44) -> #NAME? | P44: ='01_INPUTS'!B9*N44-K44 -> #NAME? | Q44: =IF(P44>0,1,0) -> #NAME? | R44: 0.84574623 | S44: 0.93441634 | T44: 0.6861318 | U44: 0.66648833 | V44: 0.32454316 | W44: 0.69199445 | X44: 0.17390586
A45: 44 | B45: =_xludf.BETA.INV(R45,'04_PSA_INPUTS'!H5,'04_PSA_INPUTS'!I5) -> #NAME? | C45: =_xludf.BETA.INV(S45,'04_PSA_INPUTS'!H6,'04_PSA_INPUTS'!I6) -> #NAME? | D45: =_xludf.GAMMA.INV(T45,'04_PSA_INPUTS'!H7,'04_PSA_INPUTS'!I7) -> #NAME? | E45: =_xludf.GAMMA.INV(U45,'04_PSA_INPUTS'!H8,'04_PSA_INPUTS'!I8) -> #NAME? | F45: =_xludf.GAMMA.INV(V45,'04_PSA_INPUTS'!H9,'04_PSA_INPUTS'!I9) -> #NAME? | G45: =_xludf.BETA.INV(W45,'04_PSA_INPUTS'!H10,'04_PSA_INPUTS'!I10) -> #NAME? | H45: =_xludf.BETA.INV(X45,'04_PSA_INPUTS'!H11,'04_PSA_INPUTS'!I11) -> #NAME? | I45: =D45+B45*F45+'01_INPUTS'!B20 -> #NAME? | J45: =E45+C45*F45+'01_INPUTS'!B21 -> #NAME? | K45: =I45-J45 -> #NAME? | L45: =G45-B45*H45 -> #NAME? | M45: =G45-C45*H45 -> #NAME? | N45: =L45-M45 -> #NAME? | O45: =IF(N45=0,"",K45/N45) -> #NAME? | P45: ='01_INPUTS'!B9*N45-K45 -> #NAME? | Q45: =IF(P45>0,1,0) -> #NAME? | R45: 0.011109689 | S45: 0.3086985 | T45: 0.53970591 | U45: 0.46938417 | V45: 0.75554284 | W45: 0.79871113 | X45: 0.40314716
A46: 45 | B46: =_xludf.BETA.INV(R46,'04_PSA_INPUTS'!H5,'04_PSA_INPUTS'!I5) -> #NAME? | C46: =_xludf.BETA.INV(S46,'04_PSA_INPUTS'!H6,'04_PSA_INPUTS'!I6) -> #NAME? | D46: =_xludf.GAMMA.INV(T46,'04_PSA_INPUTS'!H7,'04_PSA_INPUTS'!I7) -> #NAME? | E46: =_xludf.GAMMA.INV(U46,'04_PSA_INPUTS'!H8,'04_PSA_INPUTS'!I8) -> #NAME? | F46: =_xludf.GAMMA.INV(V46,'04_PSA_INPUTS'!H9,'04_PSA_INPUTS'!I9) -> #NAME? | G46: =_xludf.BETA.INV(W46,'04_PSA_INPUTS'!H10,'04_PSA_INPUTS'!I10) -> #NAME? | H46: =_xludf.BETA.INV(X46,'04_PSA_INPUTS'!H11,'04_PSA_INPUTS'!I11) -> #NAME? | I46: =D46+B46*F46+'01_INPUTS'!B20 -> #NAME? | J46: =E46+C46*F46+'01_INPUTS'!B21 -> #NAME? | K46: =I46-J46 -> #NAME? | L46: =G46-B46*H46 -> #NAME? | M46: =G46-C46*H46 -> #NAME? | N46: =L46-M46 -> #NAME? | O46: =IF(N46=0,"",K46/N46) -> #NAME? | P46: ='01_INPUTS'!B9*N46-K46 -> #NAME? | Q46: =IF(P46>0,1,0) -> #NAME? | R46: 0.45562758 | S46: 0.25202951 | T46: 0.77392007 | U46: 0.2425724 | V46: 0.66254794 | W46: 0.080804351 | X46: 0.68936024
A47: 46 | B47: =_xludf.BETA.INV(R47,'04_PSA_INPUTS'!H5,'04_PSA_INPUTS'!I5) -> #NAME? | C47: =_xludf.BETA.INV(S47,'04_PSA_INPUTS'!H6,'04_PSA_INPUTS'!I6) -> #NAME? | D47: =_xludf.GAMMA.INV(T47,'04_PSA_INPUTS'!H7,'04_PSA_INPUTS'!I7) -> #NAME? | E47: =_xludf.GAMMA.INV(U47,'04_PSA_INPUTS'!H8,'04_PSA_INPUTS'!I8) -> #NAME? | F47: =_xludf.GAMMA.INV(V47,'04_PSA_INPUTS'!H9,'04_PSA_INPUTS'!I9) -> #NAME? | G47: =_xludf.BETA.INV(W47,'04_PSA_INPUTS'!H10,'04_PSA_INPUTS'!I10) -> #NAME? | H47: =_xludf.BETA.INV(X47,'04_PSA_INPUTS'!H11,'04_PSA_INPUTS'!I11) -> #NAME? | I47: =D47+B47*F47+'01_INPUTS'!B20 -> #NAME? | J47: =E47+C47*F47+'01_INPUTS'!B21 -> #NAME? | K47: =I47-J47 -> #NAME? | L47: =G47-B47*H47 -> #NAME? | M47: =G47-C47*H47 -> #NAME? | N47: =L47-M47 -> #NAME? | O47: =IF(N47=0,"",K47/N47) -> #NAME? | P47: ='01_INPUTS'!B9*N47-K47 -> #NAME? | Q47: =IF(P47>0,1,0) -> #NAME? | R47: 0.87118939 | S47: 0.71784606 | T47: 0.52762261 | U47: 0.46673024 | V47: 0.80411013 | W47: 0.080194481 | X47: 0.65018765
A48: 47 | B48: =_xludf.BETA.INV(R48,'04_PSA_INPUTS'!H5,'04_PSA_INPUTS'!I5) -> #NAME? | C48: =_xludf.BETA.INV(S48,'04_PSA_INPUTS'!H6,'04_PSA_INPUTS'!I6) -> #NAME? | D48: =_xludf.GAMMA.INV(T48,'04_PSA_INPUTS'!H7,'04_PSA_INPUTS'!I7) -> #NAME? | E48: =_xludf.GAMMA.INV(U48,'04_PSA_INPUTS'!H8,'04_PSA_INPUTS'!I8) -> #NAME? | F48: =_xludf.GAMMA.INV(V48,'04_PSA_INPUTS'!H9,'04_PSA_INPUTS'!I9) -> #NAME? | G48: =_xludf.BETA.INV(W48,'04_PSA_INPUTS'!H10,'04_PSA_INPUTS'!I10) -> #NAME? | H48: =_xludf.BETA.INV(X48,'04_PSA_INPUTS'!H11,'04_PSA_INPUTS'!I11) -> #NAME? | I48: =D48+B48*F48+'01_INPUTS'!B20 -> #NAME? | J48: =E48+C48*F48+'01_INPUTS'!B21 -> #NAME? | K48: =I48-J48 -> #NAME? | L48: =G48-B48*H48 -> #NAME? | M48: =G48-C48*H48 -> #NAME? | N48: =L48-M48 -> #NAME? | O48: =IF(N48=0,"",K48/N48) -> #NAME? | P48: ='01_INPUTS'!B9*N48-K48 -> #NAME? | Q48: =IF(P48>0,1,0) -> #NAME? | R48: 0.90631689 | S48: 0.56824507 | T48: 0.96986798 | U48: 0.66655379 | V48: 0.10342008 | W48: 0.8084915 | X48: 0.031404236
A49: 48 | B49: =_xludf.BETA.INV(R49,'04_PSA_INPUTS'!H5,'04_PSA_INPUTS'!I5) -> #NAME? | C49: =_xludf.BETA.INV(S49,'04_PSA_INPUTS'!H6,'04_PSA_INPUTS'!I6) -> #NAME? | D49: =_xludf.GAMMA.INV(T49,'04_PSA_INPUTS'!H7,'04_PSA_INPUTS'!I7) -> #NAME? | E49: =_xludf.GAMMA.INV(U49,'04_PSA_INPUTS'!H8,'04_PSA_INPUTS'!I8) -> #NAME? | F49: =_xludf.GAMMA.INV(V49,'04_PSA_INPUTS'!H9,'04_PSA_INPUTS'!I9) -> #NAME? | G49: =_xludf.BETA.INV(W49,'04_PSA_INPUTS'!H10,'04_PSA_INPUTS'!I10) -> #NAME? | H49: =_xludf.BETA.INV(X49,'04_PSA_INPUTS'!H11,'04_PSA_INPUTS'!I11) -> #NAME? | I49: =D49+B49*F49+'01_INPUTS'!B20 -> #NAME? | J49: =E49+C49*F49+'01_INPUTS'!B21 -> #NAME? | K49: =I49-J49 -> #NAME? | L49: =G49-B49*H49 -> #NAME? | M49: =G49-C49*H49 -> #NAME? | N49: =L49-M49 -> #NAME? | O49: =IF(N49=0,"",K49/N49) -> #NAME? | P49: ='01_INPUTS'!B9*N49-K49 -> #NAME? | Q49: =IF(P49>0,1,0) -> #NAME? | R49: 0.18063207 | S49: 0.17042403 | T49: 0.65821682 | U49: 0.24657928 | V49: 0.32670726 | W49: 0.55209891 | X49: 0.24002123
A50: 49 | B50: =_xludf.BETA.INV(R50,'04_PSA_INPUTS'!H5,'04_PSA_INPUTS'!I5) -> #NAME? | C50: =_xludf.BETA.INV(S50,'04_PSA_INPUTS'!H6,'04_PSA_INPUTS'!I6) -> #NAME? | D50: =_xludf.GAMMA.INV(T50,'04_PSA_INPUTS'!H7,'04_PSA_INPUTS'!I7) -> #NAME? | E50: =_xludf.GAMMA.INV(U50,'04_PSA_INPUTS'!H8,'04_PSA_INPUTS'!I8) -> #NAME? | F50: =_xludf.GAMMA.INV(V50,'04_PSA_INPUTS'!H9,'04_PSA_INPUTS'!I9) -> #NAME? | G50: =_xludf.BETA.INV(W50,'04_PSA_INPUTS'!H10,'04_PSA_INPUTS'!I10) -> #NAME? | H50: =_xludf.BETA.INV(X50,'04_PSA_INPUTS'!H11,'04_PSA_INPUTS'!I11) -> #NAME? | I50: =D50+B50*F50+'01_INPUTS'!B20 -> #NAME? | J50: =E50+C50*F50+'01_INPUTS'!B21 -> #NAME? | K50: =I50-J50 -> #NAME? | L50: =G50-B50*H50 -> #NAME? | M50: =G50-C50*H50 -> #NAME? | N50: =L50-M50 -> #NAME? | O50: =IF(N50=0,"",K50/N50) -> #NAME? | P50: ='01_INPUTS'!B9*N50-K50 -> #NAME? | Q50: =IF(P50>0,1,0) -> #NAME? | R50: 0.31396339 | S50: 0.060174294 | T50: 0.39495469 | U50: 0.81324604 | V50: 0.58812153 | W50: 0.18205279 | X50: 0.1305537
A51: 50 | B51: =_xludf.BETA.INV(R51,'04_PSA_INPUTS'!H5,'04_PSA_INPUTS'!I5) -> #NAME? | C51: =_xludf.BETA.INV(S51,'04_PSA_INPUTS'!H6,'04_PSA_INPUTS'!I6) -> #NAME? | D51: =_xludf.GAMMA.INV(T51,'04_PSA_INPUTS'!H7,'04_PSA_INPUTS'!I7) -> #NAME? | E51: =_xludf.GAMMA.INV(U51,'04_PSA_INPUTS'!H8,'04_PSA_INPUTS'!I8) -> #NAME? | F51: =_xludf.GAMMA.INV(V51,'04_PSA_INPUTS'!H9,'04_PSA_INPUTS'!I9) -> #NAME? | G51: =_xludf.BETA.INV(W51,'04_PSA_INPUTS'!H10,'04_PSA_INPUTS'!I10) -> #NAME? | H51: =_xludf.BETA.INV(X51,'04_PSA_INPUTS'!H11,'04_PSA_INPUTS'!I11) -> #NAME? | I51: =D51+B51*F51+'01_INPUTS'!B20 -> #NAME? | J51: =E51+C51*F51+'01_INPUTS'!B21 -> #NAME? | K51: =I51-J51 -> #NAME? | L51: =G51-B51*H51 -> #NAME? | M51: =G51-C51*H51 -> #NAME? | N51: =L51-M51 -> #NAME? | O51: =IF(N51=0,"",K51/N51) -> #NAME? | P51: ='01_INPUTS'!B9*N51-K51 -> #NAME? | Q51: =IF(P51>0,1,0) -> #NAME? | R51: 0.1789456 | S51: 0.55549007 | T51: 0.66712962 | U51: 0.79957811 | V51: 0.36282129 | W51: 0.69876714 | X51: 0.34037112
A52: 51 | B52: =_xludf.BETA.INV(R52,'04_PSA_INPUTS'!H5,'04_PSA_INPUTS'!I5) -> #NAME? | C52: =_xludf.BETA.INV(S52,'04_PSA_INPUTS'!H6,'04_PSA_INPUTS'!I6) -> #NAME? | D52: =_xludf.GAMMA.INV(T52,'04_PSA_INPUTS'!H7,'04_PSA_INPUTS'!I7) -> #NAME? | E52: =_xludf.GAMMA.INV(U52,'04_PSA_INPUTS'!H8,'04_PSA_INPUTS'!I8) -> #NAME? | F52: =_xludf.GAMMA.INV(V52,'04_PSA_INPUTS'!H9,'04_PSA_INPUTS'!I9) -> #NAME? | G52: =_xludf.BETA.INV(W52,'04_PSA_INPUTS'!H10,'04_PSA_INPUTS'!I10) -> #NAME? | H52: =_xludf.BETA.INV(X52,'04_PSA_INPUTS'!H11,'04_PSA_INPUTS'!I11) -> #NAME? | I52: =D52+B52*F52+'01_INPUTS'!B20 -> #NAME? | J52: =E52+C52*F52+'01_INPUTS'!B21 -> #NAME? | K52: =I52-J52 -> #NAME? | L52: =G52-B52*H52 -> #NAME? | M52: =G52-C52*H52 -> #NAME? | N52: =L52-M52 -> #NAME? | O52: =IF(N52=0,"",K52/N52) -> #NAME? | P52: ='01_INPUTS'!B9*N52-K52 -> #NAME? | Q52: =IF(P52>0,1,0) -> #NAME? | R52: 0.55486464 | S52: 0.20140815 | T52: 0.77938047 | U52: 0.15313884 | V52: 0.60892357 | W52: 0.51522035 | X52: 0.69837221
A53: 52 | B53: =_xludf.BETA.INV(R53,'04_PSA_INPUTS'!H5,'04_PSA_INPUTS'!I5) -> #NAME? | C53: =_xludf.BETA.INV(S53,'04_PSA_INPUTS'!H6,'04_PSA_INPUTS'!I6) -> #NAME? | D53: =_xludf.GAMMA.INV(T53,'04_PSA_INPUTS'!H7,'04_PSA_INPUTS'!I7) -> #NAME? | E53: =_xludf.GAMMA.INV(U53,'04_PSA_INPUTS'!H8,'04_PSA_INPUTS'!I8) -> #NAME? | F53: =_xludf.GAMMA.INV(V53,'04_PSA_INPUTS'!H9,'04_PSA_INPUTS'!I9) -> #NAME? | G53: =_xludf.BETA.INV(W53,'04_PSA_INPUTS'!H10,'04_PSA_INPUTS'!I10) -> #NAME? | H53: =_xludf.BETA.INV(X53,'04_PSA_INPUTS'!H11,'04_PSA_INPUTS'!I11) -> #NAME? | I53: =D53+B53*F53+'01_INPUTS'!B20 -> #NAME? | J53: =E53+C53*F53+'01_INPUTS'!B21 -> #NAME? | K53: =I53-J53 -> #NAME? | L53: =G53-B53*H53 -> #NAME? | M53: =G53-C53*H53 -> #NAME? | N53: =L53-M53 -> #NAME? | O53: =IF(N53=0,"",K53/N53) -> #NAME? | P53: ='01_INPUTS'!B9*N53-K53 -> #NAME? | Q53: =IF(P53>0,1,0) -> #NAME? | R53: 0.75501689 | S53: 0.34746533 | T53: 0.47430621 | U53: 0.00098090246 | V53: 0.98069455 | W53: 0.58520456 | X53: 0.35985811
A54: 53 | B54: =_xludf.BETA.INV(R54,'04_PSA_INPUTS'!H5,'04_PSA_INPUTS'!I5) -> #NAME? | C54: =_xludf.BETA.INV(S54,'04_PSA_INPUTS'!H6,'04_PSA_INPUTS'!I6) -> #NAME? | D54: =_xludf.GAMMA.INV(T54,'04_PSA_INPUTS'!H7,'04_PSA_INPUTS'!I7) -> #NAME? | E54: =_xludf.GAMMA.INV(U54,'04_PSA_INPUTS'!H8,'04_PSA_INPUTS'!I8) -> #NAME? | F54: =_xludf.GAMMA.INV(V54,'04_PSA_INPUTS'!H9,'04_PSA_INPUTS'!I9) -> #NAME? | G54: =_xludf.BETA.INV(W54,'04_PSA_INPUTS'!H10,'04_PSA_INPUTS'!I10) -> #NAME? | H54: =_xludf.BETA.INV(X54,'04_PSA_INPUTS'!H11,'04_PSA_INPUTS'!I11) -> #NAME? | I54: =D54+B54*F54+'01_INPUTS'!B20 -> #NAME? | J54: =E54+C54*F54+'01_INPUTS'!B21 -> #NAME? | K54: =I54-J54 -> #NAME? | L54: =G54-B54*H54 -> #NAME? | M54: =G54-C54*H54 -> #NAME? | N54: =L54-M54 -> #NAME? | O54: =IF(N54=0,"",K54/N54) -> #NAME? | P54: ='01_INPUTS'!B9*N54-K54 -> #NAME? | Q54: =IF(P54>0,1,0) -> #NAME? | R54: 0.59172249 | S54: 0.98078519 | T54: 0.42449976 | U54: 0.53253493 | V54: 0.38330035 | W54: 0.37659679 | X54: 0.19802844
A55: 54 | B55: =_xludf.BETA.INV(R55,'04_PSA_INPUTS'!H5,'04_PSA_INPUTS'!I5) -> #NAME? | C55: =_xludf.BETA.INV(S55,'04_PSA_INPUTS'!H6,'04_PSA_INPUTS'!I6) -> #NAME? | D55: =_xludf.GAMMA.INV(T55,'04_PSA_INPUTS'!H7,'04_PSA_INPUTS'!I7) -> #NAME? | E55: =_xludf.GAMMA.INV(U55,'04_PSA_INPUTS'!H8,'04_PSA_INPUTS'!I8) -> #NAME? | F55: =_xludf.GAMMA.INV(V55,'04_PSA_INPUTS'!H9,'04_PSA_INPUTS'!I9) -> #NAME? | G55: =_xludf.BETA.INV(W55,'04_PSA_INPUTS'!H10,'04_PSA_INPUTS'!I10) -> #NAME? | H55: =_xludf.BETA.INV(X55,'04_PSA_INPUTS'!H11,'04_PSA_INPUTS'!I11) -> #NAME? | I55: =D55+B55*F55+'01_INPUTS'!B20 -> #NAME? | J55: =E55+C55*F55+'01_INPUTS'!B21 -> #NAME? | K55: =I55-J55 -> #NAME? | L55: =G55-B55*H55 -> #NAME? | M55: =G55-C55*H55 -> #NAME? | N55: =L55-M55 -> #NAME? | O55: =IF(N55=0,"",K55/N55) -> #NAME? | P55: ='01_INPUTS'!B9*N55-K55 -> #NAME? | Q55: =IF(P55>0,1,0) -> #NAME? | R55: 0.78640507 | S55: 0.44734117 | T55: 0.31749341 | U55: 0.67870913 | V55: 0.35230959 | W55: 0.28834725 | X55: 0.78811098
A56: 55 | B56: =_xludf.BETA.INV(R56,'04_PSA_INPUTS'!H5,'04_PSA_INPUTS'!I5) -> #NAME? | C56: =_xludf.BETA.INV(S56,'04_PSA_INPUTS'!H6,'04_PSA_INPUTS'!I6) -> #NAME? | D56: =_xludf.GAMMA.INV(T56,'04_PSA_INPUTS'!H7,'04_PSA_INPUTS'!I7) -> #NAME? | E56: =_xludf.GAMMA.INV(U56,'04_PSA_INPUTS'!H8,'04_PSA_INPUTS'!I8) -> #NAME? | F56: =_xludf.GAMMA.INV(V56,'04_PSA_INPUTS'!H9,'04_PSA_INPUTS'!I9) -> #NAME? | G56: =_xludf.BETA.INV(W56,'04_PSA_INPUTS'!H10,'04_PSA_INPUTS'!I10) -> #NAME? | H56: =_xludf.BETA.INV(X56,'04_PSA_INPUTS'!H11,'04_PSA_INPUTS'!I11) -> #NAME? | I56: =D56+B56*F56+'01_INPUTS'!B20 -> #NAME? | J56: =E56+C56*F56+'01_INPUTS'!B21 -> #NAME? | K56: =I56-J56 -> #NAME? | L56: =G56-B56*H56 -> #NAME? | M56: =G56-C56*H56 -> #NAME? | N56: =L56-M56 -> #NAME? | O56: =IF(N56=0,"",K56/N56) -> #NAME? | P56: ='01_INPUTS'!B9*N56-K56 -> #NAME? | Q56: =IF(P56>0,1,0) -> #NAME? | R56: 0.67895142 | S56: 0.92833777 | T56: 0.43943786 | U56: 0.18144326 | V56: 0.83125699 | W56: 0.82809917 | X56: 0.8670095
A57: 56 | B57: =_xludf.BETA.INV(R57,'04_PSA_INPUTS'!H5,'04_PSA_INPUTS'!I5) -> #NAME? | C57: =_xludf.BETA.INV(S57,'04_PSA_INPUTS'!H6,'04_PSA_INPUTS'!I6) -> #NAME? | D57: =_xludf.GAMMA.INV(T57,'04_PSA_INPUTS'!H7,'04_PSA_INPUTS'!I7) -> #NAME? | E57: =_xludf.GAMMA.INV(U57,'04_PSA_INPUTS'!H8,'04_PSA_INPUTS'!I8) -> #NAME? | F57: =_xludf.GAMMA.INV(V57,'04_PSA_INPUTS'!H9,'04_PSA_INPUTS'!I9) -> #NAME? | G57: =_xludf.BETA.INV(W57,'04_PSA_INPUTS'!H10,'04_PSA_INPUTS'!I10) -> #NAME? | H57: =_xludf.BETA.INV(X57,'04_PSA_INPUTS'!H11,'04_PSA_INPUTS'!I11) -> #NAME? | I57: =D57+B57*F57+'01_INPUTS'!B20 -> #NAME? | J57: =E57+C57*F57+'01_INPUTS'!B21 -> #NAME? | K57: =I57-J57 -> #NAME? | L57: =G57-B57*H57 -> #NAME? | M57: =G57-C57*H57 -> #NAME? | N57: =L57-M57 -> #NAME? | O57: =IF(N57=0,"",K57/N57) -> #NAME? | P57: ='01_INPUTS'!B9*N57-K57 -> #NAME? | Q57: =IF(P57>0,1,0) -> #NAME? | R57: 0.51907592 | S57: 0.81966443 | T57: 0.77577906 | U57: 0.94665283 | V57: 0.03586667 | W57: 0.65024862 | X57: 0.72711969
A58: 57 | B58: =_xludf.BETA.INV(R58,'04_PSA_INPUTS'!H5,'04_PSA_INPUTS'!I5) -> #NAME? | C58: =_xludf.BETA.INV(S58,'04_PSA_INPUTS'!H6,'04_PSA_INPUTS'!I6) -> #NAME? | D58: =_xludf.GAMMA.INV(T58,'04_PSA_INPUTS'!H7,'04_PSA_INPUTS'!I7) -> #NAME? | E58: =_xludf.GAMMA.INV(U58,'04_PSA_INPUTS'!H8,'04_PSA_INPUTS'!I8) -> #NAME? | F58: =_xludf.GAMMA.INV(V58,'04_PSA_INPUTS'!H9,'04_PSA_INPUTS'!I9) -> #NAME? | G58: =_xludf.BETA.INV(W58,'04_PSA_INPUTS'!H10,'04_PSA_INPUTS'!I10) -> #NAME? | H58: =_xludf.BETA.INV(X58,'04_PSA_INPUTS'!H11,'04_PSA_INPUTS'!I11) -> #NAME? | I58: =D58+B58*F58+'01_INPUTS'!B20 -> #NAME? | J58: =E58+C58*F58+'01_INPUTS'!B21 -> #NAME? | K58: =I58-J58 -> #NAME? | L58: =G58-B58*H58 -> #NAME? | M58: =G58-C58*H58 -> #NAME? | N58: =L58-M58 -> #NAME? | O58: =IF(N58=0,"",K58/N58) -> #NAME? | P58: ='01_INPUTS'!B9*N58-K58 -> #NAME? | Q58: =IF(P58>0,1,0) -> #NAME? | R58: 0.25466438 | S58: 0.35338653 | T58: 0.86373068 | U58: 0.69408294 | V58: 0.07698609 | W58: 0.13659955 | X58: 0.011377009
A59: 58 | B59: =_xludf.BETA.INV(R59,'04_PSA_INPUTS'!H5,'04_PSA_INPUTS'!I5) -> #NAME? | C59: =_xludf.BETA.INV(S59,'04_PSA_INPUTS'!H6,'04_PSA_INPUTS'!I6) -> #NAME? | D59: =_xludf.GAMMA.INV(T59,'04_PSA_INPUTS'!H7,'04_PSA_INPUTS'!I7) -> #NAME? | E59: =_xludf.GAMMA.INV(U59,'04_PSA_INPUTS'!H8,'04_PSA_INPUTS'!I8) -> #NAME? | F59: =_xludf.GAMMA.INV(V59,'04_PSA_INPUTS'!H9,'04_PSA_INPUTS'!I9) -> #NAME? | G59: =_xludf.BETA.INV(W59,'04_PSA_INPUTS'!H10,'04_PSA_INPUTS'!I10) -> #NAME? | H59: =_xludf.BETA.INV(X59,'04_PSA_INPUTS'!H11,'04_PSA_INPUTS'!I11) -> #NAME? | I59: =D59+B59*F59+'01_INPUTS'!B20 -> #NAME? | J59: =E59+C59*F59+'01_INPUTS'!B21 -> #NAME? | K59: =I59-J59 -> #NAME? | L59: =G59-B59*H59 -> #NAME? | M59: =G59-C59*H59 -> #NAME? | N59: =L59-M59 -> #NAME? | O59: =IF(N59=0,"",K59/N59) -> #NAME? | P59: ='01_INPUTS'!B9*N59-K59 -> #NAME? | Q59: =IF(P59>0,1,0) -> #NAME? | R59: 0.41649011 | S59: 0.24667618 | T59: 0.89964221 | U59: 0.15754058 | V59: 0.38866488 | W59: 0.24324866 | X59: 0.32197631
A60: 59 | B60: =_xludf.BETA.INV(R60,'04_PSA_INPUTS'!H5,'04_PSA_INPUTS'!I5) -> #NAME? | C60: =_xludf.BETA.INV(S60,'04_PSA_INPUTS'!H6,'04_PSA_INPUTS'!I6) -> #NAME? | D60: =_xludf.GAMMA.INV(T60,'04_PSA_INPUTS'!H7,'04_PSA_INPUTS'!I7) -> #NAME? | E60: =_xludf.GAMMA.INV(U60,'04_PSA_INPUTS'!H8,'04_PSA_INPUTS'!I8) -> #NAME? | F60: =_xludf.GAMMA.INV(V60,'04_PSA_INPUTS'!H9,'04_PSA_INPUTS'!I9) -> #NAME? | G60: =_xludf.BETA.INV(W60,'04_PSA_INPUTS'!H10,'04_PSA_INPUTS'!I10) -> #NAME? | H60: =_xludf.BETA.INV(X60,'04_PSA_INPUTS'!H11,'04_PSA_INPUTS'!I11) -> #NAME? | I60: =D60+B60*F60+'01_INPUTS'!B20 -> #NAME? | J60: =E60+C60*F60+'01_INPUTS'!B21 -> #NAME? | K60: =I60-J60 -> #NAME? | L60: =G60-B60*H60 -> #NAME? | M60: =G60-C60*H60 -> #NAME? | N60: =L60-M60 -> #NAME? | O60: =IF(N60=0,"",K60/N60) -> #NAME? | P60: ='01_INPUTS'!B9*N60-K60 -> #NAME? | Q60: =IF(P60>0,1,0) -> #NAME? | R60: 0.43316418 | S60: 0.40115686 | T60: 0.24451723 | U60: 0.24474287 | V60: 0.086550791 | W60: 0.91894213 | X60: 0.77703833
A61: 60 | B61: =_xludf.BETA.INV(R61,'04_PSA_INPUTS'!H5,'04_PSA_INPUTS'!I5) -> #NAME? | C61: =_xludf.BETA.INV(S61,'04_PSA_INPUTS'!H6,'04_PSA_INPUTS'!I6) -> #NAME? | D61: =_xludf.GAMMA.INV(T61,'04_PSA_INPUTS'!H7,'04_PSA_INPUTS'!I7) -> #NAME? | E61: =_xludf.GAMMA.INV(U61,'04_PSA_INPUTS'!H8,'04_PSA_INPUTS'!I8) -> #NAME? | F61: =_xludf.GAMMA.INV(V61,'04_PSA_INPUTS'!H9,'04_PSA_INPUTS'!I9) -> #NAME? | G61: =_xludf.BETA.INV(W61,'04_PSA_INPUTS'!H10,'04_PSA_INPUTS'!I10) -> #NAME? | H61: =_xludf.BETA.INV(X61,'04_PSA_INPUTS'!H11,'04_PSA_INPUTS'!I11) -> #NAME? | I61: =D61+B61*F61+'01_INPUTS'!B20 -> #NAME? | J61: =E61+C61*F61+'01_INPUTS'!B21 -> #NAME? | K61: =I61-J61 -> #NAME? | L61: =G61-B61*H61 -> #NAME? | M61: =G61-C61*H61 -> #NAME? | N61: =L61-M61 -> #NAME? | O61: =IF(N61=0,"",K61/N61) -> #NAME? | P61: ='01_INPUTS'!B9*N61-K61 -> #NAME? | Q61: =IF(P61>0,1,0) -> #NAME? | R61: 0.61113351 | S61: 0.15778638 | T61: 0.39957055 | U61: 0.43792322 | V61: 0.64917821 | W61: 0.17199392 | X61: 0.4266838
A62: 61 | B62: =_xludf.BETA.INV(R62,'04_PSA_INPUTS'!H5,'04_PSA_INPUTS'!I5) -> #NAME? | C62: =_xludf.BETA.INV(S62,'04_PSA_INPUTS'!H6,'04_PSA_INPUTS'!I6) -> #NAME? | D62: =_xludf.GAMMA.INV(T62,'04_PSA_INPUTS'!H7,'04_PSA_INPUTS'!I7) -> #NAME? | E62: =_xludf.GAMMA.INV(U62,'04_PSA_INPUTS'!H8,'04_PSA_INPUTS'!I8) -> #NAME? | F62: =_xludf.GAMMA.INV(V62,'04_PSA_INPUTS'!H9,'04_PSA_INPUTS'!I9) -> #NAME? | G62: =_xludf.BETA.INV(W62,'04_PSA_INPUTS'!H10,'04_PSA_INPUTS'!I10) -> #NAME? | H62: =_xludf.BETA.INV(X62,'04_PSA_INPUTS'!H11,'04_PSA_INPUTS'!I11) -> #NAME? | I62: =D62+B62*F62+'01_INPUTS'!B20 -> #NAME? | J62: =E62+C62*F62+'01_INPUTS'!B21 -> #NAME? | K62: =I62-J62 -> #NAME? | L62: =G62-B62*H62 -> #NAME? | M62: =G62-C62*H62 -> #NAME? | N62: =L62-M62 -> #NAME? | O62: =IF(N62=0,"",K62/N62) -> #NAME? | P62: ='01_INPUTS'!B9*N62-K62 -> #NAME? | Q62: =IF(P62>0,1,0) -> #NAME? | R62: 0.56730438 | S62: 0.86244463 | T62: 0.50872287 | U62: 0.030980661 | V62: 0.89381461 | W62: 0.58869838 | X62: 0.46892409
A63: 62 | B63: =_xludf.BETA.INV(R63,'04_PSA_INPUTS'!H5,'04_PSA_INPUTS'!I5) -> #NAME? | C63: =_xludf.BETA.INV(S63,'04_PSA_INPUTS'!H6,'04_PSA_INPUTS'!I6) -> #NAME? | D63: =_xludf.GAMMA.INV(T63,'04_PSA_INPUTS'!H7,'04_PSA_INPUTS'!I7) -> #NAME? | E63: =_xludf.GAMMA.INV(U63,'04_PSA_INPUTS'!H8,'04_PSA_INPUTS'!I8) -> #NAME? | F63: =_xludf.GAMMA.INV(V63,'04_PSA_INPUTS'!H9,'04_PSA_INPUTS'!I9) -> #NAME? | G63: =_xludf.BETA.INV(W63,'04_PSA_INPUTS'!H10,'04_PSA_INPUTS'!I10) -> #NAME? | H63: =_xludf.BETA.INV(X63,'04_PSA_INPUTS'!H11,'04_PSA_INPUTS'!I11) -> #NAME? | I63: =D63+B63*F63+'01_INPUTS'!B20 -> #NAME? | J63: =E63+C63*F63+'01_INPUTS'!B21 -> #NAME? | K63: =I63-J63 -> #NAME? | L63: =G63-B63*H63 -> #NAME? | M63: =G63-C63*H63 -> #NAME? | N63: =L63-M63 -> #NAME? | O63: =IF(N63=0,"",K63/N63) -> #NAME? | P63: ='01_INPUTS'!B9*N63-K63 -> #NAME? | Q63: =IF(P63>0,1,0) -> #NAME? | R63: 0.83563791 | S63: 0.77514509 | T63: 0.72633873 | U63: 0.83384934 | V63: 0.12569142 | W63: 0.89504043 | X63: 0.84364396
A64: 63 | B64: =_xludf.BETA.INV(R64,'04_PSA_INPUTS'!H5,'04_PSA_INPUTS'!I5) -> #NAME? | C64: =_xludf.BETA.INV(S64,'04_PSA_INPUTS'!H6,'04_PSA_INPUTS'!I6) -> #NAME? | D64: =_xludf.GAMMA.INV(T64,'04_PSA_INPUTS'!H7,'04_PSA_INPUTS'!I7) -> #NAME? | E64: =_xludf.GAMMA.INV(U64,'04_PSA_INPUTS'!H8,'04_PSA_INPUTS'!I8) -> #NAME? | F64: =_xludf.GAMMA.INV(V64,'04_PSA_INPUTS'!H9,'04_PSA_INPUTS'!I9) -> #NAME? | G64: =_xludf.BETA.INV(W64,'04_PSA_INPUTS'!H10,'04_PSA_INPUTS'!I10) -> #NAME? | H64: =_xludf.BETA.INV(X64,'04_PSA_INPUTS'!H11,'04_PSA_INPUTS'!I11) -> #NAME? | I64: =D64+B64*F64+'01_INPUTS'!B20 -> #NAME? | J64: =E64+C64*F64+'01_INPUTS'!B21 -> #NAME? | K64: =I64-J64 -> #NAME? | L64: =G64-B64*H64 -> #NAME? | M64: =G64-C64*H64 -> #NAME? | N64: =L64-M64 -> #NAME? | O64: =IF(N64=0,"",K64/N64) -> #NAME? | P64: ='01_INPUTS'!B9*N64-K64 -> #NAME? | Q64: =IF(P64>0,1,0) -> #NAME? | R64: 0.93119015 | S64: 0.88722874 | T64: 0.78477487 | U64: 0.0057358735 | V64: 0.44903592 | W64: 0.89305129 | X64: 0.48043634
A65: 64 | B65: =_xludf.BETA.INV(R65,'04_PSA_INPUTS'!H5,'04_PSA_INPUTS'!I5) -> #NAME? | C65: =_xludf.BETA.INV(S65,'04_PSA_INPUTS'!H6,'04_PSA_INPUTS'!I6) -> #NAME? | D65: =_xludf.GAMMA.INV(T65,'04_PSA_INPUTS'!H7,'04_PSA_INPUTS'!I7) -> #NAME? | E65: =_xludf.GAMMA.INV(U65,'04_PSA_INPUTS'!H8,'04_PSA_INPUTS'!I8) -> #NAME? | F65: =_xludf.GAMMA.INV(V65,'04_PSA_INPUTS'!H9,'04_PSA_INPUTS'!I9) -> #NAME? | G65: =_xludf.BETA.INV(W65,'04_PSA_INPUTS'!H10,'04_PSA_INPUTS'!I10) -> #NAME? | H65: =_xludf.BETA.INV(X65,'04_PSA_INPUTS'!H11,'04_PSA_INPUTS'!I11) -> #NAME? | I65: =D65+B65*F65+'01_INPUTS'!B20 -> #NAME? | J65: =E65+C65*F65+'01_INPUTS'!B21 -> #NAME? | K65: =I65-J65 -> #NAME? | L65: =G65-B65*H65 -> #NAME? | M65: =G65-C65*H65 -> #NAME? | N65: =L65-M65 -> #NAME? | O65: =IF(N65=0,"",K65/N65) -> #NAME? | P65: ='01_INPUTS'!B9*N65-K65 -> #NAME? | Q65: =IF(P65>0,1,0) -> #NAME? | R65: 0.73162901 | S65: 0.35835452 | T65: 0.26201555 | U65: 0.31749816 | V65: 0.38806297 | W65: 0.72666654 | X65: 0.78746555
A66: 65 | B66: =_xludf.BETA.INV(R66,'04_PSA_INPUTS'!H5,'04_PSA_INPUTS'!I5) -> #NAME? | C66: =_xludf.BETA.INV(S66,'04_PSA_INPUTS'!H6,'04_PSA_INPUTS'!I6) -> #NAME? | D66: =_xludf.GAMMA.INV(T66,'04_PSA_INPUTS'!H7,'04_PSA_INPUTS'!I7) -> #NAME? | E66: =_xludf.GAMMA.INV(U66,'04_PSA_INPUTS'!H8,'04_PSA_INPUTS'!I8) -> #NAME? | F66: =_xludf.GAMMA.INV(V66,'04_PSA_INPUTS'!H9,'04_PSA_INPUTS'!I9) -> #NAME? | G66: =_xludf.BETA.INV(W66,'04_PSA_INPUTS'!H10,'04_PSA_INPUTS'!I10) -> #NAME? | H66: =_xludf.BETA.INV(X66,'04_PSA_INPUTS'!H11,'04_PSA_INPUTS'!I11) -> #NAME? | I66: =D66+B66*F66+'01_INPUTS'!B20 -> #NAME? | J66: =E66+C66*F66+'01_INPUTS'!B21 -> #NAME? | K66: =I66-J66 -> #NAME? | L66: =G66-B66*H66 -> #NAME? | M66: =G66-C66*H66 -> #NAME? | N66: =L66-M66 -> #NAME? | O66: =IF(N66=0,"",K66/N66) -> #NAME? | P66: ='01_INPUTS'!B9*N66-K66 -> #NAME? | Q66: =IF(P66>0,1,0) -> #NAME? | R66: 0.27252415 | S66: 0.40467032 | T66: 0.20347588 | U66: 0.82032328 | V66: 0.40813953 | W66: 0.77567933 | X66: 0.4298249
A67: 66 | B67: =_xludf.BETA.INV(R67,'04_PSA_INPUTS'!H5,'04_PSA_INPUTS'!I5) -> #NAME? | C67: =_xludf.BETA.INV(S67,'04_PSA_INPUTS'!H6,'04_PSA_INPUTS'!I6) -> #NAME? | D67: =_xludf.GAMMA.INV(T67,'04_PSA_INPUTS'!H7,'04_PSA_INPUTS'!I7) -> #NAME? | E67: =_xludf.GAMMA.INV(U67,'04_PSA_INPUTS'!H8,'04_PSA_INPUTS'!I8) -> #NAME? | F67: =_xludf.GAMMA.INV(V67,'04_PSA_INPUTS'!H9,'04_PSA_INPUTS'!I9) -> #NAME? | G67: =_xludf.BETA.INV(W67,'04_PSA_INPUTS'!H10,'04_PSA_INPUTS'!I10) -> #NAME? | H67: =_xludf.BETA.INV(X67,'04_PSA_INPUTS'!H11,'04_PSA_INPUTS'!I11) -> #NAME? | I67: =D67+B67*F67+'01_INPUTS'!B20 -> #NAME? | J67: =E67+C67*F67+'01_INPUTS'!B21 -> #NAME? | K67: =I67-J67 -> #NAME? | L67: =G67-B67*H67 -> #NAME? | M67: =G67-C67*H67 -> #NAME? | N67: =L67-M67 -> #NAME? | O67: =IF(N67=0,"",K67/N67) -> #NAME? | P67: ='01_INPUTS'!B9*N67-K67 -> #NAME? | Q67: =IF(P67>0,1,0) -> #NAME? | R67: 0.1082287 | S67: 0.82353153 | T67: 0.58657567 | U67: 0.84095138 | V67: 0.82352039 | W67: 0.52329611 | X67: 0.55647392
A68: 67 | B68: =_xludf.BETA.INV(R68,'04_PSA_INPUTS'!H5,'04_PSA_INPUTS'!I5) -> #NAME? | C68: =_xludf.BETA.INV(S68,'04_PSA_INPUTS'!H6,'04_PSA_INPUTS'!I6) -> #NAME? | D68: =_xludf.GAMMA.INV(T68,'04_PSA_INPUTS'!H7,'04_PSA_INPUTS'!I7) -> #NAME? | E68: =_xludf.GAMMA.INV(U68,'04_PSA_INPUTS'!H8,'04_PSA_INPUTS'!I8) -> #NAME? | F68: =_xludf.GAMMA.INV(V68,'04_PSA_INPUTS'!H9,'04_PSA_INPUTS'!I9) -> #NAME? | G68: =_xludf.BETA.INV(W68,'04_PSA_INPUTS'!H10,'04_PSA_INPUTS'!I10) -> #NAME? | H68: =_xludf.BETA.INV(X68,'04_PSA_INPUTS'!H11,'04_PSA_INPUTS'!I11) -> #NAME? | I68: =D68+B68*F68+'01_INPUTS'!B20 -> #NAME? | J68: =E68+C68*F68+'01_INPUTS'!B21 -> #NAME? | K68: =I68-J68 -> #NAME? | L68: =G68-B68*H68 -> #NAME? | M68: =G68-C68*H68 -> #NAME? | N68: =L68-M68 -> #NAME? | O68: =IF(N68=0,"",K68/N68) -> #NAME? | P68: ='01_INPUTS'!B9*N68-K68 -> #NAME? | Q68: =IF(P68>0,1,0) -> #NAME? | R68: 0.58136944 | S68: 0.70913062 | T68: 0.81637198 | U68: 0.46792639 | V68: 0.25429643 | W68: 0.34149194 | X68: 0.66366171
A69: 68 | B69: =_xludf.BETA.INV(R69,'04_PSA_INPUTS'!H5,'04_PSA_INPUTS'!I5) -> #NAME? | C69: =_xludf.BETA.INV(S69,'04_PSA_INPUTS'!H6,'04_PSA_INPUTS'!I6) -> #NAME? | D69: =_xludf.GAMMA.INV(T69,'04_PSA_INPUTS'!H7,'04_PSA_INPUTS'!I7) -> #NAME? | E69: =_xludf.GAMMA.INV(U69,'04_PSA_INPUTS'!H8,'04_PSA_INPUTS'!I8) -> #NAME? | F69: =_xludf.GAMMA.INV(V69,'04_PSA_INPUTS'!H9,'04_PSA_INPUTS'!I9) -> #NAME? | G69: =_xludf.BETA.INV(W69,'04_PSA_INPUTS'!H10,'04_PSA_INPUTS'!I10) -> #NAME? | H69: =_xludf.BETA.INV(X69,'04_PSA_INPUTS'!H11,'04_PSA_INPUTS'!I11) -> #NAME? | I69: =D69+B69*F69+'01_INPUTS'!B20 -> #NAME? | J69: =E69+C69*F69+'01_INPUTS'!B21 -> #NAME? | K69: =I69-J69 -> #NAME? | L69: =G69-B69*H69 -> #NAME? | M69: =G69-C69*H69 -> #NAME? | N69: =L69-M69 -> #NAME? | O69: =IF(N69=0,"",K69/N69) -> #NAME? | P69: ='01_INPUTS'!B9*N69-K69 -> #NAME? | Q69: =IF(P69>0,1,0) -> #NAME? | R69: 0.69440161 | S69: 0.16714953 | T69: 0.46928271 | U69: 0.99592658 | V69: 0.47018159 | W69: 0.52303871 | X69: 0.88944838
A70: 69 | B70: =_xludf.BETA.INV(R70,'04_PSA_INPUTS'!H5,'04_PSA_INPUTS'!I5) -> #NAME? | C70: =_xludf.BETA.INV(S70,'04_PSA_INPUTS'!H6,'04_PSA_INPUTS'!I6) -> #NAME? | D70: =_xludf.GAMMA.INV(T70,'04_PSA_INPUTS'!H7,'04_PSA_INPUTS'!I7) -> #NAME? | E70: =_xludf.GAMMA.INV(U70,'04_PSA_INPUTS'!H8,'04_PSA_INPUTS'!I8) -> #NAME? | F70: =_xludf.GAMMA.INV(V70,'04_PSA_INPUTS'!H9,'04_PSA_INPUTS'!I9) -> #NAME? | G70: =_xludf.BETA.INV(W70,'04_PSA_INPUTS'!H10,'04_PSA_INPUTS'!I10) -> #NAME? | H70: =_xludf.BETA.INV(X70,'04_PSA_INPUTS'!H11,'04_PSA_INPUTS'!I11) -> #NAME? | I70: =D70+B70*F70+'01_INPUTS'!B20 -> #NAME? | J70: =E70+C70*F70+'01_INPUTS'!B21 -> #NAME? | K70: =I70-J70 -> #NAME? | L70: =G70-B70*H70 -> #NAME? | M70: =G70-C70*H70 -> #NAME? | N70: =L70-M70 -> #NAME? | O70: =IF(N70=0,"",K70/N70) -> #NAME? | P70: ='01_INPUTS'!B9*N70-K70 -> #NAME? | Q70: =IF(P70>0,1,0) -> #NAME? | R70: 0.34958903 | S70: 0.68021426 | T70: 0.60820093 | U70: 0.86050507 | V70: 0.62047801 | W70: 0.53810106 | X70: 0.33901381
A71: 70 | B71: =_xludf.BETA.INV(R71,'04_PSA_INPUTS'!H5,'04_PSA_INPUTS'!I5) -> #NAME? | C71: =_xludf.BETA.INV(S71,'04_PSA_INPUTS'!H6,'04_PSA_INPUTS'!I6) -> #NAME? | D71: =_xludf.GAMMA.INV(T71,'04_PSA_INPUTS'!H7,'04_PSA_INPUTS'!I7) -> #NAME? | E71: =_xludf.GAMMA.INV(U71,'04_PSA_INPUTS'!H8,'04_PSA_INPUTS'!I8) -> #NAME? | F71: =_xludf.GAMMA.INV(V71,'04_PSA_INPUTS'!H9,'04_PSA_INPUTS'!I9) -> #NAME? | G71: =_xludf.BETA.INV(W71,'04_PSA_INPUTS'!H10,'04_PSA_INPUTS'!I10) -> #NAME? | H71: =_xludf.BETA.INV(X71,'04_PSA_INPUTS'!H11,'04_PSA_INPUTS'!I11) -> #NAME? | I71: =D71+B71*F71+'01_INPUTS'!B20 -> #NAME? | J71: =E71+C71*F71+'01_INPUTS'!B21 -> #NAME? | K71: =I71-J71 -> #NAME? | L71: =G71-B71*H71 -> #NAME? | M71: =G71-C71*H71 -> #NAME? | N71: =L71-M71 -> #NAME? | O71: =IF(N71=0,"",K71/N71) -> #NAME? | P71: ='01_INPUTS'!B9*N71-K71 -> #NAME? | Q71: =IF(P71>0,1,0) -> #NAME? | R71: 0.12647814 | S71: 0.5143559 | T71: 0.53406879 | U71: 0.75807524 | V71: 0.23983423 | W71: 0.80978548 | X71: 0.21196019
A72: 71 | B72: =_xludf.BETA.INV(R72,'04_PSA_INPUTS'!H5,'04_PSA_INPUTS'!I5) -> #NAME? | C72: =_xludf.BETA.INV(S72,'04_PSA_INPUTS'!H6,'04_PSA_INPUTS'!I6) -> #NAME? | D72: =_xludf.GAMMA.INV(T72,'04_PSA_INPUTS'!H7,'04_PSA_INPUTS'!I7) -> #NAME? | E72: =_xludf.GAMMA.INV(U72,'04_PSA_INPUTS'!H8,'04_PSA_INPUTS'!I8) -> #NAME? | F72: =_xludf.GAMMA.INV(V72,'04_PSA_INPUTS'!H9,'04_PSA_INPUTS'!I9) -> #NAME? | G72: =_xludf.BETA.INV(W72,'04_PSA_INPUTS'!H10,'04_PSA_INPUTS'!I10) -> #NAME? | H72: =_xludf.BETA.INV(X72,'04_PSA_INPUTS'!H11,'04_PSA_INPUTS'!I11) -> #NAME? | I72: =D72+B72*F72+'01_INPUTS'!B20 -> #NAME? | J72: =E72+C72*F72+'01_INPUTS'!B21 -> #NAME? | K72: =I72-J72 -> #NAME? | L72: =G72-B72*H72 -> #NAME? | M72: =G72-C72*H72 -> #NAME? | N72: =L72-M72 -> #NAME? | O72: =IF(N72=0,"",K72/N72) -> #NAME? | P72: ='01_INPUTS'!B9*N72-K72 -> #NAME? | Q72: =IF(P72>0,1,0) -> #NAME? | R72: 0.47880234 | S72: 0.22217025 | T72: 0.35433194 | U72: 0.6768139 | V72: 0.012228807 | W72: 0.63417518 | X72: 0.50872813
A73: 72 | B73: =_xludf.BETA.INV(R73,'04_PSA_INPUTS'!H5,'04_PSA_INPUTS'!I5) -> #NAME? | C73: =_xludf.BETA.INV(S73,'04_PSA_INPUTS'!H6,'04_PSA_INPUTS'!I6) -> #NAME? | D73: =_xludf.GAMMA.INV(T73,'04_PSA_INPUTS'!H7,'04_PSA_INPUTS'!I7) -> #NAME? | E73: =_xludf.GAMMA.INV(U73,'04_PSA_INPUTS'!H8,'04_PSA_INPUTS'!I8) -> #NAME? | F73: =_xludf.GAMMA.INV(V73,'04_PSA_INPUTS'!H9,'04_PSA_INPUTS'!I9) -> #NAME? | G73: =_xludf.BETA.INV(W73,'04_PSA_INPUTS'!H10,'04_PSA_INPUTS'!I10) -> #NAME? | H73: =_xludf.BETA.INV(X73,'04_PSA_INPUTS'!H11,'04_PSA_INPUTS'!I11) -> #NAME? | I73: =D73+B73*F73+'01_INPUTS'!B20 -> #NAME? | J73: =E73+C73*F73+'01_INPUTS'!B21 -> #NAME? | K73: =I73-J73 -> #NAME? | L73: =G73-B73*H73 -> #NAME? | M73: =G73-C73*H73 -> #NAME? | N73: =L73-M73 -> #NAME? | O73: =IF(N73=0,"",K73/N73) -> #NAME? | P73: ='01_INPUTS'!B9*N73-K73 -> #NAME? | Q73: =IF(P73>0,1,0) -> #NAME? | R73: 0.82230499 | S73: 0.15914201 | T73: 0.50355351 | U73: 0.28497592 | V73: 0.22816827 | W73: 0.24307292 | X73: 0.82271932
A74: 73 | B74: =_xludf.BETA.INV(R74,'04_PSA_INPUTS'!H5,'04_PSA_INPUTS'!I5) -> #NAME? | C74: =_xludf.BETA.INV(S74,'04_PSA_INPUTS'!H6,'04_PSA_INPUTS'!I6) -> #NAME? | D74: =_xludf.GAMMA.INV(T74,'04_PSA_INPUTS'!H7,'04_PSA_INPUTS'!I7) -> #NAME? | E74: =_xludf.GAMMA.INV(U74,'04_PSA_INPUTS'!H8,'04_PSA_INPUTS'!I8) -> #NAME? | F74: =_xludf.GAMMA.INV(V74,'04_PSA_INPUTS'!H9,'04_PSA_INPUTS'!I9) -> #NAME? | G74: =_xludf.BETA.INV(W74,'04_PSA_INPUTS'!H10,'04_PSA_INPUTS'!I10) -> #NAME? | H74: =_xludf.BETA.INV(X74,'04_PSA_INPUTS'!H11,'04_PSA_INPUTS'!I11) -> #NAME? | I74: =D74+B74*F74+'01_INPUTS'!B20 -> #NAME? | J74: =E74+C74*F74+'01_INPUTS'!B21 -> #NAME? | K74: =I74-J74 -> #NAME? | L74: =G74-B74*H74 -> #NAME? | M74: =G74-C74*H74 -> #NAME? | N74: =L74-M74 -> #NAME? | O74: =IF(N74=0,"",K74/N74) -> #NAME? | P74: ='01_INPUTS'!B9*N74-K74 -> #NAME? | Q74: =IF(P74>0,1,0) -> #NAME? | R74: 0.11609727 | S74: 0.56279014 | T74: 0.58932263 | U74: 0.022822909 | V74: 0.91385694 | W74: 0.94361412 | X74: 0.19044008
A75: 74 | B75: =_xludf.BETA.INV(R75,'04_PSA_INPUTS'!H5,'04_PSA_INPUTS'!I5) -> #NAME? | C75: =_xludf.BETA.INV(S75,'04_PSA_INPUTS'!H6,'04_PSA_INPUTS'!I6) -> #NAME? | D75: =_xludf.GAMMA.INV(T75,'04_PSA_INPUTS'!H7,'04_PSA_INPUTS'!I7) -> #NAME? | E75: =_xludf.GAMMA.INV(U75,'04_PSA_INPUTS'!H8,'04_PSA_INPUTS'!I8) -> #NAME? | F75: =_xludf.GAMMA.INV(V75,'04_PSA_INPUTS'!H9,'04_PSA_INPUTS'!I9) -> #NAME? | G75: =_xludf.BETA.INV(W75,'04_PSA_INPUTS'!H10,'04_PSA_INPUTS'!I10) -> #NAME? | H75: =_xludf.BETA.INV(X75,'04_PSA_INPUTS'!H11,'04_PSA_INPUTS'!I11) -> #NAME? | I75: =D75+B75*F75+'01_INPUTS'!B20 -> #NAME? | J75: =E75+C75*F75+'01_INPUTS'!B21 -> #NAME? | K75: =I75-J75 -> #NAME? | L75: =G75-B75*H75 -> #NAME? | M75: =G75-C75*H75 -> #NAME? | N75: =L75-M75 -> #NAME? | O75: =IF(N75=0,"",K75/N75) -> #NAME? | P75: ='01_INPUTS'!B9*N75-K75 -> #NAME? | Q75: =IF(P75>0,1,0) -> #NAME? | R75: 0.73305378 | S75: 0.74506283 | T75: 0.97234126 | U75: 0.0017863181 | V75: 0.99908457 | W75: 0.68778704 | X75: 0.99302675
A76: 75 | B76: =_xludf.BETA.INV(R76,'04_PSA_INPUTS'!H5,'04_PSA_INPUTS'!I5) -> #NAME? | C76: =_xludf.BETA.INV(S76,'04_PSA_INPUTS'!H6,'04_PSA_INPUTS'!I6) -> #NAME? | D76: =_xludf.GAMMA.INV(T76,'04_PSA_INPUTS'!H7,'04_PSA_INPUTS'!I7) -> #NAME? | E76: =_xludf.GAMMA.INV(U76,'04_PSA_INPUTS'!H8,'04_PSA_INPUTS'!I8) -> #NAME? | F76: =_xludf.GAMMA.INV(V76,'04_PSA_INPUTS'!H9,'04_PSA_INPUTS'!I9) -> #NAME? | G76: =_xludf.BETA.INV(W76,'04_PSA_INPUTS'!H10,'04_PSA_INPUTS'!I10) -> #NAME? | H76: =_xludf.BETA.INV(X76,'04_PSA_INPUTS'!H11,'04_PSA_INPUTS'!I11) -> #NAME? | I76: =D76+B76*F76+'01_INPUTS'!B20 -> #NAME? | J76: =E76+C76*F76+'01_INPUTS'!B21 -> #NAME? | K76: =I76-J76 -> #NAME? | L76: =G76-B76*H76 -> #NAME? | M76: =G76-C76*H76 -> #NAME? | N76: =L76-M76 -> #NAME? | O76: =IF(N76=0,"",K76/N76) -> #NAME? | P76: ='01_INPUTS'!B9*N76-K76 -> #NAME? | Q76: =IF(P76>0,1,0) -> #NAME? | R76: 0.6563421 | S76: 0.64032005 | T76: 0.9432782 | U76: 0.11551243 | V76: 0.69069041 | W76: 0.81299831 | X76: 0.27409347
A77: 76 | B77: =_xludf.BETA.INV(R77,'04_PSA_INPUTS'!H5,'04_PSA_INPUTS'!I5) -> #NAME? | C77: =_xludf.BETA.INV(S77,'04_PSA_INPUTS'!H6,'04_PSA_INPUTS'!I6) -> #NAME? | D77: =_xludf.GAMMA.INV(T77,'04_PSA_INPUTS'!H7,'04_PSA_INPUTS'!I7) -> #NAME? | E77: =_xludf.GAMMA.INV(U77,'04_PSA_INPUTS'!H8,'04_PSA_INPUTS'!I8) -> #NAME? | F77: =_xludf.GAMMA.INV(V77,'04_PSA_INPUTS'!H9,'04_PSA_INPUTS'!I9) -> #NAME? | G77: =_xludf.BETA.INV(W77,'04_PSA_INPUTS'!H10,'04_PSA_INPUTS'!I10) -> #NAME? | H77: =_xludf.BETA.INV(X77,'04_PSA_INPUTS'!H11,'04_PSA_INPUTS'!I11) -> #NAME? | I77: =D77+B77*F77+'01_INPUTS'!B20 -> #NAME? | J77: =E77+C77*F77+'01_INPUTS'!B21 -> #NAME? | K77: =I77-J77 -> #NAME? | L77: =G77-B77*H77 -> #NAME? | M77: =G77-C77*H77 -> #NAME? | N77: =L77-M77 -> #NAME? | O77: =IF(N77=0,"",K77/N77) -> #NAME? | P77: ='01_INPUTS'!B9*N77-K77 -> #NAME? | Q77: =IF(P77>0,1,0) -> #NAME? | R77: 0.17927917 | S77: 0.058902658 | T77: 0.56573521 | U77: 0.19680288 | V77: 0.82546751 | W77: 0.72177972 | X77: 0.90397232
A78: 77 | B78: =_xludf.BETA.INV(R78,'04_PSA_INPUTS'!H5,'04_PSA_INPUTS'!I5) -> #NAME? | C78: =_xludf.BETA.INV(S78,'04_PSA_INPUTS'!H6,'04_PSA_INPUTS'!I6) -> #NAME? | D78: =_xludf.GAMMA.INV(T78,'04_PSA_INPUTS'!H7,'04_PSA_INPUTS'!I7) -> #NAME? | E78: =_xludf.GAMMA.INV(U78,'04_PSA_INPUTS'!H8,'04_PSA_INPUTS'!I8) -> #NAME? | F78: =_xludf.GAMMA.INV(V78,'04_PSA_INPUTS'!H9,'04_PSA_INPUTS'!I9) -> #NAME? | G78: =_xludf.BETA.INV(W78,'04_PSA_INPUTS'!H10,'04_PSA_INPUTS'!I10) -> #NAME? | H78: =_xludf.BETA.INV(X78,'04_PSA_INPUTS'!H11,'04_PSA_INPUTS'!I11) -> #NAME? | I78: =D78+B78*F78+'01_INPUTS'!B20 -> #NAME? | J78: =E78+C78*F78+'01_INPUTS'!B21 -> #NAME? | K78: =I78-J78 -> #NAME? | L78: =G78-B78*H78 -> #NAME? | M78: =G78-C78*H78 -> #NAME? | N78: =L78-M78 -> #NAME? | O78: =IF(N78=0,"",K78/N78) -> #NAME? | P78: ='01_INPUTS'!B9*N78-K78 -> #NAME? | Q78: =IF(P78>0,1,0) -> #NAME? | R78: 0.12965166 | S78: 0.14379787 | T78: 0.51786536 | U78: 0.41883615 | V78: 0.5017066 | W78: 0.84814978 | X78: 0.029285698
A79: 78 | B79: =_xludf.BETA.INV(R79,'04_PSA_INPUTS'!H5,'04_PSA_INPUTS'!I5) -> #NAME? | C79: =_xludf.BETA.INV(S79,'04_PSA_INPUTS'!H6,'04_PSA_INPUTS'!I6) -> #NAME? | D79: =_xludf.GAMMA.INV(T79,'04_PSA_INPUTS'!H7,'04_PSA_INPUTS'!I7) -> #NAME? | E79: =_xludf.GAMMA.INV(U79,'04_PSA_INPUTS'!H8,'04_PSA_INPUTS'!I8) -> #NAME? | F79: =_xludf.GAMMA.INV(V79,'04_PSA_INPUTS'!H9,'04_PSA_INPUTS'!I9) -> #NAME? | G79: =_xludf.BETA.INV(W79,'04_PSA_INPUTS'!H10,'04_PSA_INPUTS'!I10) -> #NAME? | H79: =_xludf.BETA.INV(X79,'04_PSA_INPUTS'!H11,'04_PSA_INPUTS'!I11) -> #NAME? | I79: =D79+B79*F79+'01_INPUTS'!B20 -> #NAME? | J79: =E79+C79*F79+'01_INPUTS'!B21 -> #NAME? | K79: =I79-J79 -> #NAME? | L79: =G79-B79*H79 -> #NAME? | M79: =G79-C79*H79 -> #NAME? | N79: =L79-M79 -> #NAME? | O79: =IF(N79=0,"",K79/N79) -> #NAME? | P79: ='01_INPUTS'!B9*N79-K79 -> #NAME? | Q79: =IF(P79>0,1,0) -> #NAME? | R79: 0.89015287 | S79: 0.46349618 | T79: 0.12644338 | U79: 0.37437155 | V79: 0.40704289 | W79: 0.49597241 | X79: 0.058730261
A80: 79 | B80: =_xludf.BETA.INV(R80,'04_PSA_INPUTS'!H5,'04_PSA_INPUTS'!I5) -> #NAME? | C80: =_xludf.BETA.INV(S80,'04_PSA_INPUTS'!H6,'04_PSA_INPUTS'!I6) -> #NAME? | D80: =_xludf.GAMMA.INV(T80,'04_PSA_INPUTS'!H7,'04_PSA_INPUTS'!I7) -> #NAME? | E80: =_xludf.GAMMA.INV(U80,'04_PSA_INPUTS'!H8,'04_PSA_INPUTS'!I8) -> #NAME? | F80: =_xludf.GAMMA.INV(V80,'04_PSA_INPUTS'!H9,'04_PSA_INPUTS'!I9) -> #NAME? | G80: =_xludf.BETA.INV(W80,'04_PSA_INPUTS'!H10,'04_PSA_INPUTS'!I10) -> #NAME? | H80: =_xludf.BETA.INV(X80,'04_PSA_INPUTS'!H11,'04_PSA_INPUTS'!I11) -> #NAME? | I80: =D80+B80*F80+'01_INPUTS'!B20 -> #NAME? | J80: =E80+C80*F80+'01_INPUTS'!B21 -> #NAME? | K80: =I80-J80 -> #NAME? | L80: =G80-B80*H80 -> #NAME? | M80: =G80-C80*H80 -> #NAME? | N80: =L80-M80 -> #NAME? | O80: =IF(N80=0,"",K80/N80) -> #NAME? | P80: ='01_INPUTS'!B9*N80-K80 -> #NAME? | Q80: =IF(P80>0,1,0) -> #NAME? | R80: 0.45442429 | S80: 0.64716455 | T80: 0.39440324 | U80: 0.84247914 | V80: 0.63537277 | W80: 0.65333219 | X80: 0.16489692
A81: 80 | B81: =_xludf.BETA.INV(R81,'04_PSA_INPUTS'!H5,'04_PSA_INPUTS'!I5) -> #NAME? | C81: =_xludf.BETA.INV(S81,'04_PSA_INPUTS'!H6,'04_PSA_INPUTS'!I6) -> #NAME? | D81: =_xludf.GAMMA.INV(T81,'04_PSA_INPUTS'!H7,'04_PSA_INPUTS'!I7) -> #NAME? | E81: =_xludf.GAMMA.INV(U81,'04_PSA_INPUTS'!H8,'04_PSA_INPUTS'!I8) -> #NAME? | F81: =_xludf.GAMMA.INV(V81,'04_PSA_INPUTS'!H9,'04_PSA_INPUTS'!I9) -> #NAME? | G81: =_xludf.BETA.INV(W81,'04_PSA_INPUTS'!H10,'04_PSA_INPUTS'!I10) -> #NAME? | H81: =_xludf.BETA.INV(X81,'04_PSA_INPUTS'!H11,'04_PSA_INPUTS'!I11) -> #NAME? | I81: =D81+B81*F81+'01_INPUTS'!B20 -> #NAME? | J81: =E81+C81*F81+'01_INPUTS'!B21 -> #NAME? | K81: =I81-J81 -> #NAME? | L81: =G81-B81*H81 -> #NAME? | M81: =G81-C81*H81 -> #NAME? | N81: =L81-M81 -> #NAME? | O81: =IF(N81=0,"",K81/N81) -> #NAME? | P81: ='01_INPUTS'!B9*N81-K81 -> #NAME? | Q81: =IF(P81>0,1,0) -> #NAME? | R81: 0.42614946 | S81: 0.95469739 | T81: 0.078800113 | U81: 0.43591488 | V81: 0.48431293 | W81: 0.20694615 | X81: 0.88989459
A82: 81 | B82: =_xludf.BETA.INV(R82,'04_PSA_INPUTS'!H5,'04_PSA_INPUTS'!I5) -> #NAME? | C82: =_xludf.BETA.INV(S82,'04_PSA_INPUTS'!H6,'04_PSA_INPUTS'!I6) -> #NAME? | D82: =_xludf.GAMMA.INV(T82,'04_PSA_INPUTS'!H7,'04_PSA_INPUTS'!I7) -> #NAME? | E82: =_xludf.GAMMA.INV(U82,'04_PSA_INPUTS'!H8,'04_PSA_INPUTS'!I8) -> #NAME? | F82: =_xludf.GAMMA.INV(V82,'04_PSA_INPUTS'!H9,'04_PSA_INPUTS'!I9) -> #NAME? | G82: =_xludf.BETA.INV(W82,'04_PSA_INPUTS'!H10,'04_PSA_INPUTS'!I10) -> #NAME? | H82: =_xludf.BETA.INV(X82,'04_PSA_INPUTS'!H11,'04_PSA_INPUTS'!I11) -> #NAME? | I82: =D82+B82*F82+'01_INPUTS'!B20 -> #NAME? | J82: =E82+C82*F82+'01_INPUTS'!B21 -> #NAME? | K82: =I82-J82 -> #NAME? | L82: =G82-B82*H82 -> #NAME? | M82: =G82-C82*H82 -> #NAME? | N82: =L82-M82 -> #NAME? | O82: =IF(N82=0,"",K82/N82) -> #NAME? | P82: ='01_INPUTS'!B9*N82-K82 -> #NAME? | Q82: =IF(P82>0,1,0) -> #NAME? | R82: 0.20914066 | S82: 0.12934021 | T82: 0.33315802 | U82: 0.8398945 | V82: 0.004797216 | W82: 0.051016316 | X82: 0.48722755
A83: 82 | B83: =_xludf.BETA.INV(R83,'04_PSA_INPUTS'!H5,'04_PSA_INPUTS'!I5) -> #NAME? | C83: =_xludf.BETA.INV(S83,'04_PSA_INPUTS'!H6,'04_PSA_INPUTS'!I6) -> #NAME? | D83: =_xludf.GAMMA.INV(T83,'04_PSA_INPUTS'!H7,'04_PSA_INPUTS'!I7) -> #NAME? | E83: =_xludf.GAMMA.INV(U83,'04_PSA_INPUTS'!H8,'04_PSA_INPUTS'!I8) -> #NAME? | F83: =_xludf.GAMMA.INV(V83,'04_PSA_INPUTS'!H9,'04_PSA_INPUTS'!I9) -> #NAME? | G83: =_xludf.BETA.INV(W83,'04_PSA_INPUTS'!H10,'04_PSA_INPUTS'!I10) -> #NAME? | H83: =_xludf.BETA.INV(X83,'04_PSA_INPUTS'!H11,'04_PSA_INPUTS'!I11) -> #NAME? | I83: =D83+B83*F83+'01_INPUTS'!B20 -> #NAME? | J83: =E83+C83*F83+'01_INPUTS'!B21 -> #NAME? | K83: =I83-J83 -> #NAME? | L83: =G83-B83*H83 -> #NAME? | M83: =G83-C83*H83 -> #NAME? | N83: =L83-M83 -> #NAME? | O83: =IF(N83=0,"",K83/N83) -> #NAME? | P83: ='01_INPUTS'!B9*N83-K83 -> #NAME? | Q83: =IF(P83>0,1,0) -> #NAME? | R83: 0.82520766 | S83: 0.5918443 | T83: 0.32541861 | U83: 0.61569026 | V83: 0.41301635 | W83: 0.030605958 | X83: 0.19743151
A84: 83 | B84: =_xludf.BETA.INV(R84,'04_PSA_INPUTS'!H5,'04_PSA_INPUTS'!I5) -> #NAME? | C84: =_xludf.BETA.INV(S84,'04_PSA_INPUTS'!H6,'04_PSA_INPUTS'!I6) -> #NAME? | D84: =_xludf.GAMMA.INV(T84,'04_PSA_INPUTS'!H7,'04_PSA_INPUTS'!I7) -> #NAME? | E84: =_xludf.GAMMA.INV(U84,'04_PSA_INPUTS'!H8,'04_PSA_INPUTS'!I8) -> #NAME? | F84: =_xludf.GAMMA.INV(V84,'04_PSA_INPUTS'!H9,'04_PSA_INPUTS'!I9) -> #NAME? | G84: =_xludf.BETA.INV(W84,'04_PSA_INPUTS'!H10,'04_PSA_INPUTS'!I10) -> #NAME? | H84: =_xludf.BETA.INV(X84,'04_PSA_INPUTS'!H11,'04_PSA_INPUTS'!I11) -> #NAME? | I84: =D84+B84*F84+'01_INPUTS'!B20 -> #NAME? | J84: =E84+C84*F84+'01_INPUTS'!B21 -> #NAME? | K84: =I84-J84 -> #NAME? | L84: =G84-B84*H84 -> #NAME? | M84: =G84-C84*H84 -> #NAME? | N84: =L84-M84 -> #NAME? | O84: =IF(N84=0,"",K84/N84) -> #NAME? | P84: ='01_INPUTS'!B9*N84-K84 -> #NAME? | Q84: =IF(P84>0,1,0) -> #NAME? | R84: 0.30152532 | S84: 0.95302526 | T84: 0.54080914 | U84: 0.92073248 | V84: 0.48217636 | W84: 0.82792755 | X84: 0.12750593
A85: 84 | B85: =_xludf.BETA.INV(R85,'04_PSA_INPUTS'!H5,'04_PSA_INPUTS'!I5) -> #NAME? | C85: =_xludf.BETA.INV(S85,'04_PSA_INPUTS'!H6,'04_PSA_INPUTS'!I6) -> #NAME? | D85: =_xludf.GAMMA.INV(T85,'04_PSA_INPUTS'!H7,'04_PSA_INPUTS'!I7) -> #NAME? | E85: =_xludf.GAMMA.INV(U85,'04_PSA_INPUTS'!H8,'04_PSA_INPUTS'!I8) -> #NAME? | F85: =_xludf.GAMMA.INV(V85,'04_PSA_INPUTS'!H9,'04_PSA_INPUTS'!I9) -> #NAME? | G85: =_xludf.BETA.INV(W85,'04_PSA_INPUTS'!H10,'04_PSA_INPUTS'!I10) -> #NAME? | H85: =_xludf.BETA.INV(X85,'04_PSA_INPUTS'!H11,'04_PSA_INPUTS'!I11) -> #NAME? | I85: =D85+B85*F85+'01_INPUTS'!B20 -> #NAME? | J85: =E85+C85*F85+'01_INPUTS'!B21 -> #NAME? | K85: =I85-J85 -> #NAME? | L85: =G85-B85*H85 -> #NAME? | M85: =G85-C85*H85 -> #NAME? | N85: =L85-M85 -> #NAME? | O85: =IF(N85=0,"",K85/N85) -> #NAME? | P85: ='01_INPUTS'!B9*N85-K85 -> #NAME? | Q85: =IF(P85>0,1,0) -> #NAME? | R85: 0.93394667 | S85: 0.1222663 | T85: 0.019584275 | U85: 0.025333849 | V85: 0.46226626 | W85: 0.54030032 | X85: 0.43669042
A86: 85 | B86: =_xludf.BETA.INV(R86,'04_PSA_INPUTS'!H5,'04_PSA_INPUTS'!I5) -> #NAME? | C86: =_xludf.BETA.INV(S86,'04_PSA_INPUTS'!H6,'04_PSA_INPUTS'!I6) -> #NAME? | D86: =_xludf.GAMMA.INV(T86,'04_PSA_INPUTS'!H7,'04_PSA_INPUTS'!I7) -> #NAME? | E86: =_xludf.GAMMA.INV(U86,'04_PSA_INPUTS'!H8,'04_PSA_INPUTS'!I8) -> #NAME? | F86: =_xludf.GAMMA.INV(V86,'04_PSA_INPUTS'!H9,'04_PSA_INPUTS'!I9) -> #NAME? | G86: =_xludf.BETA.INV(W86,'04_PSA_INPUTS'!H10,'04_PSA_INPUTS'!I10) -> #NAME? | H86: =_xludf.BETA.INV(X86,'04_PSA_INPUTS'!H11,'04_PSA_INPUTS'!I11) -> #NAME? | I86: =D86+B86*F86+'01_INPUTS'!B20 -> #NAME? | J86: =E86+C86*F86+'01_INPUTS'!B21 -> #NAME? | K86: =I86-J86 -> #NAME? | L86: =G86-B86*H86 -> #NAME? | M86: =G86-C86*H86 -> #NAME? | N86: =L86-M86 -> #NAME? | O86: =IF(N86=0,"",K86/N86) -> #NAME? | P86: ='01_INPUTS'!B9*N86-K86 -> #NAME? | Q86: =IF(P86>0,1,0) -> #NAME? | R86: 0.66475219 | S86: 0.1300417 | T86: 0.91989271 | U86: 0.33131399 | V86: 0.34334294 | W86: 0.11461074 | X86: 0.75820678
A87: 86 | B87: =_xludf.BETA.INV(R87,'04_PSA_INPUTS'!H5,'04_PSA_INPUTS'!I5) -> #NAME? | C87: =_xludf.BETA.INV(S87,'04_PSA_INPUTS'!H6,'04_PSA_INPUTS'!I6) -> #NAME? | D87: =_xludf.GAMMA.INV(T87,'04_PSA_INPUTS'!H7,'04_PSA_INPUTS'!I7) -> #NAME? | E87: =_xludf.GAMMA.INV(U87,'04_PSA_INPUTS'!H8,'04_PSA_INPUTS'!I8) -> #NAME? | F87: =_xludf.GAMMA.INV(V87,'04_PSA_INPUTS'!H9,'04_PSA_INPUTS'!I9) -> #NAME? | G87: =_xludf.BETA.INV(W87,'04_PSA_INPUTS'!H10,'04_PSA_INPUTS'!I10) -> #NAME? | H87: =_xludf.BETA.INV(X87,'04_PSA_INPUTS'!H11,'04_PSA_INPUTS'!I11) -> #NAME? | I87: =D87+B87*F87+'01_INPUTS'!B20 -> #NAME? | J87: =E87+C87*F87+'01_INPUTS'!B21 -> #NAME? | K87: =I87-J87 -> #NAME? | L87: =G87-B87*H87 -> #NAME? | M87: =G87-C87*H87 -> #NAME? | N87: =L87-M87 -> #NAME? | O87: =IF(N87=0,"",K87/N87) -> #NAME? | P87: ='01_INPUTS'!B9*N87-K87 -> #NAME? | Q87: =IF(P87>0,1,0) -> #NAME? | R87: 0.0067372851 | S87: 0.924769 | T87: 0.62066714 | U87: 0.19762635 | V87: 0.15915277 | W87: 0.32707504 | X87: 0.22060382
A88: 87 | B88: =_xludf.BETA.INV(R88,'04_PSA_INPUTS'!H5,'04_PSA_INPUTS'!I5) -> #NAME? | C88: =_xludf.BETA.INV(S88,'04_PSA_INPUTS'!H6,'04_PSA_INPUTS'!I6) -> #NAME? | D88: =_xludf.GAMMA.INV(T88,'04_PSA_INPUTS'!H7,'04_PSA_INPUTS'!I7) -> #NAME? | E88: =_xludf.GAMMA.INV(U88,'04_PSA_INPUTS'!H8,'04_PSA_INPUTS'!I8) -> #NAME? | F88: =_xludf.GAMMA.INV(V88,'04_PSA_INPUTS'!H9,'04_PSA_INPUTS'!I9) -> #NAME? | G88: =_xludf.BETA.INV(W88,'04_PSA_INPUTS'!H10,'04_PSA_INPUTS'!I10) -> #NAME? | H88: =_xludf.BETA.INV(X88,'04_PSA_INPUTS'!H11,'04_PSA_INPUTS'!I11) -> #NAME? | I88: =D88+B88*F88+'01_INPUTS'!B20 -> #NAME? | J88: =E88+C88*F88+'01_INPUTS'!B21 -> #NAME? | K88: =I88-J88 -> #NAME? | L88: =G88-B88*H88 -> #NAME? | M88: =G88-C88*H88 -> #NAME? | N88: =L88-M88 -> #NAME? | O88: =IF(N88=0,"",K88/N88) -> #NAME? | P88: ='01_INPUTS'!B9*N88-K88 -> #NAME? | Q88: =IF(P88>0,1,0) -> #NAME? | R88: 0.5324622 | S88: 0.029186768 | T88: 0.86483507 | U88: 0.5424662 | V88: 0.46354047 | W88: 0.77271998 | X88: 0.49097946
A89: 88 | B89: =_xludf.BETA.INV(R89,'04_PSA_INPUTS'!H5,'04_PSA_INPUTS'!I5) -> #NAME? | C89: =_xludf.BETA.INV(S89,'04_PSA_INPUTS'!H6,'04_PSA_INPUTS'!I6) -> #NAME? | D89: =_xludf.GAMMA.INV(T89,'04_PSA_INPUTS'!H7,'04_PSA_INPUTS'!I7) -> #NAME? | E89: =_xludf.GAMMA.INV(U89,'04_PSA_INPUTS'!H8,'04_PSA_INPUTS'!I8) -> #NAME? | F89: =_xludf.GAMMA.INV(V89,'04_PSA_INPUTS'!H9,'04_PSA_INPUTS'!I9) -> #NAME? | G89: =_xludf.BETA.INV(W89,'04_PSA_INPUTS'!H10,'04_PSA_INPUTS'!I10) -> #NAME? | H89: =_xludf.BETA.INV(X89,'04_PSA_INPUTS'!H11,'04_PSA_INPUTS'!I11) -> #NAME? | I89: =D89+B89*F89+'01_INPUTS'!B20 -> #NAME? | J89: =E89+C89*F89+'01_INPUTS'!B21 -> #NAME? | K89: =I89-J89 -> #NAME? | L89: =G89-B89*H89 -> #NAME? | M89: =G89-C89*H89 -> #NAME? | N89: =L89-M89 -> #NAME? | O89: =IF(N89=0,"",K89/N89) -> #NAME? | P89: ='01_INPUTS'!B9*N89-K89 -> #NAME? | Q89: =IF(P89>0,1,0) -> #NAME? | R89: 0.064458819 | S89: 0.60059932 | T89: 0.88619377 | U89: 0.41445934 | V89: 0.28617456 | W89: 0.072133922 | X89: 0.028145509
A90: 89 | B90: =_xludf.BETA.INV(R90,'04_PSA_INPUTS'!H5,'04_PSA_INPUTS'!I5) -> #NAME? | C90: =_xludf.BETA.INV(S90,'04_PSA_INPUTS'!H6,'04_PSA_INPUTS'!I6) -> #NAME? | D90: =_xludf.GAMMA.INV(T90,'04_PSA_INPUTS'!H7,'04_PSA_INPUTS'!I7) -> #NAME? | E90: =_xludf.GAMMA.INV(U90,'04_PSA_INPUTS'!H8,'04_PSA_INPUTS'!I8) -> #NAME? | F90: =_xludf.GAMMA.INV(V90,'04_PSA_INPUTS'!H9,'04_PSA_INPUTS'!I9) -> #NAME? | G90: =_xludf.BETA.INV(W90,'04_PSA_INPUTS'!H10,'04_PSA_INPUTS'!I10) -> #NAME? | H90: =_xludf.BETA.INV(X90,'04_PSA_INPUTS'!H11,'04_PSA_INPUTS'!I11) -> #NAME? | I90: =D90+B90*F90+'01_INPUTS'!B20 -> #NAME? | J90: =E90+C90*F90+'01_INPUTS'!B21 -> #NAME? | K90: =I90-J90 -> #NAME? | L90: =G90-B90*H90 -> #NAME? | M90: =G90-C90*H90 -> #NAME? | N90: =L90-M90 -> #NAME? | O90: =IF(N90=0,"",K90/N90) -> #NAME? | P90: ='01_INPUTS'!B9*N90-K90 -> #NAME? | Q90: =IF(P90>0,1,0) -> #NAME? | R90: 0.2161693 | S90: 0.31710542 | T90: 0.29648369 | U90: 0.93026841 | V90: 0.12646095 | W90: 0.43326892 | X90: 0.17486522
A91: 90 | B91: =_xludf.BETA.INV(R91,'04_PSA_INPUTS'!H5,'04_PSA_INPUTS'!I5) -> #NAME? | C91: =_xludf.BETA.INV(S91,'04_PSA_INPUTS'!H6,'04_PSA_INPUTS'!I6) -> #NAME? | D91: =_xludf.GAMMA.INV(T91,'04_PSA_INPUTS'!H7,'04_PSA_INPUTS'!I7) -> #NAME? | E91: =_xludf.GAMMA.INV(U91,'04_PSA_INPUTS'!H8,'04_PSA_INPUTS'!I8) -> #NAME? | F91: =_xludf.GAMMA.INV(V91,'04_PSA_INPUTS'!H9,'04_PSA_INPUTS'!I9) -> #NAME? | G91: =_xludf.BETA.INV(W91,'04_PSA_INPUTS'!H10,'04_PSA_INPUTS'!I10) -> #NAME? | H91: =_xludf.BETA.INV(X91,'04_PSA_INPUTS'!H11,'04_PSA_INPUTS'!I11) -> #NAME? | I91: =D91+B91*F91+'01_INPUTS'!B20 -> #NAME? | J91: =E91+C91*F91+'01_INPUTS'!B21 -> #NAME? | K91: =I91-J91 -> #NAME? | L91: =G91-B91*H91 -> #NAME? | M91: =G91-C91*H91 -> #NAME? | N91: =L91-M91 -> #NAME? | O91: =IF(N91=0,"",K91/N91) -> #NAME? | P91: ='01_INPUTS'!B9*N91-K91 -> #NAME? | Q91: =IF(P91>0,1,0) -> #NAME? | R91: 0.79698921 | S91: 0.8172491 | T91: 0.58589823 | U91: 0.1249181 | V91: 0.54037638 | W91: 0.58539428 | X91: 0.76978179
A92: 91 | B92: =_xludf.BETA.INV(R92,'04_PSA_INPUTS'!H5,'04_PSA_INPUTS'!I5) -> #NAME? | C92: =_xludf.BETA.INV(S92,'04_PSA_INPUTS'!H6,'04_PSA_INPUTS'!I6) -> #NAME? | D92: =_xludf.GAMMA.INV(T92,'04_PSA_INPUTS'!H7,'04_PSA_INPUTS'!I7) -> #NAME? | E92: =_xludf.GAMMA.INV(U92,'04_PSA_INPUTS'!H8,'04_PSA_INPUTS'!I8) -> #NAME? | F92: =_xludf.GAMMA.INV(V92,'04_PSA_INPUTS'!H9,'04_PSA_INPUTS'!I9) -> #NAME? | G92: =_xludf.BETA.INV(W92,'04_PSA_INPUTS'!H10,'04_PSA_INPUTS'!I10) -> #NAME? | H92: =_xludf.BETA.INV(X92,'04_PSA_INPUTS'!H11,'04_PSA_INPUTS'!I11) -> #NAME? | I92: =D92+B92*F92+'01_INPUTS'!B20 -> #NAME? | J92: =E92+C92*F92+'01_INPUTS'!B21 -> #NAME? | K92: =I92-J92 -> #NAME? | L92: =G92-B92*H92 -> #NAME? | M92: =G92-C92*H92 -> #NAME? | N92: =L92-M92 -> #NAME? | O92: =IF(N92=0,"",K92/N92) -> #NAME? | P92: ='01_INPUTS'!B9*N92-K92 -> #NAME? | Q92: =IF(P92>0,1,0) -> #NAME? | R92: 0.31460909 | S92: 0.93325515 | T92: 0.86661862 | U92: 0.65983963 | V92: 0.43748962 | W92: 0.43601206 | X92: 0.94791751
A93: 92 | B93: =_xludf.BETA.INV(R93,'04_PSA_INPUTS'!H5,'04_PSA_INPUTS'!I5) -> #NAME? | C93: =_xludf.BETA.INV(S93,'04_PSA_INPUTS'!H6,'04_PSA_INPUTS'!I6) -> #NAME? | D93: =_xludf.GAMMA.INV(T93,'04_PSA_INPUTS'!H7,'04_PSA_INPUTS'!I7) -> #NAME? | E93: =_xludf.GAMMA.INV(U93,'04_PSA_INPUTS'!H8,'04_PSA_INPUTS'!I8) -> #NAME? | F93: =_xludf.GAMMA.INV(V93,'04_PSA_INPUTS'!H9,'04_PSA_INPUTS'!I9) -> #NAME? | G93: =_xludf.BETA.INV(W93,'04_PSA_INPUTS'!H10,'04_PSA_INPUTS'!I10) -> #NAME? | H93: =_xludf.BETA.INV(X93,'04_PSA_INPUTS'!H11,'04_PSA_INPUTS'!I11) -> #NAME? | I93: =D93+B93*F93+'01_INPUTS'!B20 -> #NAME? | J93: =E93+C93*F93+'01_INPUTS'!B21 -> #NAME? | K93: =I93-J93 -> #NAME? | L93: =G93-B93*H93 -> #NAME? | M93: =G93-C93*H93 -> #NAME? | N93: =L93-M93 -> #NAME? | O93: =IF(N93=0,"",K93/N93) -> #NAME? | P93: ='01_INPUTS'!B9*N93-K93 -> #NAME? | Q93: =IF(P93>0,1,0) -> #NAME? | R93: 0.77336125 | S93: 0.86447382 | T93: 0.84764903 | U93: 0.96133318 | V93: 0.47433983 | W93: 0.23288321 | X93: 0.54434049
A94: 93 | B94: =_xludf.BETA.INV(R94,'04_PSA_INPUTS'!H5,'04_PSA_INPUTS'!I5) -> #NAME? | C94: =_xludf.BETA.INV(S94,'04_PSA_INPUTS'!H6,'04_PSA_INPUTS'!I6) -> #NAME? | D94: =_xludf.GAMMA.INV(T94,'04_PSA_INPUTS'!H7,'04_PSA_INPUTS'!I7) -> #NAME? | E94: =_xludf.GAMMA.INV(U94,'04_PSA_INPUTS'!H8,'04_PSA_INPUTS'!I8) -> #NAME? | F94: =_xludf.GAMMA.INV(V94,'04_PSA_INPUTS'!H9,'04_PSA_INPUTS'!I9) -> #NAME? | G94: =_xludf.BETA.INV(W94,'04_PSA_INPUTS'!H10,'04_PSA_INPUTS'!I10) -> #NAME? | H94: =_xludf.BETA.INV(X94,'04_PSA_INPUTS'!H11,'04_PSA_INPUTS'!I11) -> #NAME? | I94: =D94+B94*F94+'01_INPUTS'!B20 -> #NAME? | J94: =E94+C94*F94+'01_INPUTS'!B21 -> #NAME? | K94: =I94-J94 -> #NAME? | L94: =G94-B94*H94 -> #NAME? | M94: =G94-C94*H94 -> #NAME? | N94: =L94-M94 -> #NAME? | O94: =IF(N94=0,"",K94/N94) -> #NAME? | P94: ='01_INPUTS'!B9*N94-K94 -> #NAME? | Q94: =IF(P94>0,1,0) -> #NAME? | R94: 0.37114999 | S94: 0.10268407 | T94: 0.37479155 | U94: 0.10277812 | V94: 0.57789089 | W94: 0.77387272 | X94: 0.84507469
A95: 94 | B95: =_xludf.BETA.INV(R95,'04_PSA_INPUTS'!H5,'04_PSA_INPUTS'!I5) -> #NAME? | C95: =_xludf.BETA.INV(S95,'04_PSA_INPUTS'!H6,'04_PSA_INPUTS'!I6) -> #NAME? | D95: =_xludf.GAMMA.INV(T95,'04_PSA_INPUTS'!H7,'04_PSA_INPUTS'!I7) -> #NAME? | E95: =_xludf.GAMMA.INV(U95,'04_PSA_INPUTS'!H8,'04_PSA_INPUTS'!I8) -> #NAME? | F95: =_xludf.GAMMA.INV(V95,'04_PSA_INPUTS'!H9,'04_PSA_INPUTS'!I9) -> #NAME? | G95: =_xludf.BETA.INV(W95,'04_PSA_INPUTS'!H10,'04_PSA_INPUTS'!I10) -> #NAME? | H95: =_xludf.BETA.INV(X95,'04_PSA_INPUTS'!H11,'04_PSA_INPUTS'!I11) -> #NAME? | I95: =D95+B95*F95+'01_INPUTS'!B20 -> #NAME? | J95: =E95+C95*F95+'01_INPUTS'!B21 -> #NAME? | K95: =I95-J95 -> #NAME? | L95: =G95-B95*H95 -> #NAME? | M95: =G95-C95*H95 -> #NAME? | N95: =L95-M95 -> #NAME? | O95: =IF(N95=0,"",K95/N95) -> #NAME? | P95: ='01_INPUTS'!B9*N95-K95 -> #NAME? | Q95: =IF(P95>0,1,0) -> #NAME? | R95: 0.39276866 | S95: 0.51624708 | T95: 0.4660639 | U95: 0.51615495 | V95: 0.047562204 | W95: 0.77073304 | X95: 0.28949364
A96: 95 | B96: =_xludf.BETA.INV(R96,'04_PSA_INPUTS'!H5,'04_PSA_INPUTS'!I5) -> #NAME? | C96: =_xludf.BETA.INV(S96,'04_PSA_INPUTS'!H6,'04_PSA_INPUTS'!I6) -> #NAME? | D96: =_xludf.GAMMA.INV(T96,'04_PSA_INPUTS'!H7,'04_PSA_INPUTS'!I7) -> #NAME? | E96: =_xludf.GAMMA.INV(U96,'04_PSA_INPUTS'!H8,'04_PSA_INPUTS'!I8) -> #NAME? | F96: =_xludf.GAMMA.INV(V96,'04_PSA_INPUTS'!H9,'04_PSA_INPUTS'!I9) -> #NAME? | G96: =_xludf.BETA.INV(W96,'04_PSA_INPUTS'!H10,'04_PSA_INPUTS'!I10) -> #NAME? | H96: =_xludf.BETA.INV(X96,'04_PSA_INPUTS'!H11,'04_PSA_INPUTS'!I11) -> #NAME? | I96: =D96+B96*F96+'01_INPUTS'!B20 -> #NAME? | J96: =E96+C96*F96+'01_INPUTS'!B21 -> #NAME? | K96: =I96-J96 -> #NAME? | L96: =G96-B96*H96 -> #NAME? | M96: =G96-C96*H96 -> #NAME? | N96: =L96-M96 -> #NAME? | O96: =IF(N96=0,"",K96/N96) -> #NAME? | P96: ='01_INPUTS'!B9*N96-K96 -> #NAME? | Q96: =IF(P96>0,1,0) -> #NAME? | R96: 0.32839021 | S96: 0.85940039 | T96: 0.62126272 | U96: 0.68170775 | V96: 0.91107034 | W96: 0.0060059817 | X96: 0.79347065
A97: 96 | B97: =_xludf.BETA.INV(R97,'04_PSA_INPUTS'!H5,'04_PSA_INPUTS'!I5) -> #NAME? | C97: =_xludf.BETA.INV(S97,'04_PSA_INPUTS'!H6,'04_PSA_INPUTS'!I6) -> #NAME? | D97: =_xludf.GAMMA.INV(T97,'04_PSA_INPUTS'!H7,'04_PSA_INPUTS'!I7) -> #NAME? | E97: =_xludf.GAMMA.INV(U97,'04_PSA_INPUTS'!H8,'04_PSA_INPUTS'!I8) -> #NAME? | F97: =_xludf.GAMMA.INV(V97,'04_PSA_INPUTS'!H9,'04_PSA_INPUTS'!I9) -> #NAME? | G97: =_xludf.BETA.INV(W97,'04_PSA_INPUTS'!H10,'04_PSA_INPUTS'!I10) -> #NAME? | H97: =_xludf.BETA.INV(X97,'04_PSA_INPUTS'!H11,'04_PSA_INPUTS'!I11) -> #NAME? | I97: =D97+B97*F97+'01_INPUTS'!B20 -> #NAME? | J97: =E97+C97*F97+'01_INPUTS'!B21 -> #NAME? | K97: =I97-J97 -> #NAME? | L97: =G97-B97*H97 -> #NAME? | M97: =G97-C97*H97 -> #NAME? | N97: =L97-M97 -> #NAME? | O97: =IF(N97=0,"",K97/N97) -> #NAME? | P97: ='01_INPUTS'!B9*N97-K97 -> #NAME? | Q97: =IF(P97>0,1,0) -> #NAME? | R97: 0.77268509 | S97: 0.9095325 | T97: 0.67481087 | U97: 0.3798341 | V97: 0.75492407 | W97: 0.92161522 | X97: 0.45897509
A98: 97 | B98: =_xludf.BETA.INV(R98,'04_PSA_INPUTS'!H5,'04_PSA_INPUTS'!I5) -> #NAME? | C98: =_xludf.BETA.INV(S98,'04_PSA_INPUTS'!H6,'04_PSA_INPUTS'!I6) -> #NAME? | D98: =_xludf.GAMMA.INV(T98,'04_PSA_INPUTS'!H7,'04_PSA_INPUTS'!I7) -> #NAME? | E98: =_xludf.GAMMA.INV(U98,'04_PSA_INPUTS'!H8,'04_PSA_INPUTS'!I8) -> #NAME? | F98: =_xludf.GAMMA.INV(V98,'04_PSA_INPUTS'!H9,'04_PSA_INPUTS'!I9) -> #NAME? | G98: =_xludf.BETA.INV(W98,'04_PSA_INPUTS'!H10,'04_PSA_INPUTS'!I10) -> #NAME? | H98: =_xludf.BETA.INV(X98,'04_PSA_INPUTS'!H11,'04_PSA_INPUTS'!I11) -> #NAME? | I98: =D98+B98*F98+'01_INPUTS'!B20 -> #NAME? | J98: =E98+C98*F98+'01_INPUTS'!B21 -> #NAME? | K98: =I98-J98 -> #NAME? | L98: =G98-B98*H98 -> #NAME? | M98: =G98-C98*H98 -> #NAME? | N98: =L98-M98 -> #NAME? | O98: =IF(N98=0,"",K98/N98) -> #NAME? | P98: ='01_INPUTS'!B9*N98-K98 -> #NAME? | Q98: =IF(P98>0,1,0) -> #NAME? | R98: 0.82245084 | S98: 0.048578956 | T98: 0.87433726 | U98: 0.96936752 | V98: 0.47639279 | W98: 0.83877621 | X98: 0.72878257
A99: 98 | B99: =_xludf.BETA.INV(R99,'04_PSA_INPUTS'!H5,'04_PSA_INPUTS'!I5) -> #NAME? | C99: =_xludf.BETA.INV(S99,'04_PSA_INPUTS'!H6,'04_PSA_INPUTS'!I6) -> #NAME? | D99: =_xludf.GAMMA.INV(T99,'04_PSA_INPUTS'!H7,'04_PSA_INPUTS'!I7) -> #NAME? | E99: =_xludf.GAMMA.INV(U99,'04_PSA_INPUTS'!H8,'04_PSA_INPUTS'!I8) -> #NAME? | F99: =_xludf.GAMMA.INV(V99,'04_PSA_INPUTS'!H9,'04_PSA_INPUTS'!I9) -> #NAME? | G99: =_xludf.BETA.INV(W99,'04_PSA_INPUTS'!H10,'04_PSA_INPUTS'!I10) -> #NAME? | H99: =_xludf.BETA.INV(X99,'04_PSA_INPUTS'!H11,'04_PSA_INPUTS'!I11) -> #NAME? | I99: =D99+B99*F99+'01_INPUTS'!B20 -> #NAME? | J99: =E99+C99*F99+'01_INPUTS'!B21 -> #NAME? | K99: =I99-J99 -> #NAME? | L99: =G99-B99*H99 -> #NAME? | M99: =G99-C99*H99 -> #NAME? | N99: =L99-M99 -> #NAME? | O99: =IF(N99=0,"",K99/N99) -> #NAME? | P99: ='01_INPUTS'!B9*N99-K99 -> #NAME? | Q99: =IF(P99>0,1,0) -> #NAME? | R99: 0.95692467 | S99: 0.40649854 | T99: 0.59722254 | U99: 0.30891069 | V99: 0.88804517 | W99: 0.81883979 | X99: 0.73995435
A100: 99 | B100: =_xludf.BETA.INV(R100,'04_PSA_INPUTS'!H5,'04_PSA_INPUTS'!I5) -> #NAME? | C100: =_xludf.BETA.INV(S100,'04_PSA_INPUTS'!H6,'04_PSA_INPUTS'!I6) -> #NAME? | D100: =_xludf.GAMMA.INV(T100,'04_PSA_INPUTS'!H7,'04_PSA_INPUTS'!I7) -> #NAME? | E100: =_xludf.GAMMA.INV(U100,'04_PSA_INPUTS'!H8,'04_PSA_INPUTS'!I8) -> #NAME? | F100: =_xludf.GAMMA.INV(V100,'04_PSA_INPUTS'!H9,'04_PSA_INPUTS'!I9) -> #NAME? | G100: =_xludf.BETA.INV(W100,'04_PSA_INPUTS'!H10,'04_PSA_INPUTS'!I10) -> #NAME? | H100: =_xludf.BETA.INV(X100,'04_PSA_INPUTS'!H11,'04_PSA_INPUTS'!I11) -> #NAME? | I100: =D100+B100*F100+'01_INPUTS'!B20 -> #NAME? | J100: =E100+C100*F100+'01_INPUTS'!B21 -> #NAME? | K100: =I100-J100 -> #NAME? | L100: =G100-B100*H100 -> #NAME? | M100: =G100-C100*H100 -> #NAME? | N100: =L100-M100 -> #NAME? | O100: =IF(N100=0,"",K100/N100) -> #NAME? | P100: ='01_INPUTS'!B9*N100-K100 -> #NAME? | Q100: =IF(P100>0,1,0) -> #NAME? | R100: 0.77106759 | S100: 0.33313448 | T100: 0.46432448 | U100: 0.91558437 | V100: 0.54862217 | W100: 0.70798488 | X100: 0.22000575
...

Sheet 06_CE_PLANE_CEAC
A1: Cost-Effectiveness Plane and CEAC | B1: Cost-Effectiveness Plane and CEAC | C1: Cost-Effectiveness Plane and CEAC | D1: Cost-Effectiveness Plane and CEAC | E1: Cost-Effectiveness Plane and CEAC | F1: Cost-Effectiveness Plane and CEAC | G1: Cost-Effectiveness Plane and CEAC | H1: Cost-Effectiveness Plane and CEAC | I1: Cost-Effectiveness Plane and CEAC | J1: Cost-Effectiveness Plane and CEAC | K1: Cost-Effectiveness Plane and CEAC | L1: Cost-Effectiveness Plane and CEAC | M1: Cost-Effectiveness Plane and CEAC | N1: Cost-Effectiveness Plane and CEAC
A2: All tables update from current PSA inputs. Raw CE-plane coordinates can be compared directly with the DeciBridge scatter plot. | B2: All tables update from current PSA inputs. Raw CE-plane coordinates can be compared directly with the DeciBridge scatter plot. | C2: All tables update from current PSA inputs. Raw CE-plane coordinates can be compared directly with the DeciBridge scatter plot. | D2: All tables update from current PSA inputs. Raw CE-plane coordinates can be compared directly with the DeciBridge scatter plot. | E2: All tables update from current PSA inputs. Raw CE-plane coordinates can be compared directly with the DeciBridge scatter plot. | F2: All tables update from current PSA inputs. Raw CE-plane coordinates can be compared directly with the DeciBridge scatter plot. | G2: All tables update from current PSA inputs. Raw CE-plane coordinates can be compared directly with the DeciBridge scatter plot. | H2: All tables update from current PSA inputs. Raw CE-plane coordinates can be compared directly with the DeciBridge scatter plot. | I2: All tables update from current PSA inputs. Raw CE-plane coordinates can be compared directly with the DeciBridge scatter plot. | J2: All tables update from current PSA inputs. Raw CE-plane coordinates can be compared directly with the DeciBridge scatter plot. | K2: All tables update from current PSA inputs. Raw CE-plane coordinates can be compared directly with the DeciBridge scatter plot. | L2: All tables update from current PSA inputs. Raw CE-plane coordinates can be compared directly with the DeciBridge scatter plot. | M2: All tables update from current PSA inputs. Raw CE-plane coordinates can be compared directly with the DeciBridge scatter plot. | N2: All tables update from current PSA inputs. Raw CE-plane coordinates can be compared directly with the DeciBridge scatter plot.
A4: CE plane data | B4: CE plane data | D4: CEAC data | E4: CEAC data | G4: Dynamic CE-plane quadrant summary | H4: Dynamic CE-plane quadrant summary | I4: Dynamic CE-plane quadrant summary | J4: Dynamic CE-plane quadrant summary
A5: Incremental QALY | B5: Incremental cost (IDR) | D5: WTP (IDR/QALY) | E5: Probability cost-effective | G5: Quadrant | H5: Condition | I5: Simulations | J5: Probability
A6: ='05_PSA_1000'!N2 -> #NAME? | B6: ='05_PSA_1000'!K2 -> #NAME? | D6: 0 | E6: =SUMPRODUCT(--((D6*'05_PSA_1000'!$N$2:$N$1001-'05_PSA_1000'!$K$2:$K$1001)>0))/1000 -> #NAME? | G6: Dominant | H6: ΔCost < 0; ΔQALY > 0 | I6: =COUNTIFS('05_PSA_1000'!$K$2:$K$1001,"<0",'05_PSA_1000'!$N$2:$N$1001,">0") -> 0 | J6: =I6/1000 -> 0
A7: ='05_PSA_1000'!N3 -> #NAME? | B7: ='05_PSA_1000'!K3 -> #NAME? | D7: 50000000 | E7: =SUMPRODUCT(--((D7*'05_PSA_1000'!$N$2:$N$1001-'05_PSA_1000'!$K$2:$K$1001)>0))/1000 -> #NAME? | G7: Higher cost / higher QALY | H7: ΔCost ≥ 0; ΔQALY ≥ 0 | I7: =COUNTIFS('05_PSA_1000'!$K$2:$K$1001,">=0",'05_PSA_1000'!$N$2:$N$1001,">=0") -> 0 | J7: =I7/1000 -> 0
A8: ='05_PSA_1000'!N4 -> #NAME? | B8: ='05_PSA_1000'!K4 -> #NAME? | D8: 100000000 | E8: =SUMPRODUCT(--((D8*'05_PSA_1000'!$N$2:$N$1001-'05_PSA_1000'!$K$2:$K$1001)>0))/1000 -> #NAME? | G8: Lower cost / lower QALY | H8: ΔCost < 0; ΔQALY ≤ 0 | I8: =COUNTIFS('05_PSA_1000'!$K$2:$K$1001,"<0",'05_PSA_1000'!$N$2:$N$1001,"<=0") -> 0 | J8: =I8/1000 -> 0
A9: ='05_PSA_1000'!N5 -> #NAME? | B9: ='05_PSA_1000'!K5 -> #NAME? | D9: 150000000 | E9: =SUMPRODUCT(--((D9*'05_PSA_1000'!$N$2:$N$1001-'05_PSA_1000'!$K$2:$K$1001)>0))/1000 -> #NAME? | G9: Dominated | H9: ΔCost > 0; ΔQALY < 0 | I9: =COUNTIFS('05_PSA_1000'!$K$2:$K$1001,">0",'05_PSA_1000'!$N$2:$N$1001,"<0") -> 0 | J9: =I9/1000 -> 0
A10: ='05_PSA_1000'!N6 -> #NAME? | B10: ='05_PSA_1000'!K6 -> #NAME? | D10: 200000000 | E10: =SUMPRODUCT(--((D10*'05_PSA_1000'!$N$2:$N$1001-'05_PSA_1000'!$K$2:$K$1001)>0))/1000 -> #NAME?
A11: ='05_PSA_1000'!N7 -> #NAME? | B11: ='05_PSA_1000'!K7 -> #NAME? | D11: 250000000 | E11: =SUMPRODUCT(--((D11*'05_PSA_1000'!$N$2:$N$1001-'05_PSA_1000'!$K$2:$K$1001)>0))/1000 -> #NAME? | G11: The 1,000 raw coordinates in columns A:B update automatically and are the expected CE-plane data for DeciBridge.
A12: ='05_PSA_1000'!N8 -> #NAME? | B12: ='05_PSA_1000'!K8 -> #NAME? | D12: 300000000 | E12: =SUMPRODUCT(--((D12*'05_PSA_1000'!$N$2:$N$1001-'05_PSA_1000'!$K$2:$K$1001)>0))/1000 -> #NAME? | G12: The quadrant table provides an immediately visible dynamic check even when a spreadsheet viewer does not refresh an XY scatter chart.
A13: ='05_PSA_1000'!N9 -> #NAME? | B13: ='05_PSA_1000'!K9 -> #NAME? | D13: 350000000 | E13: =SUMPRODUCT(--((D13*'05_PSA_1000'!$N$2:$N$1001-'05_PSA_1000'!$K$2:$K$1001)>0))/1000 -> #NAME? | G13: ='01_INPUTS'!B28 -> Dynamic fixed-seed
A14: ='05_PSA_1000'!N10 -> #NAME? | B14: ='05_PSA_1000'!K10 -> #NAME? | D14: 400000000 | E14: =SUMPRODUCT(--((D14*'05_PSA_1000'!$N$2:$N$1001-'05_PSA_1000'!$K$2:$K$1001)>0))/1000 -> #NAME?
A15: ='05_PSA_1000'!N11 -> #NAME? | B15: ='05_PSA_1000'!K11 -> #NAME? | D15: 450000000 | E15: =SUMPRODUCT(--((D15*'05_PSA_1000'!$N$2:$N$1001-'05_PSA_1000'!$K$2:$K$1001)>0))/1000 -> #NAME?
A16: ='05_PSA_1000'!N12 -> #NAME? | B16: ='05_PSA_1000'!K12 -> #NAME? | D16: 500000000 | E16: =SUMPRODUCT(--((D16*'05_PSA_1000'!$N$2:$N$1001-'05_PSA_1000'!$K$2:$K$1001)>0))/1000 -> #NAME?
A17: ='05_PSA_1000'!N13 -> #NAME? | B17: ='05_PSA_1000'!K13 -> #NAME? | D17: 550000000 | E17: =SUMPRODUCT(--((D17*'05_PSA_1000'!$N$2:$N$1001-'05_PSA_1000'!$K$2:$K$1001)>0))/1000 -> #NAME?
A18: ='05_PSA_1000'!N14 -> #NAME? | B18: ='05_PSA_1000'!K14 -> #NAME? | D18: 600000000 | E18: =SUMPRODUCT(--((D18*'05_PSA_1000'!$N$2:$N$1001-'05_PSA_1000'!$K$2:$K$1001)>0))/1000 -> #NAME?
A19: ='05_PSA_1000'!N15 -> #NAME? | B19: ='05_PSA_1000'!K15 -> #NAME? | D19: 650000000 | E19: =SUMPRODUCT(--((D19*'05_PSA_1000'!$N$2:$N$1001-'05_PSA_1000'!$K$2:$K$1001)>0))/1000 -> #NAME?
A20: ='05_PSA_1000'!N16 -> #NAME? | B20: ='05_PSA_1000'!K16 -> #NAME? | D20: 700000000 | E20: =SUMPRODUCT(--((D20*'05_PSA_1000'!$N$2:$N$1001-'05_PSA_1000'!$K$2:$K$1001)>0))/1000 -> #NAME?
A21: ='05_PSA_1000'!N17 -> #NAME? | B21: ='05_PSA_1000'!K17 -> #NAME? | D21: 750000000 | E21: =SUMPRODUCT(--((D21*'05_PSA_1000'!$N$2:$N$1001-'05_PSA_1000'!$K$2:$K$1001)>0))/1000 -> #NAME?
A22: ='05_PSA_1000'!N18 -> #NAME? | B22: ='05_PSA_1000'!K18 -> #NAME? | D22: 800000000 | E22: =SUMPRODUCT(--((D22*'05_PSA_1000'!$N$2:$N$1001-'05_PSA_1000'!$K$2:$K$1001)>0))/1000 -> #NAME?
A23: ='05_PSA_1000'!N19 -> #NAME? | B23: ='05_PSA_1000'!K19 -> #NAME?
A24: ='05_PSA_1000'!N20 -> #NAME? | B24: ='05_PSA_1000'!K20 -> #NAME?
A25: ='05_PSA_1000'!N21 -> #NAME? | B25: ='05_PSA_1000'!K21 -> #NAME?
A26: ='05_PSA_1000'!N22 -> #NAME? | B26: ='05_PSA_1000'!K22 -> #NAME?
A27: ='05_PSA_1000'!N23 -> #NAME? | B27: ='05_PSA_1000'!K23 -> #NAME?
A28: ='05_PSA_1000'!N24 -> #NAME? | B28: ='05_PSA_1000'!K24 -> #NAME?
A29: ='05_PSA_1000'!N25 -> #NAME? | B29: ='05_PSA_1000'!K25 -> #NAME?
A30: ='05_PSA_1000'!N26 -> #NAME? | B30: ='05_PSA_1000'!K26 -> #NAME?
A31: ='05_PSA_1000'!N27 -> #NAME? | B31: ='05_PSA_1000'!K27 -> #NAME?
A32: ='05_PSA_1000'!N28 -> #NAME? | B32: ='05_PSA_1000'!K28 -> #NAME?
A33: ='05_PSA_1000'!N29 -> #NAME? | B33: ='05_PSA_1000'!K29 -> #NAME?
A34: ='05_PSA_1000'!N30 -> #NAME? | B34: ='05_PSA_1000'!K30 -> #NAME?
... A1005: ='05_PSA_1000'!N1001 -> #NAME? | B1005: ='05_PSA_1000'!K1001 -> #NAME?

Sheet 07_PSA_SUMMARY
A1: Probabilistic Sensitivity Analysis Summary | B1: Probabilistic Sensitivity Analysis Summary | C1: Probabilistic Sensitivity Analysis Summary | D1: Probabilistic Sensitivity Analysis Summary | E1: Probabilistic Sensitivity Analysis Summary | F1: Probabilistic Sensitivity Analysis Summary
A2: All values reference the 1,000 fixed-seed PSA rows. | B2: All values reference the 1,000 fixed-seed PSA rows. | C2: All values reference the 1,000 fixed-seed PSA rows. | D2: All values reference the 1,000 fixed-seed PSA rows. | E2: All values reference the 1,000 fixed-seed PSA rows. | F2: All values reference the 1,000 fixed-seed PSA rows.
A4: Metric | B4: Value | C4: Unit | D4: Interpretation
A5: Mean incremental cost | B5: =AVERAGE('05_PSA_1000'!K2:K1001) -> #NAME? | C5: IDR/patient | D5: Mean across PSA
A6: Mean incremental QALY | B6: =AVERAGE('05_PSA_1000'!N2:N1001) -> #NAME? | C6: QALY/patient | D6: Mean across PSA
A7: ICER using mean increments | B7: =B5/B6 -> #NAME? | C7: IDR/QALY | D7: Ratio of means
A8: Mean INB at base WTP | B8: =AVERAGE('05_PSA_1000'!P2:P1001) -> #NAME? | C8: IDR/patient | D8: Positive favors ARNI
A9: Probability cost-effective | B9: =AVERAGE('05_PSA_1000'!Q2:Q1001) -> #NAME? | C9: probability | D9: INB > 0 at base WTP
A10: Probability ARNI dominant | B10: =COUNTIFS('05_PSA_1000'!K2:K1001,"<0",'05_PSA_1000'!N2:N1001,">0")/1000 -> 0 | C10: probability | D10: Lower cost and higher QALY
A11: Probability ARNI dominated | B11: =COUNTIFS('05_PSA_1000'!K2:K1001,">0",'05_PSA_1000'!N2:N1001,"<0")/1000 -> 0 | C11: probability | D11: Higher cost and lower QALY
A12: 2.5th percentile incremental cost | B12: =_xludf.PERCENTILE.INC('05_PSA_1000'!K2:K1001,0.025) -> #NAME? | C12: IDR/patient | D12: PSA percentile
A13: 97.5th percentile incremental cost | B13: =_xludf.PERCENTILE.INC('05_PSA_1000'!K2:K1001,0.975) -> #NAME? | C13: IDR/patient | D13: PSA percentile
A14: Selected WTP | B14: ='01_INPUTS'!B9 -> 85000000 | C14: IDR/QALY | D14: From 01_INPUTS
A17: Interpretation warning | B17: Interpretation warning | C17: Interpretation warning | D17: Interpretation warning | E17: Interpretation warning | F17: Interpretation warning
A18: PSA quantifies parameter uncertainty in this simplified test model only.
A19: The PSA does not address structural uncertainty, omitted mortality, discontinuation, or adverse events.
A20: Do not use the probability cost-effective result for an RS Unud decision until all parameters and model structure are validated.

Sheet 08_ARB_EXTENSION
A1: ARNI versus ARB – Extension Readiness | B1: ARNI versus ARB – Extension Readiness | C1: ARNI versus ARB – Extension Readiness | D1: ARNI versus ARB – Extension Readiness | E1: ARNI versus ARB – Extension Readiness | F1: ARNI versus ARB – Extension Readiness | G1: ARNI versus ARB – Extension Readiness
A2: Clinical data are available, but economic outputs are intentionally blocked until ARB costs are supplied. | B2: Clinical data are available, but economic outputs are intentionally blocked until ARB costs are supplied. | C2: Clinical data are available, but economic outputs are intentionally blocked until ARB costs are supplied. | D2: Clinical data are available, but economic outputs are intentionally blocked until ARB costs are supplied. | E2: Clinical data are available, but economic outputs are intentionally blocked until ARB costs are supplied. | F2: Clinical data are available, but economic outputs are intentionally blocked until ARB costs are supplied. | G2: Clinical data are available, but economic outputs are intentionally blocked until ARB costs are supplied.
A4: Parameter | B4: ARNI | C4: ARB | D4: Unit | E4: Source | F4: Ready? | G4: Required action
A5: Rehospitalization | B5: 0.1316 | C5: 0.2143 | D5: proportion | E5: Casepack | F5: Yes | G5: Can validate clinical import and RR.
A6: Relative risk | B6: 0.614 | D6: RR | E6: Casepack | F6: Yes | G6: Dashboard expected RR = 0.614.
A7: Median LOS | B7: 3 | C7: 5 | D7: days | E7: Casepack | F7: Yes | G7: Dashboard expected difference = −2 days.
A8: Annual medicine cost | B8: 15399360 | D8: IDR/patient-year | E8: ARNI from template; ARB missing | F8: No | G8: Add ARB drug, strength, unit price, and dosing.
A9: HF admission cost | B9: 6889093 | C9: 6889093 | D9: IDR/admission | E9: Casepack proxy | F9: Proxy | G9: Replace with validated local cost for final model.
A10: Stable utility | B10: 0.7 | C10: 0.7 | D10: utility | E10: Illustrative | F10: Test only | G10: Validate using appropriate utility evidence.
A11: QALY loss/admission | B11: 0.1 | C11: 0.1 | D11: QALY/admission | E11: Illustrative | F11: Test only | G11: Validate using appropriate utility evidence.

Sheet 09_DATA_MAP_QC
A1: Data Mapping and Quality-Control Checks | B1: Data Mapping and Quality-Control Checks | C1: Data Mapping and Quality-Control Checks | D1: Data Mapping and Quality-Control Checks | E1: Data Mapping and Quality-Control Checks | F1: Data Mapping and Quality-Control Checks | G1: Data Mapping and Quality-Control Checks | H1: Data Mapping and Quality-Control Checks
A2: Use this sheet to compare dashboard outputs against workbook expected results. | B2: Use this sheet to compare dashboard outputs against workbook expected results. | C2: Use this sheet to compare dashboard outputs against workbook expected results. | D2: Use this sheet to compare dashboard outputs against workbook expected results. | E2: Use this sheet to compare dashboard outputs against workbook expected results. | F2: Use this sheet to compare dashboard outputs against workbook expected results. | G2: Use this sheet to compare dashboard outputs against workbook expected results. | H2: Use this sheet to compare dashboard outputs against workbook expected results.
A4: QC ID | B4: Dashboard field | C4: Expected workbook cell | D4: Expected value | E4: Tolerance | F4: Status | G4: Severity | H4: Notes
A5: QC01 | B5: Total cost ARNI | C5: '02_DETERMINISTIC'!B16 | D5: ='02_DETERMINISTIC'!B16 -> 18499452 | E5: 1 | G5: Critical | H5: IDR rounding tolerance ±1.
A6: QC02 | B6: Total cost ACEI | C6: '02_DETERMINISTIC'!B17 | D6: ='02_DETERMINISTIC'!B17 -> 5199411.1 | E6: 1 | G6: Critical | H6: IDR rounding tolerance ±1.
A7: QC03 | B7: Total QALY ARNI | C7: '02_DETERMINISTIC'!B18 | D7: ='02_DETERMINISTIC'!B18 -> 0.655 | E7: 1e-06 | G7: Critical | H7: Compare unrounded value.
A8: QC04 | B8: Total QALY ACEI | C8: '02_DETERMINISTIC'!B19 | D8: ='02_DETERMINISTIC'!B19 -> 0.62923 | E8: 1e-06 | G8: Critical | H8: Compare unrounded value.
A9: QC05 | B9: Incremental cost | C9: '02_DETERMINISTIC'!B20 | D9: ='02_DETERMINISTIC'!B20 -> 13300041 | E9: 1 | G9: Critical | H9: ARNI minus ACEI.
A10: QC06 | B10: Incremental effectiveness | C10: '02_DETERMINISTIC'!B21 | D10: ='02_DETERMINISTIC'!B21 -> 0.02577 | E10: 1e-06 | G10: Critical | H10: ARNI minus ACEI.
A11: QC07 | B11: ICER | C11: '02_DETERMINISTIC'!B22 | D11: ='02_DETERMINISTIC'!B22 -> 5.1610558e+08 | E11: 10 | G11: Critical | H11: IDR/QALY tolerance ±10.
A12: QC08 | B12: INB | C12: '02_DETERMINISTIC'!B23 | D12: ='02_DETERMINISTIC'!B23 -> -11109591 | E12: 10 | G12: Critical | H12: Selected WTP.
A13: QC09 | B13: BIA low uptake | C13: '03_BIA'!G5 | D13: ='03_BIA'!G5 -> 1.3300041e+08 | E13: 1 | G13: Major | H13: Net annual BIA.
A14: QC10 | B14: BIA medium uptake | C14: '03_BIA'!G6 | D14: ='03_BIA'!G6 -> 3.9900122e+08 | E14: 1 | G14: Major | H14: Net annual BIA.
A15: QC11 | B15: BIA high uptake | C15: '03_BIA'!G7 | D15: ='03_BIA'!G7 -> 6.6500204e+08 | E15: 1 | G15: Major | H15: Net annual BIA.
A16: QC12 | B16: PSA probability cost-effective | C16: '07_PSA_SUMMARY'!B9 | D16: ='07_PSA_SUMMARY'!B9 -> #NAME? | E16: 0.001 | G16: Major | H16: Expected fixed-seed result.
A19: Manual dashboard comparison | B19: Manual dashboard comparison | C19: Manual dashboard comparison | D19: Manual dashboard comparison | E19: Manual dashboard comparison | F19: Manual dashboard comparison | G19: Manual dashboard comparison | H19: Manual dashboard comparison
A20: QC ID | B20: Dashboard actual | C20: Absolute difference | D20: Pass/Fail | E20: Tester | F20: Test date | G20: Dashboard version | H20: Evidence/screenshot
A21: QC01 | C21: =IF(B21="","",ABS(B21-D5)) | D21: =IF(B21="","Not tested",IF(C21<=E5,"PASS","FAIL")) -> Not tested
A22: QC02 | C22: =IF(B22="","",ABS(B22-D6)) | D22: =IF(B22="","Not tested",IF(C22<=E6,"PASS","FAIL")) -> Not tested
A23: QC03 | C23: =IF(B23="","",ABS(B23-D7)) | D23: =IF(B23="","Not tested",IF(C23<=E7,"PASS","FAIL")) -> Not tested
A24: QC04 | C24: =IF(B24="","",ABS(B24-D8)) | D24: =IF(B24="","Not tested",IF(C24<=E8,"PASS","FAIL")) -> Not tested
A25: QC05 | C25: =IF(B25="","",ABS(B25-D9)) | D25: =IF(B25="","Not tested",IF(C25<=E9,"PASS","FAIL")) -> Not tested
A26: QC06 | C26: =IF(B26="","",ABS(B26-D10)) | D26: =IF(B26="","Not tested",IF(C26<=E10,"PASS","FAIL")) -> Not tested
A27: QC07 | C27: =IF(B27="","",ABS(B27-D11)) | D27: =IF(B27="","Not tested",IF(C27<=E11,"PASS","FAIL")) -> Not tested
A28: QC08 | C28: =IF(B28="","",ABS(B28-D12)) | D28: =IF(B28="","Not tested",IF(C28<=E12,"PASS","FAIL")) -> Not tested
A29: QC09 | C29: =IF(B29="","",ABS(B29-D13)) | D29: =IF(B29="","Not tested",IF(C29<=E13,"PASS","FAIL")) -> Not tested
A30: QC10 | C30: =IF(B30="","",ABS(B30-D14)) | D30: =IF(B30="","Not tested",IF(C30<=E14,"PASS","FAIL")) -> Not tested
A31: QC11 | C31: =IF(B31="","",ABS(B31-D15)) | D31: =IF(B31="","Not tested",IF(C31<=E15,"PASS","FAIL")) -> Not tested
A32: QC12 | C32: =IF(B32="","",ABS(B32-D16)) | D32: =IF(B32="","Not tested",IF(C32<=E16,"PASS","FAIL")) -> Not tested
